Workbook
Name nebulae: 'Nebulae & Cluster Sizes'!$A$2:$F$33
Name systems: 'Coordinates Conversion'!$A$2:$D$3177
Name ownership: Systems!$I$2:$AZ$3177

Sheet About
B1: Sarna Unified Cartography Kit (SUCKit aka SUCK)
B2: The kit is comprised of: | C2: Background:
A3: 1) | B3: Systems: indicates system coordinates and faction ownership in select years | C3: BattleTechWiki:System coordinates
A4: 2) | B4: Factions: contains the different factions in BattleTech, their assigned unique ID, colors assigned to them (for mapping purposes), foundation and dissolution years, and the number of systems they posses in a given year | C4: Discussion:
A5: 3) | B5: Pathfinding: jump route calculator based on available data | C5: BattleTechWiki talk:System coordinates
A6: 4) | B6: Coordinates Conversion: contains the raw coordinates from PDF sources and the formula for converting them to the base 2764 map orientation and scale
A7: 5) | B7: Nebulae & Cluster Sizes: contains the raw coordinates from PDF sources and the formula for converting them to the base 2764 map orientation and scale, as well as their scaled heights and widths based on current maps
A8: 6) | B8: Process Write-up: brief description of what went through each task that led to the output that you see before you
A9: 7) | B9: Credits: the people who have contributed to the SUCKit from its early years up to the present
A11: Version | B11: Changes | C11: Notes | D11: Updated by | E11: Sources used for update
A12: 2025.03.03 | B12: 1) Added faction ownership data from Handbook: House Marik 2571 map 2) Added faction ownership data from Handbook: House Liao 2571 map 3) Added faction ownership data from Handbook: House Davion 2571 map 4) Added faction ownership data from Handbook: House Kurita 2571 map 5) Added faction ownership data from Handbook: House Steiner 2571 map 6) Added MOC, OA faction ownership data from Handbook: Major Periphery States 2571 maps 7) Marked cells containing conflicting faction ownership data in Red. Entered best guess in the absence of official ruling 8) Renamed Dark Nebula in Systems sheet to Erit Cluster, using the coordinates of Dark Nebula 9) Restored 3030 faction data from a previous backup due to an overwrite error (still pending verification) 10) Corrected typo on start year of Vesper Marches and Malthus Confederation 11) Added more faction Sarna links | C12: 1) I need a long break 2) If anyone can cite sources and page numbers for start and end year of the various factions, I'd be forever grateful. I'm trying to trace back where I got some of the start years but am unable to find the sources | D12: Volt
A13: 2025.03.02 | B13: 1) Added faction ownership data from Handbook: House Kurita 2319 map 2) Added undiscovered faction ownership data source from Handbook: House Davion 2317 map and Handbook: House Marik 2271 map 3) Added faction ownership data from Handbook: House Steiner 2341 map 4) Renamed Tsamma | D13: Volt
A14: 2025.03.01 | B14: 1) Optimized some formulas in various sheets to reduce loading time 2) Corrected swapped height and width information on nebulae and clusters | D14: Volt
A15: 2025.02.04 | B15: 1) Updated faction ownership of various deep periphery systems based on actual available data (removed ambiguous assumptions) 2) Added faction ownership from Handbook: House Marik 2271 map 3) Added faction ownership from Handbook: House Davion 2317 map 4) Added faction ownerwhip from Handbook: House Liao 2367 map 5) Added Sarna links of factions 6) Updated ownership of affected systems from FS to FCF until 3063 7) Changed Chaos March to Independent from 3057-3068 and removed Chaos March as a faction 8) Added color coding to the faction ownership data. white cells are confirmed ownership data from maps or text, yellow are blank and assumed ownership status 9) Removed SLDF as a faction and restored TH faction ownership in 2783-2786 10) Changed I from Independent to Inhabited | C15: Reread Liberation of Terra vol 2 and corrected a mistake madde in the 2025.01.02 edit. Technically the FedCom ceased to be in 3067 when Yvonne declared the FedCom to be the FedSuns again. I restarted cleanup of the faction ownership data by going through all previous maps (and some sourcebook text I had access to, plus articless on Sarna of course) and decided to mark confirmed faction ownership in white and all assumed or interpolated date in yellow Incorporated updates from House Arano book (missed several faction ownership from maps) and maps from the BattleTech Universe Sourcebook | D15: Volt
A16: 2025.02.03 | B16: 1) Renamed Valencia (Nueva Castile) to Ascua (the star's name) 2) Renamed Rosetta to Ptolemy (the star's name) 3) Added Sarna link for Cielo 4) Major change to scaling formula for increased accuracy, affecting 125 systems, with the most significant impact on systems in the rimward periphery, particularly those in the Aurigan Reach 5) Merged Polybius and Appian 6) Jumps > 30LY in SIPS now appear as purple broken lines instead of solid lines to show viewer that the jump required intermediate jump points to reach the next system | C16: I decide to use statistical tools to modify my scaling and translation formulas. Before, I just used the average of the scales of the reference pairs, now I'm using the Least Squares method (a form of linear regression) to minimize measurement errors. Turns out Appian and Polybius are the same system. Initially thought it was two systems because some of the coordinates of the map from house Arano shifted around, which caused some confusion. | D16: Volt
A17: 2025.02.02 | B17: 1) Reduced the number of named ranges and amended the SIPS accordingly in order to reduce spreadsheet read iterations to further speed it up 2) Optimized SIPS extended jump pathfinding to skip over systems that bring the path farther from the destination if along the way an extended jump would be triggered anyway. Explanation in the Process Write-up sheet 3) Changed >30LY jump to evaluate all valid neighbors that fall within the criteria instead of just selecting the closest one in order to increase pathfinding flexibility. 4) Switched from A* pathfinding to Bidirectional A* pathfinding, reducing runtime by approximately 30% | C17: Okay, so I wasn't supposed to work on the SIPS anymore but I just happened to think of more optimizations to the code. I might design a flowchart (eventually) that better explains how the code works. | D17: Volt
A18: 2025.02.01 | B18: 1) Upgraded the SIPS to include pathfinding visualization. Now, whenever the Find Path button is clicked, a sidebar will appear after a path is found, which will show the entirety of the Inner Sphere and Deep Periphery without any borders, and a blue line that will connect the starting system to the destination system 2) Added SIPS menu bar item that will allow users to draw the map (without a path) and find a path. The menu bar item will appear as soon as the script is authorized by the user. | C18: It took me a couple of tries to get the pathfinding visualization to work, and apparently GAS will automatically deploy the visualization without any additional coding necessary on the file accessing the SIPS library. This might already be the final version of the SIPS as it is already a working tool. I do not know coding well enough to implement faction borders and different system sizes, but if anyone is willing to lend a hand, I'd appreciate it. | D18: Volt
A19: 2025.01.04 | B19: 1) Made minor corrections to Nebula & Clusters Sizes sheet 2) logic changes in SIPS pathfinding to improve performance 3) Deployed the SIPS as a library in Google Apps Script to make updating easier in case others would like to use the same script for other purposes 4) Merged changes from Volt's cleaned-up master copy to the Sarna official copy | C19: Apparently, dynamically searching for neighbors within 30LY is faster than using a cached list , so I eliminated the Neighbors sheet and modified the code to dynamically search for neighbors. | D19: Volt
A20: 2025.01.03 | B20: Completed the SUCKit Integrated Pathfinding Script (SIPS) | C20: After two months of work, the Pathfinding Script finally works. Users can set start and destination points and the script witll always find a path to connect the two systems. By default, the script will find the path with the fewest number of jumps, which also has the shortest total distance. Details on the SIPS can be found in the process write-up sheet. | D20: Volt
A21: 2025.01.02 | B21: 1) Added 3152 faction ownership from ilKhan's Eyes Only 2) Added faction ownership of Dark Nebula 3) Added Star League faction, changed the pre-2780 remote TH systems to SL 4) Added Star League Defense Force faction, changed the post-2780 TH systems to SLDF, and post-2780 remote TH systems to A 5) updated start and end year of some factions 6) removed faction ownership of deep periphery systems after 3095 for those that have not been mentioned since ISP3 | C21: Busy weekend since acquiring a copy of ilKhan's Eyes Only. Did a recheck of various entries, updated old ones and cleaned up some formulas. Because the Terran Hegemony ceased to exist after the Amaris Coup, I changed TH systems to SL and SLDF. All periphery systems after the dissolution of the SL were changed to Abandoned, and the TH worlds were changed to SLDF in 2783, and Independent in 2786 because by this time the Exodus had occurred. | D21: Volt
A22: 2025.01.01 | B22: 1) Added faction tags to systems with duplicate names to better identify them 2) Changed lookup for Pathfinding and distance calculation in Systems sheet from entering ID to entering system name to make the search more user-friendly | C22: I made the system selection based on the system name, made unique by adding faction tags to systems with duplicate names, instead of the system ID. Adding data validation by range also adds autocomplete so it makes typing up names easier | D22: Volt
A23: 2024.12.01 | B23: 1) Added Neighbors sheet in preparation for the SUCKit-Integrated Pathfinding Script (SIPS) 2) Added a Dark Nebula entry in systems to represent Erit Cluster and Camelot Command, both locations found within the nebula so that it can be a starting point or a destination later on once the SIPS is up and running. | C23: Working with ChatGPT (because I have not done any actual coding in over 25 years) to develop a pathfinding tool using Google Apps Script given the data in the SUCKit. But since GAS has a 6-min runtime limit I had to predetermine system neighbors to eliminate a lot of the iterative work. Was able to come up with a working script that would determine and record the system neighbors within 30LY. Initial version took around 70+ seconds to process everything, then I asked ChatGPT to optimize the code and it was able to trim the runtime down to about 10-11 seconds. I'm sure more optimizations can be done to speed up processing but I'll explore that when I have more free time. | D23: Volt
A24: 2024.11.01 | B24: 1) Added dissolution year of Republic of the Sphere 2) updated Sarna links to several systems 3) renamed Sonnia to Rahway and updated link 4) renamed Alpha Eridani to Achernar and updated link | D24: Volt
A25: 2023.06.02 | B25: 1) final cleanup of various sheets, interconnecting their content via formulas 2) changed version numbering to year.month.edit number 3) added pre-SUCKit changelog entries at the bottom of this page | D25: Volt
A26: 2023.06.01 | B26: 1) cleaned up the About page 2) cleaned up conditional formatting related to formula-bearing cells (gray) in various sheets and the distance Column to show Green for systems that are within 30LY and then Yellow going to Red for those beyond 30LY for easy reference 3) fixed some spelling errors 4) turned system size into a formula based on data on Nebulae & Cluster Sizes 5) removed 2271 to 2571, and 3030 | C26: Because of a potential data extraction issue carried over from the 2011.08.01 version of the faction ownership database, it is possible that some systems have been put under a certain affiliation but are actually not officially recognized. This is because faction ownership of systems that were obscured by pdf map borders from the various Handbook PDFs were included. As a result, the years from 2271 to 2571, and 3030 were removed until an updated faction ownership using corrected extraction procedures are retrieved. | D26: Volt
A27: 2023.03.02 | B27: Updated the Sarna Links of Alekseyevka and Badlands Cluster | D27: Volt
A28: 2023.03.01 | B28: 1) Corrected ownership of Rocky from HB:HK map and TtS: Rocky 2) Update the Sarna link of New Galicia | D28: Volt
A29: 2022.08.03 | B29: 1) Updated faction ownership of Crellacor in 3145 2) Updated Gustrell as Faction Capital beginning 3095 3) Updated faction ownership of Tamar Pact, Alyina Mercantile League, Arc-Royal Liberty Coalition and Vesper Marches systems in 3151 4) Changed Year Titles in Systems-Description and Systems sheets for better compatibility with the GUMS | C29: GUMS = Gruese's Ultimate Mapmaking Script, Sarna.net's preferred map generator | D29: Volt
A30: 2022.08.02 | B30: 1) Renamed Rodigo entry to the star's name, Alsace 2) Updated faction ownership of Joppa before 3067 | D30: Volt
A31: 2022.08.01 | B31: 1) Removed 14 systems erroneously included in the 3152 list that shouldn't be present because they are not visible in the maps 2) Swapped height and width of Caliban Nebula | D31: Volt
A32: 2022.07.02 | B32: 1) Coordinates for Cielo extracted and incorporated 2) Added Dalrymple (formerly abandoned Tintavel) | D32: Volt
A33: 2022.07.01 | B33: 1) Qualip marked abandoned in 2864 2) Renamed Kandersteg to Matahari 3) Updated Faction Ownership of Matahari, Gibraltar, Sadurni and Gienah before 2750 4) Extended Scorpion Empire systems Ownership to 3152 5) Updated Faction Ownership of Bolan in 2367 6) Added new system Cielo (Coordinates to follow) 7) Added The Institute (formerly abandoned New Galicia) | D33: Volt
A34: 2022.03.01 | B34: 1) Changed Faction Ownership of Arcturus, Blue Diamond, Kelenfold, Borghese and Kerensky's Vision in 3151 2) Changed Sarna link of Almotacen | D34: Volt
A35: 2022.01.01 | B35: 1) Added faction ownership of systems appearing in Tamar Rising maps 2) updated coordinates of Matteo based on PDF map raw data 3) removed non-canon label of Matteo faction ownership on all periods before 3151 4) added placeholder Sarna link for Matteo 5) added new factions from Tamar Rising | C35: thanks to Hammer from the MegaMek team for sharing their data from mining the content of Tamar Rising. Their file effectively cut the work of the SUCS in half by identifying the faction ownership of the systems that appeared on the maps, allowing us to devote our time to identifying ownership changes, abandoned systems, reappeared and new systems, and coordinates extraction. | D35: Volt
A36: 2021.10.01 | B36: Updated the Sarna link of Dieudonné | C36: special thanks to Nic Jansma | D36: Volt
A37: 2021.09.02 | B37: Renamed the descriptions of 3135, 3145 and 3151 in the Systems-Description sheet | C37: Got lazy and just wrote "Dark Age" before | D37: Volt
A38: 2021.09.01 | B38: Fixed incorrect description in the Systems-Description sheet | C38: Thanks, Revanche! | D38: Volt
A39: 2021.08.02 | B39: Fixed incorrect column labels in the Systems-Description sheet | C39: Thanks, gruese! | D39: Volt
A40: 2021.08.01 | B40: 1) Updated the Sarna links to some systems 2) renamed Alnasi to Gamma Sagittarius for consistency with Sarna.net | C40: 1) thanks, Nic! 2) BTW, Alnasi should have been Alnasl, typo error | D40: Volt
A41: 2021.07.06 | B41: Changed name merge formula in Coordinates Conversion sheet from vlookup to index-match-match | D41: Volt
A42: 2021.07.05 | B42: 1) Changed Farstar's faction ownership from 3085 onwards from CSR to RA 2) Changed colors of some factions where applicable to make them look more distinct on a map 3) Corrected ownership of Promised Land in 2271 | C42: missed this one, CSR and OA merged to form RA in 3083 so there shouldn't be a CSR anymore by 3085 | D42: Volt
A43: 2021.07.04 | B43: 1) Simplified the formula for counting the number of systems per faction per year in the Factions sheet 2) Changed the distance calculation formula from vlookup to index-match-match to make the lookup more flexible, then used the named ranges 3) Added conditional formatting to reflect faction color of a system at a certain year (WIP) | C43: I don't know what I was thinking, using sumproduct and len on a formula I could have simply used countif. Well, at least that's that. I hope the shorter formula makes the sheet tally faster index-match is supposed to be more efficient than vlookup, and it doesn't break when the number of columns shift because their lookup is based on the column header instead of a static column number | D43: Volt
A44: 2021.07.03 | B44: Tagged Kanata as a Major Capital in 2783 and 2786 | C44: wow, i wonder what else I've missed over the years... would be nice to have fact checkers | D44: Volt
A45: 2021.07.02 | B45: 1) Corrected Faction ownership of Apinzel in 2786 2) Changed the date that Erin was renamed to Von Strang's World from 2830+ to 2786+ | D45: Volt
A46: 2021.07.01 | B46: 1) Added Finmark Free Republic Faction 2) Changed faction color of OA to match Inner Sphere at War color | D46: Volt
A47: 2021.06.04 | B47: Changed lookup formulas from vlookup to index-match to speed up processing | C47: no change in the data, just improving the formulas | D47: Volt
A48: 2021.06.03 | B48: 1) Changed formula for scaling maps to the base map, affecting the coordinates of 123 systems 2) added a Process Write-up sheet to explain the process done to build the SUCK | C48: Tweaked the formula for higher accuracy | D48: Volt
A49: 2021.06.02 | B49: 1) created formula to display name of system in Coordinates Conversion sheet as referenced from Systems tab 2) revised formulas in Coordinates Conversion sheet for error handling and missing reference coordinates 3) renamed column headers in Coordinates Conversion sheet 4) added placeholder data for Matteo 5) changed (A) faction tag for Apocryphal to (X) to mean Non-Canon 6) added alternate names for Baggville and Stonarboi based on the information from Gideon on an upcoming sourcebook 7) Corrected Faction ownership of Gibraltar, Lepaterique, and Atzenbrugg in 3151 8) Corrected Faction ownership of Alhena in 3135 9) Corrected Scorpion Empire Faction ID 10) Removed Scorpion Empire Faction Affiliation in 3151 because we have no source | C49: minor edit to link data between sheets to improve QoL for future users changed names of the reference ID X and Y to indicate that the references should be based on Origin, North, South, East and West-most systems for scaling purposes added Matteo in preparation for the new sourcebook, but marked faction ownership as non-canon for now, with coordinates based on the data given by Gideon in the Sarna.net discord server and the Sarna article on Non-Canon as the link technically speaking, all apocryphal fall under non-canon, but not all non-canon are apocryphal (apocryphal being a subset of non-canon) so I changed the reference accordingly | D49: Volt
A50: 2021.06.01 | B50: 1) Updated the formulas for distance calculations in the Systems sheet 2) incorporated the coordinates conversion sheets into the SUCK 3) Updated the Nebulae sheet to include the raw data and calculations | C50: added a text lookup to display the name(s) of the system with the selected ID number, and added error handling if the ID is left blank instead of having to externally reference a different file, I decided to incorporate it as an extra sheet here so that everything is in one place, making it easier to pass the torch later on | D50: Volt
A51: 2021.04.01 | B51: Added alternate name for Heiligendreuz | D51: Volt
A52: 2021.01.01 | B52: Marked Tukayyid as Undiscovered (unsettled) in 2367 from Battle of Tukayyid campaign book | D52: Volt
A53: 2020.10.02 | B53: Added 7 new systems from Operational Turning Points: Hanseatic Crusade | C53: big shout out to Dmon! | D53: Volt
A54: 2020.10.01 | B54: Renamed Götterdämmerung and updated Sarna link | C54: Included the tréma in the spelling in accordance with consensus from Sarna editors | D54: Volt
A55: 2020.09.01 | B55: 1) Added system Eliat from House Arano book 2) Updated Systems and Factions sheet formulas to accommodate inserted systems 3) Updated Faction Ownership of Kaumberg, Braunschweig and Valencia from Touring The Stars | C55: thanks to Hobbes over at Sarna.net for discovering this system that we overlooked | D55: Volt
A56: 2020.08.01 | B56: 1) Corrected Faction tag of Apocryphal System to be consistent with that of Hidden Systems 2) Corrected Sum Ranges on Factions Sheet 3) Added Total Inhabited on Factions Sheet 4) Added background colors to Major House, Abandoned, Disputed and Undiscovered systems in Faction Sheet | C56: while composing an email to Bad_Syntax, I noticed some of the numbers on the Factions tab didn't add up. A short investigation uncovered an error in tagging that prevented one system from showing up on the Factions table. After correcting it, I realized I wanted to quickly see how how many inhabited systems existed each year. | D56: Volt
A57: 2020.05.01 | B57: 1) Edited alternate name entry of Rigil Kentarus 2) Edited alternate name entry of Commonwealth Mining Outpost 26 | C57: Data updated from the new Touring the Stars books | D57: Volt
A58: 2020.04.02 | B58: Updated Sarna link of Galatia | D58: Volt
A59: 2020.04.01 | B59: Updated Sarna link of several systems | C59: Frabby changed the addresses by taking away the roman numerals, thereby referencing the system in the article instead of the planet | D59: Volt
A60: 2020.03.02 | B60: Updated Sarna link of Van Diemen | D60: Volt
A61: 2020.03.01 | B61: Updated Sarna links of several systems | C61: Frabby changed the addresses by taking away the roman numerals, thereby referencing the system in the article instead of the planet | D61: Volt
A62: 2020.02.02 | B62: Fixed Sarna links of Trent and Juniper | D62: Volt
A63: 2020.02.01 | B63: Updated the Sarna link of Santander | D63: Volt
A64: 2020.01.04 | B64: Fixed Aquila Rift spelling | D64: Volt
A65: 2020.01.03 | B65: Algol, Alrescha, Buchlau, Kansu, and New Hessen were all incorrectly tagged as Major Capitals in 3151, fixed | D65: Volt
A66: 2020.01.02 | B66: Renamed Monument to Man to SVSC A0V.4900 | C66: In keeping with using the SUCK standard notation of referencing an entry with the system name | D66: Volt
A67: 2020.01.01 | B67: Updated Sarna link of Cavanaugh, Trent and Homer | C67: Thanks, Nic Jansma (of Sarna.net fame) | D67: Volt
A68: 2019.12.04 | B68: Made Brinton TC from 2864 to 3079 | C68: Turns out, Brinton wasn't lost during the 2nd Succession War, it just got quarantined but was still recognized as a TC system but was taken out of ComStar maps, so I reflected that affiliation | D68: Volt
A69: 2019.12.03 | B69: Changed Regis Roost to a hidden system in 3025 | C69: info from Touring the Stars: Regis Roost | D69: Volt
A70: 2019.12.02 | B70: Corrected HEX values of faction colors | C70: thanks to gruese for pointing out that some hex values were wrong, turns out over half the hex values did not match the cell colors they were supposed to represent | D70: Volt
A71: 2019.12.01 | B71: 1) removed duplicate Aurigan Directorate faction in Factions tab 2) fixed some typos | C71: some years-long typos and a single instance of illegal faction cloning have been found by lastjedi, thanks again! | D71: Volt
A72: 2019.10.01 | B72: Changed distance formula to reference ID instead of system name | C72: distances for systems with duplicate names are resolved incorrectly so I had to reference the ID instead of the name. Should have seen that problem sooner in the 9.Sep.19 change | D72: Volt
A73: 2019.09.02 | B73: 1) Added the Sarna link for the last 7 systems 2) reduced precision of height and width of clusters from 4 to 3 decimal places | C73: 1) I made the article pages but they're just stubs, so the only thing in them as of this writing are the coordinates 2) do we really need to be that accurate? What's the difference between 0.0001 and 0.00001LY at this scale anyway, right? | D73: Volt
A74: 2019.09.01 | B74: 1) changed Status Column to Primary ID 2) added apocryphal system as (A) | C74: 1) I decided to add a Primary ID key to the entries to make each one unique, so I don't have to have the differentiator part of the system's name 2) Saggina is a mapped system but remain apocryphal because it's not within the visible borders of the map. In order to see it, you have to remove the border layer on the map page | D74: Volt
A75: 2019.08.02 | B75: 1) changed faction color in Factions sheet from RGB to HEX 2) deleted the #class column 3) renamed columns in Systems and Factions sheet | C75: thought i'd reduce the number of columns by putting the data in one cell | D75: Volt
A76: 2019.08.01 | B76: 1) changed entry of Aurigan Coalition systems from AC to AuC (AC is already used, although no actual systems fall under that faction) 2) changed 20.Jun.19 4) entry from AC to AuC | D76: Volt
A77: 2019.07.01 | B77: 1) adjusted syntax for renames and multiple planets 2) dropped old spelling of names | C77: systems with multiple planets have commas separating the multiple planets (ex: Niops) systems with renames or alternate names have slash separating the names (ex: Carver) removed the old spelling of system names from alternate names since they won't be used moving forward | D77: Volt
A78: 2019.06.02 | B78: 1) Renamed Chandan entry to Chaadan to reflect errata report response from official forums 2) added Adrian Gideon to the credits section for this contribution 3) deep periphery systems discovered by IE made Undiscovered before IE's formation in 2974 4) changed affiliation of some systems from IE to I unless specifically stated in sourcebooks to be under IE's control/administration | C78: 1) so now the original name was Chaadan, then became Chadan and then Chandan as a nod to the numerous errata and naming inconsistencies from HBS (quite amusing, really) 2) for the first time EVER since the SUCK was created, we finally have one year with 100% faction affiliation defined (2765) | D78: Volt
A79: 2019.06.01 | B79: 1) Updated coordinates of systems introduced in House Arano book 2) Added seven new systems from House Arano book 3) Created Aurigan Directorate and Aurigan Coalition Factions 4) changed affiliation of 22 AuC systems in 3025 | C79: 1) Alamagordo does not appear in the maps 2) Chandan is incorrectly spelled Chaadan and Chadan in two maps 3) Regis Roost is missing in the 3022 map 4) El Giza erroneously appears in the 3022 map, this should be Alamagordo so I used those coordinates | D79: Volt
A80: 2019.04.01 | B80: Updated affiliation of McEvans' Sacrifice based on OTP: Fronc Reaches | D80: Volt
A81: 2019.03.02 | B81: 1) fixed a typo 2) removed the apocryphal names of the alleged hidden WoB systems | D81: Volt
A82: 2019.03.01 | B82: 1) changed status of Saggina to Apocryphal 2) indicated source maps for various years in Systems-Description sheet | D82: Volt
A83: 2019.02.07 | B83: 1) fixed some hyperlink issues 2) marked several hidden systems as (H) 3) changed the 2 apocryphal/non-canon WoB hidden worlds from CS(H) and WB(H) to A | C83: Since we never really got official confirmation of two WoB hidden systems, I've restored the "Abandoned" tag to those systems instead of marking them as hidden | D83: Volt
A84: 2019.02.06 | B84: more typo corrections | D84: Volt
A85: 2019.02.05 | B85: typo error correction | C85: thanks for the find, gruese! | D85: Volt
A86: 2019.02.04 | B86: Added a sheet with a short description of each column for the Systems Sheet | D86: Volt
A87: 2019.02.03 | B87: Marked several hidden systems as (H) | D87: Volt
A88: 2019.02.02 | B88: Marked Sol [Terra] as a Faction Capital | C88: dunno how i missed that out on most of its entries | D88: Volt
A89: 2019.02.01 | B89: 1) changed the designation of the Hidden ComStar/Word of Blake systems from CS/WB to CS(H)/WB(H) to indicate their hidden nature 2) applied formula used in counting disputed systems in the Factions Tab to work with the Hidden Systems | C89: Map makers can make use of the (H) tag to exclude those systems in border generation algorithms so they do not exert any influence in the surrounding areas | D89: Volt
A90: 2019.01.03 | B90: changed format of alternate names for Tabit, Hope and Carver as requested | D90: Volt
A91: 2019.01.02 | B91: added information from Touring the Stars: Sherwood | C91: apparently Sherwood was an Independent colony from 2415 | D91: Volt
A92: 2019.01.01 | B92: added information from some Touring the Stars books that have been generously lent by contributors | C92: The copies sent to me have since been deleted after the required information has been extracted. Much thanks to you guys, rest assured I am not in the habit of sharing paid property. | D92: Volt
A93: 2018.12.02 | B93: changed cluster sizes from total height and total width to x- and y-axis dimensions (radius, if the cluster is a circle) | C93: basically i just divided the total height and total width by 2 in order to get the major axis and minor axis values of the ellipse shape that will represent the cluster | D93: Volt
A94: 2018.12.01 | B94: 1) changed cluster scale to cluster size 2) defined factions laying claim to disputed systems | C94: encountered a problem in using a variable scale to define the size of a cluster so I applied the same method in determining the size of a nebula. Having a fixed size instead of an adjustable size based on a scale makes the cluster cover the same space regardless of he size of system icons if one were to generate maps. to give added flavor to disputed systems, I indicated what factions contested the territory, allowing map makers to make more dynamic borders taking disputed systems into account | D94: Volt
A95: 2018.11.01 | B95: Added column for system scale and rotation | C95: as requested by gruese, i've added an x,y,r scale property to each system for map makers to be able to apply variable system sizes particularly on clusters. The properties are X-scale, Y-scale and rotation. The base scale is the default length and width of an ordinary planetary system entry. The rotation will be used if the cluster will exhibit a non-circular (ie elliptical) appearance | D95: Volt
A96: 2018.09.02 | B96: corrected the wrong link | C96: *facepalm* when you want to get things done right... | D96: Volt
A97: 2018.09.01 | B97: added last missing sarna link | C97: thanks to BrokenMnemonic for generating the article for Union_of Samoyedic Colonies | D97: Volt
A98: 2018.08.05 | B98: 1) added links to four newly created article pages on Sarna 2) added year 3151 from Shattered Sphere with affiliations 3) removed assumed affiliations beyond 3095 for Deep Periphery systems and others 4) extended affiliation of Transfer Facility 4 up to 3095, changed from ComStar to Independent 5) added Aurigan Directorate as a Faction 6) removed Khwarazm Empire as a Faction 7) added founding year of Interstellar Expeditions 8) added dissolution year for Regulan Fiefs 9) added dissolution year for Rim Collection 10) added Timbuktu Collective as a Faction 11) various other changes in affiliation of other systems based on actual sources | C98: only one missing link to go just got my copy of Shattered Sphere, there's a two-page 3151 map so anyone who doesn't want any spoilers better not look at the new column | D98: Volt
A99: 2018.08.04 | B99: 1) added newly created article page links (only 5 left) | C99: kudos to Revanche for creating the over thirty missing articles for the new systems from Second Succession War and Interstellar Expeditions 3 | D99: Volt
A100: 2018.08.03 | B100: no changes, just some thoughts ---> | C100: I had failed to note in the 12.Apr.18 update that I had changed the coordinates of the 16 systems from the BattleTech game. Instead of interpolating from the Kickstarter raster map I had taken the coordinates from in-game that Justin Kase provided and scaled those raw coordinates against the standard that SUCK uses (2764 map from FM: SLDF) using the same method used to consolidate all other maps to that base. The shift from the in-game coordinates is a mere 0.015% (<0.1 LY) on the X axis and 0.008% (-0.01) on the Y axis, so that's really barely visible to the naked eye when printed out at 1 LY = 1 pixel scale | D100: Volt
A101: 2018.08.02 | B101: 1) fixed spelling errors 2) added newly created article page links (thanks Rev) | D101: Volt
...

Sheet Systems Sheet Description
A1: Column | B1: Title | C1: Description
A2: =iferror(right(left(address(1,match($B2,Systems!$2:$2,)),2),1),"") -> A | B2: {=transpose(Systems!$2:$2)} -> systemId | C2: unique system ID number (because some systems have duplicate names)
A3: =iferror(right(left(address(1,match($B3,Systems!$2:$2,)),2),1),"") -> B | B3: systemName | C3: Name of the System
A4: =iferror(right(left(address(1,match($B4,Systems!$2:$2,)),2),1),"") -> C | B4: alternateName | C4: Alternate names of the system, name changes (with year), and/or notable worlds within the system
A5: =iferror(right(left(address(1,match($B5,Systems!$2:$2,)),2),1),"") -> D | B5: x | C5: X-ordinate for mapping purposes as extracted from official maps
A6: =iferror(right(left(address(1,match($B6,Systems!$2:$2,)),2),1),"") -> E | B6: y | C6: y-ordinate for mapping purposes as extracted from official maps
A7: =iferror(right(left(address(1,match($B7,Systems!$2:$2,)),2),1),"") -> F | B7: size | C7: reference size (in LY) of a system/cluster for mapping purposes, [width,height,rotation]. Widths and heights are from center to edge, not edge to edge
A8: =iferror(right(left(address(1,match($B8,Systems!$2:$2,)),2),1),"") -> G | B8: sarnaLink | C8: URL of the entry in www.sarna.net
A9: =iferror(right(left(address(1,match($B9,Systems!$2:$2,)),2),1),"") -> H | B9: distance (LY) | C9: based on the coordinates, the linear distance of the system from a reference point indicated in cell H1 (Sol by default)
B10: 2271 | C10: Free Worlds League Founding | D10: [35019] Handbook: House Marik
B11: 2317 | C11: Federated Suns Founding | D11: [35024] Handbook: House Davion
B12: 2319 | C12: Draconis Combine Founding | D12: [35205] Handbook: House Kurita
B13: 2341 | C13: Lyran Commonwealth Founding | D13: [35001] Handbook: House Steiner
B14: 2366 | C14: Capellan Confederation Founding | D14: [35204] Handbook: House Liao
B15: 2571 | C15: Star League Founding | D15: [35019] Handbook: House Marik [35204] Handbook: House Liao [35024] Handbook: House Davion [35205] Handbook: House Kurita [35001] Handbook: House Steiner [35203] Handbook: Major Periphery States
B16: 2596 | C16: End of Reunification War | D16: [35231] Historical: Reunification War
B17: 2750 | C17: Beginning of the Fall of the Star League | D17: [35222] Era Report: 2750
B18: 2765 | C18: Eve of the Amaris Coup | D18: [35232] Historical: Liberation of Terra volume 1 [35SN501] House Arano: The Aurigan Coalition [35702] BattleTech Universe
B19: 2767 | C19: Amaris Empire | D19: 2765 map with the core TH worlds shifted to AE because of the Coup
B20: 2783 | C20: Great House Annexations of the remnants of the Terran Hegemony | D20: [35233] Historical: Liberation of Terra volume 2
B21: 2786 | C21: Start of 1st Succession War & Settlement of Pentagon | D21: [35230] Historical: Operation Klondike [35233] Historical: Liberation of Terra volume 2 [35702] BattleTech Universe
... B26: 3025 | C26: End of 3rd Succession War | D26: Inner Sphere at War 3025 PDF map [35SN501] House Arano: The Aurigan Coalition [35702] BattleTech Universe
B27: 3030 | C27: End of 4th Succession War
B28: 3040 | C28: End of War of 3039 | D28: [35014] Historical: War of 3039
B29: 3049 | C29: Operation Revival: Periphery Action | D29: [35230] Era Report: 3052
B30: 3050a | C30: Operation Revival: Wave 1 | D30: [35230] Era Report: 3052
B31: 3050b | C31: Operation Revival: Wave 2 | D31: [35230] Era Report: 3052
B32: 3050c | C32: Operation Revival: Wave 3 | D32: [35230] Era Report: 3052
B33: 3051 | C33: Operation Revival: Wave 4 / Year of Peace | D33: [35230] Era Report: 3052
B34: 3052 | C34: Operation Revival: Wave 5 / End of Operation Revival | D34: [35230] Era Report: 3052
B35: 3057 | C35: Start of Operation Guerrero | D35: [35221] Era Report: 3062, but reflecting the formation of the Lyran Alliance while keeping the FedCom march divisions
B36: 3058 | C36: End of Operation Guerrero | D36: [35221] Era Report: 3062 reflecting the formation of the Chaos March, and Lyran Alliance having the Provincial divisions
B37: 3059a | C37: Operation Bulldog: Wave 1 | D37: [35221] Era Report: 3062
B38: 3059b | C38: Operation Bulldog: Wave 2 | D38: [35221] Era Report: 3062
B39: 3059c | C39: Operation Bulldog: Wave 3 | D39: [35221] Era Report: 3062
B40: 3059d | C40: Operation Bulldog: Wave 4 | D40: [35221] Era Report: 3062
B41: 3063 | C41: Start of FC Civil War | D41: [35221] Era Report: 3062
B42: 3067 | C42: End of FC Civil War | D42: [35307] Jihad: Final Reckoning
B43: 3068 | C43: Start of WB Jihad | D43: 3067 map with the WoB Protectorate
B44: 3075 | C44: Middle of the WoB Jihad | D44: [35303] Jihad Secrets: The Blake Documents
B45: 3079 | C45: Waning years of the WoB Jihad | D45: [35FR001] Field Report: CCAF [35FR002] Field Report: DCMS [35FR003] Field Report: AFFS [35FR004] Field Report: FWLM [35FR005] Field Report: LAAF [35FR006] Field Report: Periphery [35FR007] Field Report: The Clans
B46: 3081 | C46: End of WoB Jihad | D46: [35307] Jihad: Final Reckoning
B47: 3085 | C47: End of Wars of Reaving | D47: [35221] Field Manual: 3085 [35306] The Wars of Reaving
B48: 3095 | C48: Republic of the Sphere | D48: [35221] Field Manual: 3085 [30308] Interstellar Players 3: Interstellar Expeditions
B49: 3130 | C49: Devlin Stone's Retirement | D49: [35ED003] Era Digest: Dark Age
B50: 3135 | C50: Fortress Republic | D50: [35223] Era Report: 3145
B51: 3145 | C51: Return of Devlin Stone | D51: [35223] Era Report: 3145 [35P025] Operational Turning Points: Hanseatic Crusade
B52: 3151 | C52: IlClan Trial | D52: [35900] Shattered Fortress
B53: 3152 | C53: IlClan Era | D53: [35902] Tamar Rising [25903] Empire Alone [35904] Dominions Divided [35905] IlKhan's Eyes Only

Sheet Systems
C1: Systems Count : | D1: =COUNTA(B3:B3178) -> 3175 | F1: Reference System : | G1: Sol [Terra, Luna, Mars] | H1: {=INDEX(systems,MATCH(G1,INDEX(systems,0,2),),1)} -> 2370 | I1: =counta(I3:I3178)/$D$1 -> 0.64724409 | J1: =counta(J3:J3178)/$D$1 -> 0.62834646 | K1: =counta(K3:K3178)/$D$1 -> 0.64944882 | L1: =counta(L3:L3178)/$D$1 -> 0.59370079 | M1: =counta(M3:M3178)/$D$1 -> 0.64314961 | N1: =counta(N3:N3178)/$D$1 -> 0.90519685 | O1: =counta(O3:O3178)/$D$1 -> 0.52850394 | P1: =counta(P3:P3178)/$D$1 -> 0.99338583 | ... AZ1: =counta(AZ3:AZ3178)/$D$1 -> 0.95086614
A2: systemId | B2: systemName | C2: alternateName | D2: x | E2: y | F2: size | G2: sarnaLink | H2: distance (LY) | I2: 2271 | J2: 2317 | K2: 2319 | L2: 2341 | M2: 2366 | N2: 2571 | O2: 2596 | P2: 2750 | Q2: 2765 | R2: 2767 | S2: 2783 | T2: 2786 | U2: 2821 | V2: 2822 | W2: 2830 | X2: 2864 | Y2: 3025 | Z2: 3030 | AA2: 3040 | AB2: 3049 | AC2: 3050a | AD2: 3050b | AE2: 3050c | AF2: 3051 | AG2: 3052 | AH2: 3057 | AI2: 3058 | AJ2: 3059a | AK2: 3059b | AL2: 3059c | AM2: 3059d | AN2: 3063 | AO2: 3067 | AP2: 3068 | AQ2: 3075 | AR2: 3079 | AS2: 3081 | AT2: 3085 | AU2: 3095 | AV2: 3130 | AW2: 3135 | AX2: 3145 | AY2: 3151 | AZ2: 3152
A3: 1 | B3: A Place | D3: {=index(systems,match($A3,INDEX(systems,0,1),),3)} -> -123.764 | E3: {=index(systems,match($A3,INDEX(systems,0,1),),4)} -> 272.182 | F3: =IFERROR(__xludf.DUMMYFUNCTION("let(row, match($B3&if($C3<>"""","" [""&$C3&""]"",""""),index(nebulae,,2),0),join("","",iferror(round(index(nebulae,row,5)/2,3),1),iferror(round(index(nebulae,row,6)/2,3),1),0))"),"1,1,0") -> 1,1,0 | G3: https://www.sarna.net/wiki/A_Place | H3: {=let(systemId,match(A3,index(systems,0,1),),refSystemId,match($H$1,index(systems,0,1),),x,index(systems,systemId,3),y,index(systems,systemId,4),refX,index(systems,refSystemId,3),refY,index(systems,refSystemId,4),round(sqrt((x-refX)^2+(y-refY)^2),3))} -> 298.999 | I3: U | J3: U | K3: U | L3: U | M3: U | N3: U | P3: LC,Tamar Pact,Tamar Domains | Q3: LC,Tamar Pact,Tamar Domains | R3: LC,Tamar Pact,Tamar Domains | S3: LC,Tamar Pact,Tamar Domains | T3: LC,Tamar Pact,Tamar Domains | U3: LC,Tamar Pact,Tamar Domains | V3: LC,Tamar Pact,Tamar Domains | W3: LC,Tamar Pact,Tamar Domains | X3: LC,Tamar Pact,Tamar Domains | Y3: LC,Tamar Pact,Tamar Domains | Z3: LC,Tamar Pact,Tamar Domains | AA3: FCL,Tamar March,Benfled Operational Area,Region 2 | AB3: FCL,Tamar March,Benfled Operational Area,Region 2 | AC3: FCL,Tamar March,Benfled Operational Area,Region 2 | AD3: FCL,Tamar March,Benfled Operational Area,Region 2 | AE3: FCL,Tamar March,Benfled Operational Area,Region 2 | AF3: FCL,Tamar March,Benfled Operational Area,Region 2 | AG3: FCL,Tamar March,Pandora Operational Area,Region 1 | AH3: LA,Tamar March,Pandora Operational Area,Region 1 | AI3: LA,Donegal Province,Pandora Theater,Arc-Royal Defense Cordon | AJ3: LA,Donegal Province,Pandora Theater,Arc-Royal Defense Cordon | AK3: LA,Donegal Province,Pandora Theater,Arc-Royal Defense Cordon | AL3: LA,Donegal Province,Pandora Theater,Arc-Royal Defense Cordon | AM3: LA,Donegal Province,Pandora Theater,Arc-Royal Defense Cordon | AN3: LA,Donegal Province,Pandora Theater,Arc-Royal Defense Cordon | AO3: LA,Arc-Royal Theater | AP3: LA,Arc-Royal Theater | AQ3: LA,Arc-Royal Theater | AR3: LA,Arc-Royal Theater | AS3: LA,Arc-Royal Theater | AT3: LC,Arc-Royal Theater | AU3: LC,Arc-Royal Theater | AV3: D(LC,CJF) | AW3: D(LC,CJF) | AX3: CJF | AY3: CJF | AZ3: I
A4: 2 | B4: Aalzorg | D4: {=index(systems,match($A4,INDEX(systems,0,1),),3)} -> 583.881 | E4: {=index(systems,match($A4,INDEX(systems,0,1),),4)} -> 256.931 | F4: =IFERROR(__xludf.DUMMYFUNCTION("let(row, match($B4&if($C4<>"""","" [""&$C4&""]"",""""),index(nebulae,,2),0),join("","",iferror(round(index(nebulae,row,5)/2,3),1),iferror(round(index(nebulae,row,6)/2,3),1),0))"),"1,1,0") -> 1,1,0 | G4: https://www.sarna.net/wiki/Aalzorg | H4: {=let(systemId,match(A4,index(systems,0,1),),refSystemId,match($H$1,index(systems,0,1),),x,index(systems,systemId,3),y,index(systems,systemId,4),refX,index(systems,refSystemId,3),refY,index(systems,refSystemId,4),round(sqrt((x-refX)^2+(y-refY)^2),3))} -> 637.911 | I4: U | J4: U | K4: U | L4: U | M4: U | N4: U | P4: OA,Traders Domain | Q4: OA,Traders Domain | R4: OA,Traders Domain | S4: OA,Traders Domain | T4: OA,Traders Domain | U4: A | V4: A | W4: A | X4: A | Y4: A | Z4: A | AA4: A | AB4: A | AC4: A | AD4: A | AE4: A | AF4: A | AG4: A | AH4: A | AI4: A | AJ4: A | AK4: A | AL4: A | AM4: A | AN4: A | AO4: A | AP4: A | AQ4: A | AR4: A | AS4: A | AT4: A | AU4: A | AV4: A | AW4: A | AX4: A | AY4: A | AZ4: OW,Traders Domain
A5: 3 | B5: Abadan | D5: {=index(systems,match($A5,INDEX(systems,0,1),),3)} -> -70.319 | E5: {=index(systems,match($A5,INDEX(systems,0,1),),4)} -> -95.949 | F5: =IFERROR(__xludf.DUMMYFUNCTION("let(row, match($B5&if($C5<>"""","" [""&$C5&""]"",""""),index(nebulae,,2),0),join("","",iferror(round(index(nebulae,row,5)/2,3),1),iferror(round(index(nebulae,row,6)/2,3),1),0))"),"1,1,0") -> 1,1,0 | G5: https://www.sarna.net/wiki/Abadan | H5: {=let(systemId,match(A5,index(systems,0,1),),refSystemId,match($H$1,index(systems,0,1),),x,index(systems,systemId,3),y,index(systems,systemId,4),refX,index(systems,refSystemId,3),refY,index(systems,refSystemId,4),round(sqrt((x-refX)^2+(y-refY)^2),3))} -> 118.958 | I5: MCM | J5: FWL,Marik Commonwealth | K5: FWL,Marik Commonwealth | L5: FWL,Marik Commonwealth | M5: FWL,Marik Commonwealth | N5: FWL,Marik Commonwealth | O5: FWL,Marik Commonwealth | P5: FWL,Marik Commonwealth | Q5: FWL,Marik Commonwealth | R5: FWL,Marik Commonwealth | S5: FWL,Marik Commonwealth | T5: FWL,Marik Commonwealth | U5: FWL,Marik Commonwealth | V5: FWL,Marik Commonwealth | W5: FWL,Marik Commonwealth | X5: FWL,Marik Commonwealth | Y5: FWL,Marik Commonwealth | Z5: FWL,Marik Commonwealth | AA5: FWL,Marik Commonwealth | AB5: FWL,Marik Commonwealth | AC5: FWL,Marik Commonwealth | AD5: FWL,Marik Commonwealth | AE5: FWL,Marik Commonwealth | AF5: FWL,Marik Commonwealth | AG5: FWL,Marik Commonwealth | AH5: FWL,Marik Commonwealth | AI5: FWL,Marik Commonwealth | AJ5: FWL,Marik Commonwealth | AK5: FWL,Marik Commonwealth | AL5: FWL,Marik Commonwealth | AM5: FWL,Marik Commonwealth | AN5: FWL,Marik Commonwealth | AO5: FWL,Marik Commonwealth | AP5: FWL,Marik Commonwealth | AQ5: FWL,Marik Commonwealth | AR5: MCM | AS5: MCM | AT5: RS,Prefecture VII | AU5: RS,Prefecture VII | AV5: RS,Prefecture VII | AW5: I | AX5: FWL,Clan Protectorate | AY5: FWL,Clan Protectorate | AZ5: FWL,Clan Protectorate
A6: 4 | B6: Abagnar | D6: {=index(systems,match($A6,INDEX(systems,0,1),),3)} -> 380.231 | E6: {=index(systems,match($A6,INDEX(systems,0,1),),4)} -> 314.823 | F6: =IFERROR(__xludf.DUMMYFUNCTION("let(row, match($B6&if($C6<>"""","" [""&$C6&""]"",""""),index(nebulae,,2),0),join("","",iferror(round(index(nebulae,row,5)/2,3),1),iferror(round(index(nebulae,row,6)/2,3),1),0))"),"1,1,0") -> 1,1,0 | G6: https://www.sarna.net/wiki/Abagnar | H6: {=let(systemId,match(A6,index(systems,0,1),),refSystemId,match($H$1,index(systems,0,1),),x,index(systems,systemId,3),y,index(systems,systemId,4),refX,index(systems,refSystemId,3),refY,index(systems,refSystemId,4),round(sqrt((x-refX)^2+(y-refY)^2),3))} -> 493.649 | I6: U | J6: U | K6: U | L6: U | M6: U | N6: U | P6: DC,Pesht Military District,Ningxia Prefecture | Q6: DC,Pesht Military District,Ningxia Prefecture | R6: DC,Pesht Military District,Ningxia Prefecture | S6: DC,Pesht Military District,Ningxia Prefecture | T6: DC,Pesht Military District,Ningxia Prefecture | U6: DC,Pesht Military District,Ningxia Prefecture | V6: DC,Pesht Military District,Ningxia Prefecture | W6: DC,Pesht Military District,Ningxia Prefecture | X6: DC,Pesht Military District,Ningxia Prefecture | Y6: DC,Pesht Military District,Ningxia Prefecture | Z6: DC,Pesht Military District,Ningxia Prefecture | AA6: DC,Pesht Military District,Ningxia Prefecture | AB6: DC,Pesht Military District,Ningxia Prefecture | AC6: DC,Pesht Military District,Ningxia Prefecture | AD6: DC,Pesht Military District,Ningxia Prefecture | AE6: DC,Pesht Military District,Ningxia Prefecture | AF6: DC,Pesht Military District,Ningxia Prefecture | AG6: DC,Pesht Military District,Ningxia Prefecture | AH6: DC,Pesht Military District,Ningxia Prefecture | AI6: DC,Pesht Military District,Ningxia Prefecture | AJ6: DC,Pesht Military District,Ningxia Prefecture | AK6: DC,Pesht Military District,Ningxia Prefecture | AL6: DC,Pesht Military District,Ningxia Prefecture | AM6: DC,Pesht Military District,Ningxia Prefecture | AN6: DC,Pesht Military District,Ningxia Prefecture | AO6: DC,Pesht Military District,Ningxia Prefecture | AP6: DC,Pesht Military District,Ningxia Prefecture | AQ6: DC,Pesht Military District,Ningxia Prefecture | AR6: DC,Pesht Military District,Ningxia Prefecture | AS6: DC,Pesht Military District,Ningxia Prefecture | AT6: DC,Pesht Military District,Ningxia Prefecture | AU6: DC,Pesht Military District,Ningxia Prefecture | AV6: DC,Pesht Military District,Ningxia Prefecture | AW6: DC,Pesht Military District,Ningxia Prefecture | AX6: DC,Pesht Military District,Ningxia Prefecture | AY6: DC,Pesht Military District,Ningxia Prefecture | AZ6: DC,Pesht Military District,Ningxia Prefecture
A7: 5 | B7: Abbadiyah | D7: {=index(systems,match($A7,INDEX(systems,0,1),),3)} -> -317.967 | E7: {=index(systems,match($A7,INDEX(systems,0,1),),4)} -> 246.551 | F7: =IFERROR(__xludf.DUMMYFUNCTION("let(row, match($B7&if($C7<>"""","" [""&$C7&""]"",""""),index(nebulae,,2),0),join("","",iferror(round(index(nebulae,row,5)/2,3),1),iferror(round(index(nebulae,row,6)/2,3),1),0))"),"1,1,0") -> 1,1,0 | G7: https://www.sarna.net/wiki/Abbadiyah | H7: {=let(systemId,match(A7,index(systems,0,1),),refSystemId,match($H$1,index(systems,0,1),),x,index(systems,systemId,3),y,index(systems,systemId,4),refX,index(systems,refSystemId,3),refY,index(systems,refSystemId,4),round(sqrt((x-refX)^2+(y-refY)^2),3))} -> 402.356 | N7: LC,Protectorate of Donegal,Coventry Province | O7: LC,Protectorate of Donegal,Coventry Province | P7: LC,Protectorate of Donegal,Coventry Province | Q7: LC,Protectorate of Donegal,Coventry Province | R7: LC,Protectorate of Donegal,Coventry Province | S7: LC,Protectorate of Donegal,Coventry Province | T7: LC,Protectorate of Donegal,Coventry Province | U7: LC,Protectorate of Donegal,Coventry Province | V7: LC,Protectorate of Donegal,Coventry Province | W7: LC,Protectorate of Donegal,Coventry Province | X7: LC,Protectorate of Donegal,Coventry Province | Y7: LC,Protectorate of Donegal,Coventry Province | Z7: LC,Protectorate of Donegal,Coventry Province | AA7: FCL,Donegal March,Coventry Operational Area,Region 2 | AB7: FCL,Donegal March,Coventry Operational Area,Region 2 | AC7: FCL,Donegal March,Coventry Operational Area,Region 2 | AD7: FCL,Donegal March,Coventry Operational Area,Region 2 | AE7: FCL,Donegal March,Coventry Operational Area,Region 2 | AF7: FCL,Donegal March,Coventry Operational Area,Region 2 | AG7: FCL,Donegal March,Coventry Operational Area,Region 2 | AH7: LA,Donegal March,Coventry Operational Area,Region 2 | AI7: LA,Coventry Province | AJ7: LA,Coventry Province | AK7: LA,Coventry Province | AL7: LA,Coventry Province | AM7: LA,Coventry Province | AN7: LA,Coventry Province | AO7: LA,Coventry Province | AP7: LA,Coventry Province | AQ7: LA,Coventry Province | AR7: LA,Coventry Province | AS7: LA,Coventry Province | AT7: LC,Coventry Province | AU7: LC,Coventry Province | AV7: LC,Coventry Province | AW7: LC,Coventry Province | AX7: LC,Coventry Province | AY7: LC,Coventry Province | AZ7: LC,Coventry Province
A8: 6 | B8: Abbeville | D8: {=index(systems,match($A8,INDEX(systems,0,1),),3)} -> 605.903 | E8: {=index(systems,match($A8,INDEX(systems,0,1),),4)} -> -39.852 | F8: =IFERROR(__xludf.DUMMYFUNCTION("let(row, match($B8&if($C8<>"""","" [""&$C8&""]"",""""),index(nebulae,,2),0),join("","",iferror(round(index(nebulae,row,5)/2,3),1),iferror(round(index(nebulae,row,6)/2,3),1),0))"),"1,1,0") -> 1,1,0 | G8: https://www.sarna.net/wiki/Abbeville | H8: {=let(systemId,match(A8,index(systems,0,1),),refSystemId,match($H$1,index(systems,0,1),),x,index(systems,systemId,3),y,index(systems,systemId,4),refX,index(systems,refSystemId,3),refY,index(systems,refSystemId,4),round(sqrt((x-refX)^2+(y-refY)^2),3))} -> 607.212 | N8: FS,Draconis March,Woodbine Operational Area,Region 2 | O8: FS,Draconis March,Woodbine Operational Area,Region 2 | P8: FS,Draconis March,Woodbine Operational Area,Region 2 | Q8: FS,Draconis March,Woodbine Operational Area,Region 2 | R8: FS,Draconis March,Woodbine Operational Area,Region 2 | S8: FS,Draconis March,Woodbine Operational Area,Region 2 | T8: FS,Draconis March,Woodbine Operational Area,Region 2 | U8: FS,Draconis March,Woodbine Operational Area,Region 4 | V8: FS,Draconis March,Woodbine Operational Area,Region 4 | W8: FS,Draconis March,Woodbine Operational Area,Region 4 | X8: FS,Draconis March,Woodbine Operational Area,Region 4 | Y8: FS,Draconis March,Woodbine Operational Area,Kilbourne PDZ | Z8: FS,Draconis March,Woodbine Operational Area,Kilbourne PDZ | AA8: FCF,Draconis March,Woodbine Operational Area,Kilbourne PDZ | AB8: FCF,Draconis March,Woodbine Operational Area,Kilbourne PDZ | AC8: FCF,Draconis March,Woodbine Operational Area,Kilbourne PDZ | AD8: FCF,Draconis March,Woodbine Operational Area,Kilbourne PDZ | AE8: FCF,Draconis March,Woodbine Operational Area,Kilbourne PDZ | AF8: FCF,Draconis March,Woodbine Operational Area,Kilbourne PDZ | AG8: FCF,Draconis March,Woodbine Operational Area,Kilbourne PDZ | AH8: FCF,Draconis March,Woodbine Operational Area,Kilbourne PDZ | AI8: FCF,Draconis March,Woodbine Operational Area,Kilbourne PDZ | AJ8: FCF,Draconis March,Woodbine Operational Area,Kilbourne PDZ | AK8: FCF,Draconis March,Woodbine Operational Area,Kilbourne PDZ | AL8: FCF,Draconis March,Woodbine Operational Area,Kilbourne PDZ | AM8: FCF,Draconis March,Woodbine Operational Area,Kilbourne PDZ | AN8: FCF,Draconis March,Woodbine Operational Area,Kilbourne PDZ | AO8: FS,Draconis March,Woodbine Operational Area,Kilbourne PDZ | AP8: FS,Draconis March,Woodbine Operational Area,Kilbourne PDZ | AQ8: FS,Draconis March,Woodbine Operational Area,Kilbourne PDZ | AR8: FS,Periphery March,Woodbine Operational Area,Kilbourne PDZ | AS8: FS,Periphery March,Woodbine Operational Area,Kilbourne PDZ | AT8: FS,Periphery March,Woodbine Operational Area,Kilbourne PDZ | AU8: FS,Periphery March,Woodbine Operational Area,Kilbourne PDZ | AV8: FS,Periphery March,Woodbine Operational Area,Kilbourne PDZ | AW8: FS,Periphery March,Woodbine Operational Area,Kilbourne PDZ | AX8: FS,Periphery March,Woodbine Operational Area,Kilbourne PDZ | AY8: FS,Periphery March,Woodbine Operational Area,Kilbourne PDZ | AZ8: FS,Periphery March,Woodbine Operational Area,Kilbourne PDZ
A9: 7 | B9: Abejorral | D9: {=index(systems,match($A9,INDEX(systems,0,1),),3)} -> -299.341 | E9: {=index(systems,match($A9,INDEX(systems,0,1),),4)} -> 127.388 | F9: =IFERROR(__xludf.DUMMYFUNCTION("let(row, match($B9&if($C9<>"""","" [""&$C9&""]"",""""),index(nebulae,,2),0),join("","",iferror(round(index(nebulae,row,5)/2,3),1),iferror(round(index(nebulae,row,6)/2,3),1),0))"),"1,1,0") -> 1,1,0 | G9: https://www.sarna.net/wiki/Abejorral | H9: {=let(systemId,match(A9,index(systems,0,1),),refSystemId,match($H$1,index(systems,0,1),),x,index(systems,systemId,3),y,index(systems,systemId,4),refX,index(systems,refSystemId,3),refY,index(systems,refSystemId,4),round(sqrt((x-refX)^2+(y-refY)^2),3))} -> 325.319 | I9: U | J9: U | K9: U | L9: U | M9: U | N9: U | P9: LC,Protectorate of Donegal,Alarion Province | Q9: LC,Protectorate of Donegal,Alarion Province | R9: LC,Protectorate of Donegal,Alarion Province | S9: LC,Protectorate of Donegal,Alarion Province | T9: LC,Protectorate of Donegal,Alarion Province | U9: LC,Protectorate of Donegal,Alarion Province | V9: LC,Protectorate of Donegal,Alarion Province | W9: LC,Protectorate of Donegal,Alarion Province | X9: LC,Protectorate of Donegal,Alarion Province | Y9: LC,Protectorate of Donegal,Alarion Province | Z9: LC,Protectorate of Donegal,Alarion Province | AA9: FCL,Donegal March,Alarion Operational Area,Region 1 | AB9: FCL,Donegal March,Alarion Operational Area,Region 1 | AC9: FCL,Donegal March,Alarion Operational Area,Region 1 | AD9: FCL,Donegal March,Alarion Operational Area,Region 1 | AE9: FCL,Donegal March,Alarion Operational Area,Region 1 | AF9: FCL,Donegal March,Alarion Operational Area,Region 1 | AG9: FCL,Donegal March,Alarion Operational Area,Region 1 | AH9: LA,Donegal March,Alarion Operational Area,Region 1 | AI9: LA,Alarion Province | AJ9: LA,Alarion Province | AK9: LA,Alarion Province | AL9: LA,Alarion Province | AM9: LA,Alarion Province | AN9: LA,Alarion Province | AO9: LA,Alarion Province | AP9: LA,Alarion Province | AQ9: LA,Alarion Province | AR9: LA,Alarion Province | AS9: LA,Buena Province | AT9: LC,Buena Province | AU9: LC,Buena Province | AV9: LC,Buena Province | AW9: LC,Buena Province | AX9: LC,Buena Province | AY9: LC,Buena Province | AZ9: LC,Bolan Province
A10: 3146 | B10: Abeline | C10: Taygete (2890+) | D10: {=index(systems,match($A10,INDEX(systems,0,1),),3)} -> -26.218 | E10: {=index(systems,match($A10,INDEX(systems,0,1),),4)} -> -481.285 | F10: =IFERROR(__xludf.DUMMYFUNCTION("let(row, match($B10&if($C10<>"""","" [""&$C10&""]"",""""),index(nebulae,,2),0),join("","",iferror(round(index(nebulae,row,5)/2,3),1),iferror(round(index(nebulae,row,6)/2,3),1),0))"),"1,1,0") -> 1,1,0 | G10: https://www.sarna.net/wiki/Taygete | H10: {=let(systemId,match(A10,index(systems,0,1),),refSystemId,match($H$1,index(systems,0,1),),x,index(systems,systemId,3),y,index(systems,systemId,4),refX,index(systems,refSystemId,3),refY,index(systems,refSystemId,4),round(sqrt((x-refX)^2+(y-refY)^2),3))} -> 481.999 | I10: U | J10: U | K10: U | L10: U | M10: U | N10: U | P10: U | Q10: U | R10: U | S10: U | T10: U | V10: I | W10: I | X10: I | Y10: A | Z10: A | AA10: A | AB10: A | AC10: A | AD10: A | AE10: A | AF10: A | AG10: A | AH10: A | AI10: A | AJ10: A | AK10: A | AL10: A | AM10: A | AN10: A | AO10: A | AP10: A | AQ10: A | AR10: A | AS10: A | AT10: A | AU10: A | AV10: A | AW10: A | AX10: A | AY10: A | AZ10: A
A11: 8 | B11: Aberystwyth | D11: {=index(systems,match($A11,INDEX(systems,0,1),),3)} -> -430.967 | E11: {=index(systems,match($A11,INDEX(systems,0,1),),4)} -> 58.633 | F11: =IFERROR(__xludf.DUMMYFUNCTION("let(row, match($B11&if($C11<>"""","" [""&$C11&""]"",""""),index(nebulae,,2),0),join("","",iferror(round(index(nebulae,row,5)/2,3),1),iferror(round(index(nebulae,row,6)/2,3),1),0))"),"1,1,0") -> 1,1,0 | G11: https://www.sarna.net/wiki/Aberystwyth | H11: {=let(systemId,match(A11,index(systems,0,1),),refSystemId,match($H$1,index(systems,0,1),),x,index(systems,systemId,3),y,index(systems,systemId,4),refX,index(systems,refSystemId,3),refY,index(systems,refSystemId,4),round(sqrt((x-refX)^2+(y-refY)^2),3))} -> 434.937 | I11: U | J11: U | K11: U | L11: U | M11: U | N11: U | P11: RW,Timbuktu Province | Q11: RW,Timbuktu Province | R11: RW,Timbuktu Province | S11: LC,Protectorate of Donegal,Alarion Province | T11: LC,Protectorate of Donegal,Alarion Province | U11: LC,Protectorate of Donegal,Alarion Province | V11: LC,Protectorate of Donegal,Alarion Province | W11: LC,Protectorate of Donegal,Alarion Province | X11: LC,Protectorate of Donegal,Alarion Province | Y11: LC,Protectorate of Donegal,Alarion Province | Z11: LC,Protectorate of Donegal,Alarion Province | AA11: FCL,Periphery March,Venaria Operational Area,Region 2 | AB11: FCL,Periphery March,Venaria Operational Area,Region 2 | AC11: FCL,Periphery March,Venaria Operational Area,Region 2 | AD11: FCL,Periphery March,Venaria Operational Area,Region 2 | AE11: FCL,Periphery March,Venaria Operational Area,Region 2 | AF11: FCL,Periphery March,Venaria Operational Area,Region 2 | AG11: FCL,Periphery March,Venaria Operational Area,Region 2 | AH11: LA,Periphery March,Venaria Operational Area,Region 2 | AI11: LA,Alarion Province,Timbuktu Theater | AJ11: LA,Alarion Province,Timbuktu Theater | AK11: LA,Alarion Province,Timbuktu Theater | AL11: LA,Alarion Province,Timbuktu Theater | AM11: LA,Alarion Province,Timbuktu Theater | AN11: LA,Alarion Province,Timbuktu Theater | AO11: LA,Alarion Province,Timbuktu Theater | AP11: LA,Alarion Province,Timbuktu Theater | AQ11: LA,Alarion Province,Timbuktu Theater,Buena Archonette | AR11: LA,Alarion Province,Timbuktu Theater,Buena Archonette | AS11: LA,Timbuktu Theater | AT11: LC,Timbuktu Theater | AU11: LC,Timbuktu Theater | AV11: LC,Timbuktu Theater | AW11: LC,Timbuktu Theater | AX11: LC,Florida Theater | AY11: LC,Florida Theater | AZ11: LC,Florida Theater
A12: 9 | B12: Abiy Adi | D12: {=index(systems,match($A12,INDEX(systems,0,1),),3)} -> 349.466 | E12: {=index(systems,match($A12,INDEX(systems,0,1),),4)} -> 314.567 | F12: =IFERROR(__xludf.DUMMYFUNCTION("let(row, match($B12&if($C12<>"""","" [""&$C12&""]"",""""),index(nebulae,,2),0),join("","",iferror(round(index(nebulae,row,5)/2,3),1),iferror(round(index(nebulae,row,6)/2,3),1),0))"),"1,1,0") -> 1,1,0 | G12: https://www.sarna.net/wiki/Abiy_Adi | H12: {=let(systemId,match(A12,index(systems,0,1),),refSystemId,match($H$1,index(systems,0,1),),x,index(systems,systemId,3),y,index(systems,systemId,4),refX,index(systems,refSystemId,3),refY,index(systems,refSystemId,4),round(sqrt((x-refX)^2+(y-refY)^2),3))} -> 470.19 | I12: U | J12: U | K12: U | L12: U | M12: U | N12: U | P12: DC,Pesht Military District,Ningxia Prefecture | Q12: DC,Pesht Military District,Ningxia Prefecture | R12: DC,Pesht Military District,Ningxia Prefecture | S12: DC,Pesht Military District,Ningxia Prefecture | T12: DC,Pesht Military District,Ningxia Prefecture | U12: DC,Pesht Military District,Ningxia Prefecture | V12: DC,Pesht Military District,Ningxia Prefecture | W12: DC,Pesht Military District,Ningxia Prefecture | X12: DC,Pesht Military District,Ningxia Prefecture | Y12: DC,Pesht Military District,Ningxia Prefecture | Z12: DC,Pesht Military District,Ningxia Prefecture | AA12: DC,Pesht Military District,Ningxia Prefecture | AB12: DC,Pesht Military District,Ningxia Prefecture | AC12: DC,Pesht Military District,Ningxia Prefecture | AD12: DC,Pesht Military District,Ningxia Prefecture | AE12: DC,Pesht Military District,Ningxia Prefecture | AF12: DC,Pesht Military District,Ningxia Prefecture | AG12: DC,Pesht Military District,Ningxia Prefecture | AH12: DC,Pesht Military District,Ningxia Prefecture | AI12: DC,Pesht Military District,Ningxia Prefecture | AJ12: DC,Pesht Military District,Ningxia Prefecture | AK12: DC,Pesht Military District,Ningxia Prefecture | AL12: DC,Pesht Military District,Ningxia Prefecture | AM12: DC,Pesht Military District,Ningxia Prefecture | AN12: DC,Pesht Military District,Ningxia Prefecture | AO12: DC,Pesht Military District,Ningxia Prefecture | AP12: DC,Pesht Military District,Ningxia Prefecture | AQ12: DC,Pesht Military District,Ningxia Prefecture | AR12: DC,Pesht Military District,Ningxia Prefecture | AS12: DC,Pesht Military District,Ningxia Prefecture | AT12: DC,Pesht Military District,Ningxia Prefecture | AU12: DC,Pesht Military District,Ningxia Prefecture | AV12: DC,Pesht Military District,Ningxia Prefecture | AW12: DC,Pesht Military District,Ningxia Prefecture | AX12: DC,Pesht Military District,Ningxia Prefecture | AY12: DC,Pesht Military District,Ningxia Prefecture | AZ12: DC,Pesht Military District,Ningxia Prefecture
A13: 3126 | B13: Able's Glory | D13: {=index(systems,match($A13,INDEX(systems,0,1),),3)} -> -539.232 | E13: {=index(systems,match($A13,INDEX(systems,0,1),),4)} -> 124.693 | F13: =IFERROR(__xludf.DUMMYFUNCTION("let(row, match($B13&if($C13<>"""","" [""&$C13&""]"",""""),index(nebulae,,2),0),join("","",iferror(round(index(nebulae,row,5)/2,3),1),iferror(round(index(nebulae,row,6)/2,3),1),0))"),"1,1,0") -> 1,1,0 | G13: https://www.sarna.net/wiki/Able's_Glory | H13: {=let(systemId,match(A13,index(systems,0,1),),refSystemId,match($H$1,index(systems,0,1),),x,index(systems,systemId,3),y,index(systems,systemId,4),refX,index(systems,refSystemId,3),refY,index(systems,refSystemId,4),round(sqrt((x-refX)^2+(y-refY)^2),3))} -> 553.461 | I13: U | J13: U | K13: U | L13: U | M13: U | N13: U | P13: U | Q13: U | R13: U | S13: U | T13: U | U13: U | V13: U | W13: U | X13: U | Y13: U | Z13: U | AA13: U | AB13: U | AC13: U | AD13: U | AE13: U | AF13: U | AG13: U | AH13: U | AI13: U | AJ13: U | AK13: U | AL13: U | AM13: U | AN13: U | AO13: U | AP13: U | AQ13: U | AR13: U | AS13: U | AT13: U | AU13: U | AV13: RC | AW13: RC | AX13: RC | AY13: TiC | AZ13: TiC
A14: 10 | B14: Aboukir | D14: {=index(systems,match($A14,INDEX(systems,0,1),),3)} -> -419.964 | E14: {=index(systems,match($A14,INDEX(systems,0,1),),4)} -> 287.637 | F14: =IFERROR(__xludf.DUMMYFUNCTION("let(row, match($B14&if($C14<>"""","" [""&$C14&""]"",""""),index(nebulae,,2),0),join("","",iferror(round(index(nebulae,row,5)/2,3),1),iferror(round(index(nebulae,row,6)/2,3),1),0))"),"1,1,0") -> 1,1,0 | G14: https://www.sarna.net/wiki/Aboukir | H14: {=let(systemId,match(A14,index(systems,0,1),),refSystemId,match($H$1,index(systems,0,1),),x,index(systems,systemId,3),y,index(systems,systemId,4),refX,index(systems,refSystemId,3),refY,index(systems,refSystemId,4),round(sqrt((x-refX)^2+(y-refY)^2),3))} -> 509.023 | I14: U | J14: U | K14: U | L14: U | M14: U | N14: U | P14: RW,Finmark Province | Q14: RW,Finmark Province | R14: RW,Finmark Province | S14: LC,Protectorate of Donegal,Coventry Province | T14: LC,Protectorate of Donegal,Coventry Province | U14: LC,Protectorate of Donegal,Coventry Province | V14: LC,Protectorate of Donegal,Coventry Province | W14: LC,Protectorate of Donegal,Coventry Province | X14: LC,Protectorate of Donegal,Coventry Province | Y14: A | Z14: A | AA14: A | AB14: A | AC14: A | AD14: A | AE14: A | AF14: A | AG14: A | AH14: A | AI14: A | AJ14: A | AK14: A | AL14: A | AM14: A | AN14: A | AO14: A | AP14: A | AQ14: A | AR14: A | AS14: A | AT14: A | AU14: A | AV14: A | AW14: A | AX14: A | AY14: A | AZ14: A
A15: 11 | B15: Abramkovo | D15: {=index(systems,match($A15,INDEX(systems,0,1),),3)} -> -330.86 | E15: {=index(systems,match($A15,INDEX(systems,0,1),),4)} -> -28.739 | F15: =IFERROR(__xludf.DUMMYFUNCTION("let(row, match($B15&if($C15<>"""","" [""&$C15&""]"",""""),index(nebulae,,2),0),join("","",iferror(round(index(nebulae,row,5)/2,3),1),iferror(round(index(nebulae,row,6)/2,3),1),0))"),"1,1,0") -> 1,1,0 | G15: https://www.sarna.net/wiki/Abramkovo | H15: {=let(systemId,match(A15,index(systems,0,1),),refSystemId,match($H$1,index(systems,0,1),),x,index(systems,systemId,3),y,index(systems,systemId,4),refX,index(systems,refSystemId,3),refY,index(systems,refSystemId,4),round(sqrt((x-refX)^2+(y-refY)^2),3))} -> 332.106 | I15: U | J15: U | K15: U | L15: U | M15: U | N15: U | P15: LC,Protectorate of Donegal,Alarion Province | Q15: LC,Protectorate of Donegal,Alarion Province | R15: LC,Protectorate of Donegal,Alarion Province | S15: LC,Protectorate of Donegal,Alarion Province | T15: LC,Protectorate of Donegal,Alarion Province | U15: LC,Protectorate of Donegal,Alarion Province | V15: LC,Protectorate of Donegal,Alarion Province | W15: LC,Protectorate of Donegal,Alarion Province | X15: LC,Protectorate of Donegal,Alarion Province | Y15: LC,Protectorate of Donegal,Alarion Province | Z15: LC,Protectorate of Donegal,Bolan Province | AA15: FCL,Tamarind March,Bolan Operational Area,Region 2 | AB15: FCL,Tamarind March,Bolan Operational Area,Region 2 | AC15: FCL,Tamarind March,Bolan Operational Area,Region 2 | AD15: FCL,Tamarind March,Bolan Operational Area,Region 2 | AE15: FCL,Tamarind March,Bolan Operational Area,Region 2 | AF15: FCL,Tamarind March,Bolan Operational Area,Region 2 | AG15: FCL,Tamarind March,Bolan Operational Area,Region 2 | AH15: LA,Tamarind March,Bolan Operational Area,Region 2 | AI15: LA,Bolan Province,Cavanaugh Theater | AJ15: LA,Bolan Province,Cavanaugh Theater | AK15: LA,Bolan Province,Cavanaugh Theater | AL15: LA,Bolan Province,Cavanaugh Theater | AM15: LA,Bolan Province,Cavanaugh Theater | AN15: LA,Bolan Province,Cavanaugh Theater | AO15: LA,Bolan Province,Cavanaugh Theater | AP15: LA,Bolan Province,Dixie Theater | AQ15: LA,Bolan Province,Dixie Theater | AR15: LA,Bolan Province,Dixie Theater | AS15: LA,Bolan Province,Dixie Theater | AT15: LC,Bolan Province,Dixie Theater | AU15: LC,Bolan Province,Dixie Theater | AV15: LC,Bolan Province,Cavanaugh Theater | AW15: LC,Bolan Province,Cavanaugh Theater | AX15: LC,Timbuktu Theater | AY15: FWL,Duchy of Tammarind-Abbey | AZ15: FWL,Duchy of Tammarind-Abbey
A16: 12 | B16: Abruzzi | D16: {=index(systems,match($A16,INDEX(systems,0,1),),3)} -> 149.392 | E16: {=index(systems,match($A16,INDEX(systems,0,1),),4)} -> -304.327 | F16: =IFERROR(__xludf.DUMMYFUNCTION("let(row, match($B16&if($C16<>"""","" [""&$C16&""]"",""""),index(nebulae,,2),0),join("","",iferror(round(index(nebulae,row,5)/2,3),1),iferror(round(index(nebulae,row,6)/2,3),1),0))"),"1,1,0") -> 1,1,0 | G16: https://www.sarna.net/wiki/Abruzzi | H16: {=let(systemId,match(A16,index(systems,0,1),),refSystemId,match($H$1,index(systems,0,1),),x,index(systems,systemId,3),y,index(systems,systemId,4),refX,index(systems,refSystemId,3),refY,index(systems,refSystemId,4),round(sqrt((x-refX)^2+(y-refY)^2),3))} -> 339.018 | I16: U | J16: U | K16: U | L16: U | M16: U | N16: U | P16: CC,St. Ives Commonality,Region 6 | Q16: CC,St. Ives Commonality,Region 6 | R16: CC,St. Ives Commonality,Region 6 | S16: CC,St. Ives Commonality,Region 6 | T16: CC,St. Ives Commonality,Region 6 | U16: CC,St. Ives Commonality,Region 6 | V16: CC,St. Ives Commonality,Region 6 | W16: CC,St. Ives Commonality,Region 6 | X16: FS,Capellan March,Taygeta Operational Area,Region 1 | Y16: FS,Capellan March,Taygeta Operational Area,Sirdar PDZ | Z16: FS,Capellan March,Taygeta Operational Area,Sirdar PDZ | AA16: FCF,Capellan March,Taygeta Operational Area,Sirdar PDZ | AB16: FCF,Capellan March,Taygeta Operational Area,Sirdar PDZ | AC16: FCF,Capellan March,Taygeta Operational Area,Sirdar PDZ | AD16: FCF,Capellan March,Taygeta Operational Area,Sirdar PDZ | AE16: FCF,Capellan March,Taygeta Operational Area,Sirdar PDZ | AF16: FCF,Capellan March,Taygeta Operational Area,Sirdar PDZ | AG16: FCF,Capellan March,Taygeta Operational Area,Sirdar PDZ | AH16: FCF,Capellan March,Taygeta Operational Area,Sirdar PDZ | AI16: FCF,Capellan March,Taygeta Operational Area,Sirdar PDZ | AJ16: FCF,Capellan March,Taygeta Operational Area,Sirdar PDZ | AK16: FCF,Capellan March,Taygeta Operational Area,Sirdar PDZ | AL16: FCF,Capellan March,Taygeta Operational Area,Sirdar PDZ | AM16: FCF,Capellan March,Taygeta Operational Area,Sirdar PDZ | AN16: FCF,Capellan March,Taygeta Operational Area,Sirdar PDZ | AO16: FS,Capellan March,Taygeta Operational Area,Sirdar PDZ | AP16: FS,Capellan March,Taygeta Operational Area,Sirdar PDZ | AQ16: FS,Capellan March,Taygeta Operational Area,Sirdar PDZ | AR16: FS,Capellan March,Taygeta Operational Area,Sirdar PDZ | AS16: FS,Capellan March,Taygeta Operational Area,Sirdar PDZ | AT16: FS,Capellan March,Taygeta Operational Area,Sirdar PDZ | AU16: FS,Capellan March,Taygeta Operational Area,Sirdar PDZ | AV16: FS,Capellan March,Taygeta Operational Area,Sirdar PDZ | AW16: FS,Capellan March,Taygeta Operational Area,Sirdar PDZ | AX16: FS,Capellan March,Sirdar Operational Area,Sirdar PDZ | AY16: FS,Capellan March,Taygeta Operational Area,Sirdar PDZ | AZ16: FS,Capellan March,Taygeta Operational Area,Sirdar PDZ
A17: 13 | B17: Abushiri | D17: {=index(systems,match($A17,INDEX(systems,0,1),),3)} -> -267.585 | E17: {=index(systems,match($A17,INDEX(systems,0,1),),4)} -> 326.475 | F17: =IFERROR(__xludf.DUMMYFUNCTION("let(row, match($B17&if($C17<>"""","" [""&$C17&""]"",""""),index(nebulae,,2),0),join("","",iferror(round(index(nebulae,row,5)/2,3),1),iferror(round(index(nebulae,row,6)/2,3),1),0))"),"1,1,0") -> 1,1,0 | G17: https://www.sarna.net/wiki/Abushiri | H17: {=let(systemId,match(A17,index(systems,0,1),),refSystemId,match($H$1,index(systems,0,1),),x,index(systems,systemId,3),y,index(systems,systemId,4),refX,index(systems,refSystemId,3),refY,index(systems,refSystemId,4),round(sqrt((x-refX)^2+(y-refY)^2),3))} -> 422.123 | I17: U | J17: U | K17: U | L17: U | M17: U | N17: U | P17: RW,Apollo Province | Q17: RW,Apollo Province | R17: RW,Apollo Province | S17: LC,Protectorate of Donegal,Coventry Province | T17: LC,Protectorate of Donegal,Coventry Province | U17: LC,Protectorate of Donegal,Coventry Province | V17: LC,Protectorate of Donegal,Coventry Province | W17: LC,Protectorate of Donegal,Coventry Province | X17: LC,Protectorate of Donegal,Coventry Province | Y17: A | Z17: A | AA17: A | AB17: A | AC17: A | AD17: A | AE17: A | AF17: A | AG17: A | AH17: A | AI17: A | AJ17: A | AK17: A | AL17: A | AM17: A | AN17: A | AO17: A | AP17: A | AQ17: A | AR17: A | AS17: A | AT17: A | AU17: A | AV17: A | AW17: A | AX17: A | AY17: A | AZ17: A
A18: 14 | B18: Acala | D18: {=index(systems,match($A18,INDEX(systems,0,1),),3)} -> 134.156 | E18: {=index(systems,match($A18,INDEX(systems,0,1),),4)} -> -124.34 | F18: =IFERROR(__xludf.DUMMYFUNCTION("let(row, match($B18&if($C18<>"""","" [""&$C18&""]"",""""),index(nebulae,,2),0),join("","",iferror(round(index(nebulae,row,5)/2,3),1),iferror(round(index(nebulae,row,6)/2,3),1),0))"),"1,1,0") -> 1,1,0 | G18: https://www.sarna.net/wiki/Acala | H18: {=let(systemId,match(A18,index(systems,0,1),),refSystemId,match($H$1,index(systems,0,1),),x,index(systems,systemId,3),y,index(systems,systemId,4),refX,index(systems,refSystemId,3),refY,index(systems,refSystemId,4),round(sqrt((x-refX)^2+(y-refY)^2),3))} -> 182.916 | J18: I | M18: FS | N18: CC,Sarna Commonality,Region 7 | O18: CC,Sarna Commonality,Region 7 | P18: CC,Sarna Commonality,Region 7 | Q18: CC,Sarna Commonality,Region 7 | R18: CC,Sarna Commonality,Region 7 | S18: CC,Sarna Commonality,Region 7 | T18: CC,Sarna Commonality,Region 7 | U18: CC,Sarna Commonality,Region 7 | V18: CC,Sarna Commonality,Region 7 | W18: CC,Sarna Commonality,Region 7 | X18: FS,Capellan March,Kathil Operational Area,Region 1 | Y18: FS,Capellan March,Kathil Operational Area,Valexa PDZ | Z18: FS,Capellan March,Kathil Operational Area,Valexa PDZ | AA18: FCF,Capellan March,Kathil Operational Area,Valexa PDZ | AB18: FCF,Capellan March,Kathil Operational Area,Valexa PDZ | AC18: FCF,Capellan March,Kathil Operational Area,Valexa PDZ | AD18: FCF,Capellan March,Kathil Operational Area,Valexa PDZ | AE18: FCF,Capellan March,Kathil Operational Area,Valexa PDZ | AF18: FCF,Capellan March,Kathil Operational Area,Valexa PDZ | AG18: FCF,Capellan March,Kathil Operational Area,Valexa PDZ | AH18: FCF,Capellan March,Kathil Operational Area,Valexa PDZ | AI18: FCF,Capellan March,Kathil Operational Area,Valexa PDZ | AJ18: FCF,Capellan March,Kathil Operational Area,Valexa PDZ | AK18: FCF,Capellan March,Kathil Operational Area,Valexa PDZ | AL18: FCF,Capellan March,Kathil Operational Area,Valexa PDZ | AM18: FCF,Capellan March,Kathil Operational Area,Valexa PDZ | AN18: FCF,Capellan March,Kathil Operational Area,Valexa PDZ | AO18: FS,Capellan March,Kathil Operational Area,Valexa PDZ | AP18: FS,Capellan March,Kathil Operational Area,Valexa PDZ | AQ18: FS,Capellan March,Kathil Operational Area,Valexa PDZ | AR18: FS,Capellan March,Kathil Operational Area,Valexa PDZ | AS18: FS,Capellan March,Kathil Operational Area,Valexa PDZ | AT18: FS,Capellan March,Kathil Operational Area,Valexa PDZ | AU18: FS,Capellan March,Kathil Operational Area,Valexa PDZ | AV18: FS,Capellan March,Kathil Operational Area,Alcyone PDZ | AW18: FS,Capellan March,Kathil Operational Area,Alcyone PDZ | AX18: FS,Capellan March,Kathil Operational Area,Alcyone PDZ | AY18: FS,Capellan March,Kathil Operational Area,Alcyone PDZ | AZ18: FS,Capellan March,Kathil Operational Area,Alcyone PDZ
A19: 15 | B19: Acamar | D19: {=index(systems,match($A19,INDEX(systems,0,1),),3)} -> 39.543 | E19: {=index(systems,match($A19,INDEX(systems,0,1),),4)} -> -38.565 | F19: =IFERROR(__xludf.DUMMYFUNCTION("let(row, match($B19&if($C19<>"""","" [""&$C19&""]"",""""),index(nebulae,,2),0),join("","",iferror(round(index(nebulae,row,5)/2,3),1),iferror(round(index(nebulae,row,6)/2,3),1),0))"),"1,1,0") -> 1,1,0 | G19: https://www.sarna.net/wiki/Acamar | H19: {=let(systemId,match(A19,index(systems,0,1),),refSystemId,match($H$1,index(systems,0,1),),x,index(systems,systemId,3),y,index(systems,systemId,4),refX,index(systems,refSystemId,3),refY,index(systems,refSystemId,4),round(sqrt((x-refX)^2+(y-refY)^2),3))} -> 55.235 | I19: I | L19: TH | M19: TH | N19: TH,Terra Firma Province | O19: TH,Terra Firma Province | P19: TH,Terra Firma Province | Q19: TH,Terra Firma Province | R19: AE,Terra Firma Province | S19: TH,Terra Firma Province | T19: TH,Brownsville Province | U19: CC,Tikonov Commonality,Region 3 | V19: CC,Tikonov Commonality,Region 3 | W19: CC,Tikonov Commonality,Region 3 | X19: CC,Tikonov Commonality,Region 3 | Y19: CC,Tikonov Commonality,Region 5 | Z19: TFR | AA19: FCL,Sarna March,Terra Firma Operational Area,Region 2 | AB19: FCL,Sarna March,Terra Firma Operational Area,Region 2 | AC19: FCL,Sarna March,Terra Firma Operational Area,Region 2 | AD19: FCL,Sarna March,Terra Firma Operational Area,Region 2 | AE19: FCL,Sarna March,Terra Firma Operational Area,Region 2 | AF19: FCL,Sarna March,Terra Firma Operational Area,Region 2 | AG19: FCL,Sarna March,Terra Firma Operational Area,Region 2 | AH19: I | AI19: I | AJ19: I | AK19: I | AL19: I | AM19: I | AN19: I | AO19: FS,Capellan March,Kathil Operational Area,Region 1 | AP19: WB | AQ19: WB | AR19: CoF | AS19: RS,Prefecture V | AT19: RS,Prefecture V | AU19: RS,Prefecture V | AV19: RS,Prefecture V | AW19: I | AX19: CC,Tikonov Commonality,Region 1 | AY19: CC,Tikonov Commonality,Region 6 | AZ19: CC,Tikonov Commonality,Region 6
A20: 16 | B20: Accrington | D20: {=index(systems,match($A20,INDEX(systems,0,1),),3)} -> -10.088 | E20: {=index(systems,match($A20,INDEX(systems,0,1),),4)} -> 144.968 | F20: =IFERROR(__xludf.DUMMYFUNCTION("let(row, match($B20&if($C20<>"""","" [""&$C20&""]"",""""),index(nebulae,,2),0),join("","",iferror(round(index(nebulae,row,5)/2,3),1),iferror(round(index(nebulae,row,6)/2,3),1),0))"),"1,1,0") -> 1,1,0 | G20: https://www.sarna.net/wiki/Accrington | H20: {=let(systemId,match(A20,index(systems,0,1),),refSystemId,match($H$1,index(systems,0,1),),x,index(systems,systemId,3),y,index(systems,systemId,4),refX,index(systems,refSystemId,3),refY,index(systems,refSystemId,4),round(sqrt((x-refX)^2+(y-refY)^2),3))} -> 145.319 | K20: FoS | L20: FoS | M20: LC,Federation of Skye | N20: LC,Federation of Skye,Kannon Shire | O20: LC,Federation of Skye,Kannon Shire | P20: LC,Federation of Skye,Kannon Shire | Q20: LC,Federation of Skye,Kannon Shire | R20: LC,Federation of Skye,Kannon Shire | S20: LC,Federation of Skye,Kannon Shire | T20: LC,Federation of Skye,Kannon Shire | U20: LC,Federation of Skye,Kannon Shire | V20: LC,Federation of Skye,Kannon Shire | W20: LC,Federation of Skye,Kannon Shire | X20: LC,Federation of Skye,Kannon Shire | Y20: LC,Federation of Skye,Virginia Shire | Z20: LC,Federation of Skye,Virginia Shire | AA20: FCL,Skye March,Ryde Operational Area,Region 1 | AB20: FCL,Skye March,Ryde Operational Area,Region 1 | AC20: FCL,Skye March,Ryde Operational Area,Region 1 | AD20: FCL,Skye March,Ryde Operational Area,Region 1 | AE20: FCL,Skye March,Ryde Operational Area,Region 1 | AF20: FCL,Skye March,Ryde Operational Area,Region 1 | AG20: FCL,Skye March,Ryde Operational Area,Region 1 | AH20: LA,Skye March,Ryde Operational Area,Region 1 | AI20: LA,Skye Province,Freedom Theater | AJ20: LA,Skye Province,Freedom Theater | AK20: LA,Skye Province,Freedom Theater | AL20: LA,Skye Province,Freedom Theater | AM20: LA,Skye Province,Freedom Theater | AN20: LA,Skye Province,Freedom Theater | AO20: LA,Skye Province,Freedom Theater | AP20: LA,Skye Province,Freedom Theater | AQ20: LA,Skye Province,Freedom Theater | AR20: LA,Skye Province,Freedom Theater | AS20: LA,Arc-Royal Theater | AT20: LC,Arc-Royal Theater | AU20: LC,Arc-Royal Theater | AV20: LC,Donegal Province | AW20: LC,Donegal Province | AX20: RD,Region 3 | AY20: RD,Region 3 | AZ20: RD,Region 3
A21: 87 | B21: Achernar | D21: {=index(systems,match($A21,INDEX(systems,0,1),),3)} -> 77.285 | E21: {=index(systems,match($A21,INDEX(systems,0,1),),4)} -> -32.361 | F21: =IFERROR(__xludf.DUMMYFUNCTION("let(row, match($B21&if($C21<>"""","" [""&$C21&""]"",""""),index(nebulae,,2),0),join("","",iferror(round(index(nebulae,row,5)/2,3),1),iferror(round(index(nebulae,row,6)/2,3),1),0))"),"1,1,0") -> 1,1,0 | G21: https://www.sarna.net/wiki/Achernar | H21: {=let(systemId,match(A21,index(systems,0,1),),refSystemId,match($H$1,index(systems,0,1),),x,index(systems,systemId,3),y,index(systems,systemId,4),refX,index(systems,refSystemId,3),refY,index(systems,refSystemId,4),round(sqrt((x-refX)^2+(y-refY)^2),3))} -> 83.787 | J21: I | K21: I | M21: TH | N21: TH,Lockdale Province | O21: TH,Lockdale Province | P21: TH,Lockdale Province | Q21: TH,Lockdale Province | R21: AE,Lockdale Province | S21: TH,Lockdale Province | T21: TH,Lockdale Province | U21: CC,Tikonov Commonality,Region 4 | V21: CC,Tikonov Commonality,Region 4 | W21: CC,Tikonov Commonality,Region 4 | X21: CC,Tikonov Commonality,Region 4 | Y21: CC,Tikonov Commonality,Region 6 | Z21: LC,Sarna March,Tikonov Operational Area,Region 2 | AA21: FCL,Sarna March,Terra Firma Operational Area,Region 3 | AB21: FCL,Sarna March,Terra Firma Operational Area,Region 3 | AC21: FCL,Sarna March,Terra Firma Operational Area,Region 3 | AD21: FCL,Sarna March,Terra Firma Operational Area,Region 3 | AE21: FCL,Sarna March,Terra Firma Operational Area,Region 3 | AF21: FCL,Sarna March,Terra Firma Operational Area,Region 3 | AG21: FCL,Sarna March,Terra Firma Operational Area,Region 3 | AH21: FCF,Draconis March,Robinson Operational Area,Addicks PDZ | AI21: FCF,Draconis March,Robinson Operational Area,Addicks PDZ | AJ21: FCF,Draconis March,Robinson Operational Area,Addicks PDZ | AK21: FCF,Draconis March,Robinson Operational Area,Addicks PDZ | AL21: FCF,Draconis March,Robinson Operational Area,Addicks PDZ | AM21: FCF,Draconis March,Robinson Operational Area,Addicks PDZ | AN21: FCF,Draconis March,Robinson Operational Area,Addicks PDZ | AO21: FS,Capellan March,Kathil Operational Area,Region 1 | AP21: FS,Capellan March,Kathil Operational Area,Region 1 | AQ21: WB | AR21: CoF | AS21: RS,Prefecture IV | AT21: RS,Prefecture IV | AU21: RS,Prefecture IV | AV21: RS,Prefecture IV | AW21: I | AX21: CC,Tikonov Commonality,Region 2 | AY21: CC,Tikonov Commonality,Region 8 | AZ21: CC,Tikonov Commonality,Region 8
A22: 17 | B22: Achilles | D22: {=index(systems,match($A22,INDEX(systems,0,1),),3)} -> 44.858 | E22: {=index(systems,match($A22,INDEX(systems,0,1),),4)} -> -132.111 | F22: =IFERROR(__xludf.DUMMYFUNCTION("let(row, match($B22&if($C22<>"""","" [""&$C22&""]"",""""),index(nebulae,,2),0),join("","",iferror(round(index(nebulae,row,5)/2,3),1),iferror(round(index(nebulae,row,6)/2,3),1),0))"),"1,1,0") -> 1,1,0 | G22: https://www.sarna.net/wiki/Achilles_(system) | H22: {=let(systemId,match(A22,index(systems,0,1),),refSystemId,match($H$1,index(systems,0,1),),x,index(systems,systemId,3),y,index(systems,systemId,4),refX,index(systems,refSystemId,3),refY,index(systems,refSystemId,4),round(sqrt((x-refX)^2+(y-refY)^2),3))} -> 139.519 | I22: U | J22: U | K22: U | L22: U | M22: U | N22: U | P22: CC,Sarna Commonality,Region 4 | Q22: CC,Sarna Commonality,Region 4 | R22: CC,Sarna Commonality,Region 4 | S22: CC,Sarna Commonality,Region 4 | T22: CC,Sarna Commonality,Region 4 | U22: CC,Sarna Commonality,Region 4 | V22: CC,Sarna Commonality,Region 4 | W22: CC,Sarna Commonality,Region 4 | X22: CC,Sarna Commonality,Region 4 | Y22: A | Z22: A | AA22: A | AB22: A | AC22: A | AD22: A | AE22: A | AF22: A | AG22: A | AH22: A | AI22: A | AJ22: A | AK22: A | AL22: A | AM22: A | AN22: A | AO22: A | AP22: A | AQ22: A | AR22: A | AS22: A | AT22: A | AU22: A | AV22: A | AW22: A | AX22: A | AY22: A | AZ22: A
A23: 18 | B23: Achnoly | D23: {=index(systems,match($A23,INDEX(systems,0,1),),3)} -> 638.819 | E23: {=index(systems,match($A23,INDEX(systems,0,1),),4)} -> 199.142 | F23: =IFERROR(__xludf.DUMMYFUNCTION("let(row, match($B23&if($C23<>"""","" [""&$C23&""]"",""""),index(nebulae,,2),0),join("","",iferror(round(index(nebulae,row,5)/2,3),1),iferror(round(index(nebulae,row,6)/2,3),1),0))"),"1,1,0") -> 1,1,0 | G23: https://www.sarna.net/wiki/Achnoly | H23: {=let(systemId,match(A23,index(systems,0,1),),refSystemId,match($H$1,index(systems,0,1),),x,index(systems,systemId,3),y,index(systems,systemId,4),refX,index(systems,refSystemId,3),refY,index(systems,refSystemId,4),round(sqrt((x-refX)^2+(y-refY)^2),3))} -> 669.139 | I23: U | J23: U | K23: U | L23: U | M23: U | N23: U | P23: OA,Onverwacht Province | Q23: OA,Onverwacht Province | R23: OA,Onverwacht Province | S23: OA,Onverwacht Province | T23: OA,Onverwacht Province | U23: OA,Onverwacht Province | V23: OA,Onverwacht Province | W23: OA,Onverwacht Province | X23: A | Y23: A | Z23: A | AA23: A | AB23: A | AC23: A | AD23: A | AE23: A | AF23: A | AG23: A | AH23: A | AI23: A | AJ23: A | AK23: A | AL23: A | AM23: A | AN23: A | AO23: A | AP23: A | AQ23: A | AR23: A | AS23: A | AT23: A | AU23: A | AV23: A | AW23: A | AX23: A | AY23: A | AZ23: OW,Onverwacht Province
A24: 19 | B24: Achton | D24: {=index(systems,match($A24,INDEX(systems,0,1),),3)} -> 632.323 | E24: {=index(systems,match($A24,INDEX(systems,0,1),),4)} -> 190.916 | F24: =IFERROR(__xludf.DUMMYFUNCTION("let(row, match($B24&if($C24<>"""","" [""&$C24&""]"",""""),index(nebulae,,2),0),join("","",iferror(round(index(nebulae,row,5)/2,3),1),iferror(round(index(nebulae,row,6)/2,3),1),0))"),"1,1,0") -> 1,1,0 | G24: https://www.sarna.net/wiki/Achton | H24: {=let(systemId,match(A24,index(systems,0,1),),refSystemId,match($H$1,index(systems,0,1),),x,index(systems,systemId,3),y,index(systems,systemId,4),refX,index(systems,refSystemId,3),refY,index(systems,refSystemId,4),round(sqrt((x-refX)^2+(y-refY)^2),3))} -> 660.516 | I24: U | J24: U | K24: U | L24: U | M24: U | N24: U | P24: OA,Onverwacht Province | Q24: OA,Onverwacht Province | R24: OA,Onverwacht Province | S24: OA,Onverwacht Province | T24: OA,Onverwacht Province | U24: OA,Onverwacht Province | V24: OA,Onverwacht Province | W24: OA,Onverwacht Province | X24: OA | Y24: A | Z24: A | AA24: A | AB24: A | AC24: A | AD24: A | AE24: A | AF24: A | AG24: A | AH24: A | AI24: A | AJ24: A | AK24: A | AL24: A | AM24: A | AN24: A | AO24: A | AP24: A | AQ24: A | AR24: A | AS24: A | AT24: A | AU24: A | AV24: A | AW24: A | AX24: A | AY24: A | AZ24: OW,Onverwacht Province
A25: 20 | B25: Acoma | D25: {=index(systems,match($A25,INDEX(systems,0,1),),3)} -> 224.416 | E25: {=index(systems,match($A25,INDEX(systems,0,1),),4)} -> -62.259 | F25: =IFERROR(__xludf.DUMMYFUNCTION("let(row, match($B25&if($C25<>"""","" [""&$C25&""]"",""""),index(nebulae,,2),0),join("","",iferror(round(index(nebulae,row,5)/2,3),1),iferror(round(index(nebulae,row,6)/2,3),1),0))"),"1,1,0") -> 1,1,0 | G25: https://www.sarna.net/wiki/Acoma | H25: {=let(systemId,match(A25,index(systems,0,1),),refSystemId,match($H$1,index(systems,0,1),),x,index(systems,systemId,3),y,index(systems,systemId,4),refX,index(systems,refSystemId,3),refY,index(systems,refSystemId,4),round(sqrt((x-refX)^2+(y-refY)^2),3))} -> 232.892 | I25: U | J25: U | K25: U | L25: U | M25: U | N25: U | P25: FS,Crucis March,Markesan Operational Area,Region 1 | Q25: FS,Crucis March,Markesan Operational Area,Region 1 | R25: FS,Crucis March,Markesan Operational Area,Region 1 | S25: FS,Crucis March,Markesan Operational Area,Region 1 | T25: FS,Crucis March,Markesan Operational Area,Region 1 | U25: A | V25: A | W25: A | X25: A | Y25: A | Z25: A | AA25: A | AB25: A | AC25: A | AD25: A | AE25: A | AF25: A | AG25: A | AH25: A | AI25: A | AJ25: A | AK25: A | AL25: A | AM25: A | AN25: A | AO25: A | AP25: A | AQ25: A | AR25: A | AS25: A | AT25: A | AU25: A | AV25: A | AW25: A | AX25: A | AY25: A | AZ25: A
A26: 21 | B26: Aconcagua | D26: {=index(systems,match($A26,INDEX(systems,0,1),),3)} -> -275.03 | E26: {=index(systems,match($A26,INDEX(systems,0,1),),4)} -> -189.625 | F26: =IFERROR(__xludf.DUMMYFUNCTION("let(row, match($B26&if($C26<>"""","" [""&$C26&""]"",""""),index(nebulae,,2),0),join("","",iferror(round(index(nebulae,row,5)/2,3),1),iferror(round(index(nebulae,row,6)/2,3),1),0))"),"1,1,0") -> 1,1,0 | G26: https://www.sarna.net/wiki/Aconcagua | H26: {=let(systemId,match(A26,index(systems,0,1),),refSystemId,match($H$1,index(systems,0,1),),x,index(systems,systemId,3),y,index(systems,systemId,4),refX,index(systems,refSystemId,3),refY,index(systems,refSystemId,4),round(sqrt((x-refX)^2+(y-refY)^2),3))} -> 334.065 | I26: I | N26: FWL,Principality of Regulus | O26: FWL,Principality of Regulus | P26: FWL,Principality of Gibson | Q26: FWL,Principality of Gibson | R26: FWL,Principality of Gibson | S26: FWL,Principality of Gibson | T26: FWL,Principality of Gibson | U26: FWL,Principality of Gibson | V26: FWL,Principality of Gibson | W26: FWL,Principality of Gibson | X26: FWL,Principality of Gibson | Y26: FWL | Z26: FWL | AA26: FWL | AB26: FWL | AC26: FWL | AD26: FWL | AE26: FWL | AF26: FWL | AG26: FWL | AH26: FWL | AI26: FWL | AJ26: FWL | AK26: FWL | AL26: FWL | AM26: FWL | AN26: FWL | AO26: FWL | AP26: FWL | AQ26: FWL | AR26: FWL | AS26: I | AT26: I | AU26: I | AV26: I | AW26: I | AX26: FWL | AY26: FWL | AZ26: FWL
A27: 22 | B27: Acrux | D27: {=index(systems,match($A27,INDEX(systems,0,1),),3)} -> -352.026 | E27: {=index(systems,match($A27,INDEX(systems,0,1),),4)} -> 40.745 | F27: =IFERROR(__xludf.DUMMYFUNCTION("let(row, match($B27&if($C27<>"""","" [""&$C27&""]"",""""),index(nebulae,,2),0),join("","",iferror(round(index(nebulae,row,5)/2,3),1),iferror(round(index(nebulae,row,6)/2,3),1),0))"),"1,1,0") -> 1,1,0 | G27: https://www.sarna.net/wiki/Acrux | H27: {=let(systemId,match(A27,index(systems,0,1),),refSystemId,match($H$1,index(systems,0,1),),x,index(systems,systemId,3),y,index(systems,systemId,4),refX,index(systems,refSystemId,3),refY,index(systems,refSystemId,4),round(sqrt((x-refX)^2+(y-refY)^2),3))} -> 354.376 | I27: U | J27: U | K27: U | L27: U | M27: U | N27: U | P27: FWL | Q27: FWL | R27: FWL | S27: FWL | T27: FWL | U27: LC,Protectorate of Donegal,Alarion Province | V27: LC,Protectorate of Donegal,Alarion Province | W27: LC,Protectorate of Donegal,Alarion Province | X27: LC,Protectorate of Donegal,Alarion Province | Y27: LC,Protectorate of Donegal,Alarion Province | Z27: LC,Protectorate of Donegal,Alarion Province | AA27: FCL,Donegal March,Alarion Operational Area,Region 3 | AB27: FCL,Donegal March,Alarion Operational Area,Region 3 | AC27: FCL,Donegal March,Alarion Operational Area,Region 3 | AD27: FCL,Donegal March,Alarion Operational Area,Region 3 | AE27: FCL,Donegal March,Alarion Operational Area,Region 3 | AF27: FCL,Donegal March,Alarion Operational Area,Region 3 | AG27: FCL,Donegal March,Alarion Operational Area,Region 3 | AH27: LA,Donegal March,Alarion Operational Area,Region 3 | AI27: LA,Alarion Province | AJ27: LA,Alarion Province | AK27: LA,Alarion Province | AL27: LA,Alarion Province | AM27: LA,Alarion Province | AN27: LA,Alarion Province | AO27: LA,Alarion Province | AP27: LA,Alarion Province | AQ27: LA,Alarion Province,Buena Archonette | AR27: LA,Alarion Province,Buena Archonette | AS27: LA,Buena Province | AT27: LC,Buena Province | AU27: LC,Buena Province | AV27: LC,Buena Province | AW27: LC,Buena Province | AX27: LC,Buena Province | AY27: LC,Buena Province | AZ27: LC,Bolan Province
A28: 23 | B28: Acubens | D28: {=index(systems,match($A28,INDEX(systems,0,1),),3)} -> -52.221 | E28: {=index(systems,match($A28,INDEX(systems,0,1),),4)} -> -50.716 | F28: =IFERROR(__xludf.DUMMYFUNCTION("let(row, match($B28&if($C28<>"""","" [""&$C28&""]"",""""),index(nebulae,,2),0),join("","",iferror(round(index(nebulae,row,5)/2,3),1),iferror(round(index(nebulae,row,6)/2,3),1),0))"),"1,1,0") -> 1,1,0 | G28: https://www.sarna.net/wiki/Acubens | H28: {=let(systemId,match(A28,index(systems,0,1),),refSystemId,match($H$1,index(systems,0,1),),x,index(systems,systemId,3),y,index(systems,systemId,4),refX,index(systems,refSystemId,3),refY,index(systems,refSystemId,4),round(sqrt((x-refX)^2+(y-refY)^2),3))} -> 72.795 | I28: I | J28: I | K28: I | L28: I | M28: FWL | N28: FWL,Marik Commonwealth | O28: FWL,Marik Commonwealth | P28: FWL,Marik Commonwealth | Q28: FWL,Marik Commonwealth | R28: FWL,Marik Commonwealth | S28: FWL,Marik Commonwealth | T28: FWL,Marik Commonwealth | U28: FWL,Marik Commonwealth | V28: FWL,Marik Commonwealth | W28: FWL,Marik Commonwealth | X28: FWL | Y28: FWL | Z28: FWL | AA28: FWL | AB28: FWL | AC28: FWL | AD28: FWL | AE28: FWL | AF28: FWL | AG28: FWL | AH28: FWL | AI28: FWL | AJ28: FWL | AK28: FWL | AL28: FWL | AM28: FWL | AN28: FWL | AO28: FWL | AP28: FWL | AQ28: WB | AR28: CoF | AS28: RS,Prefecture VII | AT28: RS,Prefecture VII | AU28: RS,Prefecture VII | AV28: RS,Prefecture VII | AW28: I | AX28: FWL,Covenant Worlds | AY28: FWL,Covenant Worlds | AZ28: FWL,Covenant Worlds
A29: 24 | B29: Ad Duwayd | D29: {=index(systems,match($A29,INDEX(systems,0,1),),3)} -> 361.884 | E29: {=index(systems,match($A29,INDEX(systems,0,1),),4)} -> 374.511 | F29: =IFERROR(__xludf.DUMMYFUNCTION("let(row, match($B29&if($C29<>"""","" [""&$C29&""]"",""""),index(nebulae,,2),0),join("","",iferror(round(index(nebulae,row,5)/2,3),1),iferror(round(index(nebulae,row,6)/2,3),1),0))"),"1,1,0") -> 1,1,0 | G29: https://www.sarna.net/wiki/Ad_Duwayd | H29: {=let(systemId,match(A29,index(systems,0,1),),refSystemId,match($H$1,index(systems,0,1),),x,index(systems,systemId,3),y,index(systems,systemId,4),refX,index(systems,refSystemId,3),refY,index(systems,refSystemId,4),round(sqrt((x-refX)^2+(y-refY)^2),3))} -> 520.786 | I29: U | J29: U | K29: U | N29: DC,Pesht Military District,Pusht-i-rud Prefecture | O29: DC,Pesht Military District,Pusht-i-rud Prefecture | P29: DC,Pesht Military District,Pusht-i-rud Prefecture | Q29: DC,Pesht Military District,Pusht-i-rud Prefecture | R29: DC,Pesht Military District,Pusht-i-rud Prefecture | S29: DC,Pesht Military District,Pusht-i-rud Prefecture | T29: DC,Pesht Military District,Pusht-i-rud Prefecture | U29: DC,Pesht Military District,Pusht-i-rud Prefecture | V29: DC,Pesht Military District,Pusht-i-rud Prefecture | W29: DC,Pesht Military District,Pusht-i-rud Prefecture | X29: DC,Pesht Military District,Pusht-i-rud Prefecture | Y29: DC,Pesht Military District,Qandahar Prefecture | Z29: DC,Pesht Military District,Qandahar Prefecture | AA29: DC,Pesht Military District,Qandahar Prefecture | AB29: DC,Pesht Military District,Qandahar Prefecture | AC29: DC,Pesht Military District,Qandahar Prefecture | AD29: DC,Pesht Military District,Qandahar Prefecture | AE29: DC,Pesht Military District,Qandahar Prefecture | AF29: DC,Pesht Military District,Qandahar Prefecture | AG29: DC,Pesht Military District,Qandahar Prefecture | AH29: DC,Pesht Military District,Qandahar Prefecture | AI29: DC,Pesht Military District,Qandahar Prefecture | AJ29: DC,Pesht Military District,Qandahar Prefecture | AK29: DC,Pesht Military District,Qandahar Prefecture | AL29: DC,Pesht Military District,Qandahar Prefecture | AM29: DC,Pesht Military District,Qandahar Prefecture | AN29: DC,Pesht Military District,Qandahar Prefecture | AO29: DC,Pesht Military District,Qandahar Prefecture | AP29: DC,Pesht Military District,Qandahar Prefecture | AQ29: DC,Pesht Military District,Qandahar Prefecture | AR29: DC,Pesht Military District,Qandahar Prefecture | AS29: DC,Pesht Military District,Qandahar Prefecture | AT29: DC,Pesht Military District,Qandahar Prefecture | AU29: DC,Pesht Military District,Qandahar Prefecture | AV29: DC,Pesht Military District,Qandahar Prefecture | AW29: DC,Pesht Military District,Qandahar Prefecture | AX29: DC,Pesht Military District,Qandahar Prefecture | AY29: DC,Pesht Military District,Qandahar Prefecture | AZ29: DC,Pesht Military District,Qandahar Prefecture
A30: 25 | B30: Addasar | D30: {=index(systems,match($A30,INDEX(systems,0,1),),3)} -> -29.439 | E30: {=index(systems,match($A30,INDEX(systems,0,1),),4)} -> -516.52 | F30: =IFERROR(__xludf.DUMMYFUNCTION("let(row, match($B30&if($C30<>"""","" [""&$C30&""]"",""""),index(nebulae,,2),0),join("","",iferror(round(index(nebulae,row,5)/2,3),1),iferror(round(index(nebulae,row,6)/2,3),1),0))"),"1,1,0") -> 1,1,0 | G30: https://www.sarna.net/wiki/Addasar | H30: {=let(systemId,match(A30,index(systems,0,1),),refSystemId,match($H$1,index(systems,0,1),),x,index(systems,systemId,3),y,index(systems,systemId,4),refX,index(systems,refSystemId,3),refY,index(systems,refSystemId,4),round(sqrt((x-refX)^2+(y-refY)^2),3))} -> 517.358 | I30: U | J30: U | K30: U | L30: U | M30: U | P30: MOC,Luxen Province | Q30: MOC,Luxen Province | R30: MOC,Luxen Province | S30: MOC,Luxen Province | T30: MOC,Luxen Province | U30: MOC,Luxen Province | V30: MOC,Luxen Province | W30: MOC,Luxen Province | X30: MOC | Y30: MOC | Z30: MOC | AA30: MOC | AB30: MOC | AC30: MOC | AD30: MOC | AE30: MOC | AF30: MOC | AG30: MOC | AH30: MOC | AI30: MOC | AJ30: MOC | AK30: MOC | AL30: MOC | AM30: MOC | AN30: MOC | AO30: MOC | AP30: MOC | AQ30: MOC | AR30: MOC | AS30: MOC | AT30: MOC | AU30: MOC | AV30: MOC | AW30: MOC | AX30: MOC | AY30: MOC | AZ30: MOC
A31: 2856 | B31: Addhara | D31: {=index(systems,match($A31,INDEX(systems,0,1),),3)} -> -443.663 | E31: {=index(systems,match($A31,INDEX(systems,0,1),),4)} -> -293.348 | F31: =IFERROR(__xludf.DUMMYFUNCTION("let(row, match($B31&if($C31<>"""","" [""&$C31&""]"",""""),index(nebulae,,2),0),join("","",iferror(round(index(nebulae,row,5)/2,3),1),iferror(round(index(nebulae,row,6)/2,3),1),0))"),"1,1,0") -> 1,1,0 | G31: https://www.sarna.net/wiki/Addhara | H31: {=let(systemId,match(A31,index(systems,0,1),),refSystemId,match($H$1,index(systems,0,1),),x,index(systems,systemId,3),y,index(systems,systemId,4),refX,index(systems,refSystemId,3),refY,index(systems,refSystemId,4),round(sqrt((x-refX)^2+(y-refY)^2),3))} -> 531.874 | P31: U | Q31: U | R31: U | S31: U | T31: U | U31: U | V31: U | W31: U | X31: U | Y31: MH | Z31: MH | AA31: MH | AB31: MH | AC31: MH | AD31: MH | AE31: MH | AF31: MH | AG31: MH | AH31: MH | AI31: MH | AJ31: MH | AK31: MH | AL31: MH | AM31: MH | AN31: MH | AO31: MH | AP31: MH | AQ31: MH | AR31: MH | AS31: MH | AT31: MH | AU31: MH | AV31: MH | AW31: MH | AX31: MH | AY31: MH | AZ31: MH
A32: 26 | B32: Addicks | D32: {=index(systems,match($A32,INDEX(systems,0,1),),3)} -> 71.439 | E32: {=index(systems,match($A32,INDEX(systems,0,1),),4)} -> -0.696 | F32: =IFERROR(__xludf.DUMMYFUNCTION("let(row, match($B32&if($C32<>"""","" [""&$C32&""]"",""""),index(nebulae,,2),0),join("","",iferror(round(index(nebulae,row,5)/2,3),1),iferror(round(index(nebulae,row,6)/2,3),1),0))"),"1,1,0") -> 1,1,0 | G32: https://www.sarna.net/wiki/Addicks | H32: {=let(systemId,match(A32,index(systems,0,1),),refSystemId,match($H$1,index(systems,0,1),),x,index(systems,systemId,3),y,index(systems,systemId,4),refX,index(systems,refSystemId,3),refY,index(systems,refSystemId,4),round(sqrt((x-refX)^2+(y-refY)^2),3))} -> 71.442 | J32: I | K32: I | M32: TH | N32: TH,Lockdale Province | O32: TH,Lockdale Province | P32: TH,Lockdale Province | Q32: TH,Lockdale Province | R32: AE,Lockdale Province | S32: TH,Lockdale Province | T32: FS,Draconis March,Robinson Operational Area,Region 1 | U32: DC,Dieron Military District,Addicks Prefecture,Minor Capital | V32: DC,Dieron Military District,Addicks Prefecture,Minor Capital | W32: DC,Dieron Military District,Addicks Prefecture,Minor Capital | X32: FS,Draconis March,Robinson Operational Area,Region 1 | Y32: FS,Draconis March,Robinson Operational Area,Addicks PDZ | Z32: FS,Draconis March,Robinson Operational Area,Addicks PDZ | AA32: FCF,Draconis March,Robinson Operational Area,Addicks PDZ | AB32: FCF,Draconis March,Robinson Operational Area,Addicks PDZ | AC32: FCF,Draconis March,Robinson Operational Area,Addicks PDZ | AD32: FCF,Draconis March,Robinson Operational Area,Addicks PDZ | AE32: FCF,Draconis March,Robinson Operational Area,Addicks PDZ | AF32: FCF,Draconis March,Robinson Operational Area,Addicks PDZ | AG32: FCF,Draconis March,Robinson Operational Area,Addicks PDZ | AH32: FCF,Draconis March,Robinson Operational Area,Addicks PDZ | AI32: FCF,Draconis March,Robinson Operational Area,Addicks PDZ | AJ32: FCF,Draconis March,Robinson Operational Area,Addicks PDZ | AK32: FCF,Draconis March,Robinson Operational Area,Addicks PDZ | AL32: FCF,Draconis March,Robinson Operational Area,Addicks PDZ | AM32: FCF,Draconis March,Robinson Operational Area,Addicks PDZ | AN32: FCF,Draconis March,Robinson Operational Area,Addicks PDZ | AO32: FS,Draconis March,Robinson Operational Area,Addicks PDZ | AP32: D(FS,WB) | AQ32: WB | AR32: CoF | AS32: RS,Prefecture III | AT32: RS,Prefecture III | AU32: RS,Prefecture III | AV32: RS,Prefecture III | AW32: I | AX32: DC,Dieron Military District,Ashio Prefecture | AY32: DC,Dieron Military District,Ashio Prefecture | AZ32: DC,Dieron Military District,Ashio Prefecture
A33: 27 | B33: Adelaide | D33: {=index(systems,match($A33,INDEX(systems,0,1),),3)} -> -250.471 | E33: {=index(systems,match($A33,INDEX(systems,0,1),),4)} -> 315.316 | F33: =IFERROR(__xludf.DUMMYFUNCTION("let(row, match($B33&if($C33<>"""","" [""&$C33&""]"",""""),index(nebulae,,2),0),join("","",iferror(round(index(nebulae,row,5)/2,3),1),iferror(round(index(nebulae,row,6)/2,3),1),0))"),"1,1,0") -> 1,1,0 | G33: https://www.sarna.net/wiki/Adelaide | H33: {=let(systemId,match(A33,index(systems,0,1),),refSystemId,match($H$1,index(systems,0,1),),x,index(systems,systemId,3),y,index(systems,systemId,4),refX,index(systems,refSystemId,3),refY,index(systems,refSystemId,4),round(sqrt((x-refX)^2+(y-refY)^2),3))} -> 402.691 | I33: U | J33: U | K33: U | L33: U | N33: LC,Protectorate of Donegal,Coventry Province | O33: LC,Protectorate of Donegal,Coventry Province | P33: LC,Protectorate of Donegal,Coventry Province | Q33: LC,Protectorate of Donegal,Coventry Province | R33: LC,Protectorate of Donegal,Coventry Province | S33: LC,Protectorate of Donegal,Coventry Province | T33: LC,Protectorate of Donegal,Coventry Province | U33: LC,Protectorate of Donegal,Coventry Province | V33: LC,Protectorate of Donegal,Coventry Province | W33: LC,Protectorate of Donegal,Coventry Province | X33: LC,Protectorate of Donegal,Coventry Province | Y33: LC,Protectorate of Donegal,Coventry Province | Z33: LC,Protectorate of Donegal,Coventry Province | AA33: FCL,Donegal March,Coventry Operational Area,Region 1 | AB33: FCL,Donegal March,Coventry Operational Area,Region 1 | AC33: FCL,Donegal March,Coventry Operational Area,Region 1 | AD33: FCL,Donegal March,Coventry Operational Area,Region 1 | AE33: FCL,Donegal March,Coventry Operational Area,Region 1 | AF33: FCL,Donegal March,Coventry Operational Area,Region 1 | AG33: FCL,Donegal March,Coventry Operational Area,Region 1 | AH33: LA,Donegal March,Coventry Operational Area,Region 1 | AI33: LA,Coventry Province,Melissia Theater | AJ33: LA,Coventry Province,Melissia Theater | AK33: LA,Coventry Province,Melissia Theater | AL33: LA,Coventry Province,Melissia Theater | AM33: LA,Coventry Province,Melissia Theater | AN33: LA,Coventry Province,Melissia Theater | AO33: LA,Coventry Province,Melissia Theater | AP33: LA,Coventry Province,Melissia Theater | AQ33: LA,Coventry Province,Melissia Theater | AR33: LA,Coventry Province,Melissia Theater | AS33: LA,Coventry Province,Melissia Theater | AT33: LC,Coventry Province,Melissia Theater | AU33: LC,Coventry Province,Melissia Theater | AV33: LC,Coventry Province,Melissia Theater | AW33: LC,Bucklands Theater | AX33: LC,Bucklands Theater | AY33: LC,Bucklands Theater | AZ33: LC,Bucklands Theater
A34: 28 | B34: Adelson | D34: {=index(systems,match($A34,INDEX(systems,0,1),),3)} -> 472.766 | E34: {=index(systems,match($A34,INDEX(systems,0,1),),4)} -> -245.354 | F34: =IFERROR(__xludf.DUMMYFUNCTION("let(row, match($B34&if($C34<>"""","" [""&$C34&""]"",""""),index(nebulae,,2),0),join("","",iferror(round(index(nebulae,row,5)/2,3),1),iferror(round(index(nebulae,row,6)/2,3),1),0))"),"1,1,0") -> 1,1,0 | G34: https://www.sarna.net/wiki/Adelson | H34: {=let(systemId,match(A34,index(systems,0,1),),refSystemId,match($H$1,index(systems,0,1),),x,index(systems,systemId,3),y,index(systems,systemId,4),refX,index(systems,refSystemId,3),refY,index(systems,refSystemId,4),round(sqrt((x-refX)^2+(y-refY)^2),3))} -> 532.641 | I34: U | J34: U | K34: U | L34: U | M34: U | N34: U | P34: FS,Crucis March,Minette Operational Area,Broken Wheel Combat Region | Q34: FS,Crucis March,Minette Operational Area,Broken Wheel Combat Region | R34: FS,Crucis March,Minette Operational Area,Broken Wheel Combat Region | S34: FS,Crucis March,Minette Operational Area,Broken Wheel Combat Region | T34: FS,Crucis March,Minette Operational Area,Broken Wheel Combat Region | U34: FS,Crucis March,Minette Operational Area,Broken Wheel Combat Region | V34: FS,Crucis March,Minette Operational Area,Broken Wheel Combat Region | W34: FS,Crucis March,Minette Operational Area,Broken Wheel Combat Region | X34: FS,Crucis March,Minette Operational Area,Broken Wheel Combat Region | Y34: FS,Crucis March,Minette Operational Area,Broken Wheel Combat Region | Z34: FS,Crucis March,Minette Operational Area,Broken Wheel Combat Region | AA34: FCF,Crucis March,Minette Operational Area,Broken Wheel Combat Region | AB34: FCF,Crucis March,Minette Operational Area,Broken Wheel Combat Region | AC34: FCF,Crucis March,Minette Operational Area,Broken Wheel Combat Region | AD34: FCF,Crucis March,Minette Operational Area,Broken Wheel Combat Region | AE34: FCF,Crucis March,Minette Operational Area,Broken Wheel Combat Region | AF34: FCF,Crucis March,Minette Operational Area,Broken Wheel Combat Region | AG34: FCF,Crucis March,Minette Operational Area,Broken Wheel Combat Region | AH34: FCF,Crucis March,Minette Operational Area,Broken Wheel Combat Region | AI34: FCF,Crucis March,Minette Operational Area,Broken Wheel Combat Region | AJ34: FCF,Crucis March,Minette Operational Area,Broken Wheel Combat Region | AK34: FCF,Crucis March,Minette Operational Area,Broken Wheel Combat Region | AL34: FCF,Crucis March,Minette Operational Area,Broken Wheel Combat Region | AM34: FCF,Crucis March,Minette Operational Area,Broken Wheel Combat Region | AN34: FCF,Crucis March,Minette Operational Area,Broken Wheel Combat Region | AO34: FS,Crucis March,Minette Operational Area,Broken Wheel Combat Region | AP34: FS,Crucis March,Minette Operational Area,Broken Wheel Combat Region | AQ34: FS,Crucis March,Minette Operational Area,Broken Wheel Combat Region | AR34: FS,Periphery March,Anjin Muerto Operational Area,Broken Wheel Combat Region | AS34: FS,Periphery March,Anjin Muerto Operational Area,Broken Wheel Combat Region | AT34: FS,Periphery March,Anjin Muerto Operational Area,Broken Wheel Combat Region | AU34: FS,Periphery March,Anjin Muerto Operational Area,Broken Wheel Combat Region | AV34: FS,Periphery March,Anjin Muerto Operational Area,Broken Wheel Combat Region | AW34: FS,Periphery March,Anjin Muerto Operational Area,Broken Wheel Combat Region | AX34: FS,Periphery March,Anjin Muerto Operational Area,Broken Wheel Combat Region | AY34: FS,Periphery March,Anjin Muerto Operational Area,Broken Wheel Combat Region | AZ34: FS,Periphery March,Anjin Muerto Operational Area,Broken Wheel Combat Region
A35: 29 | B35: Adhafera | D35: {=index(systems,match($A35,INDEX(systems,0,1),),3)} -> -105.278 | E35: {=index(systems,match($A35,INDEX(systems,0,1),),4)} -> -51.227 | F35: =IFERROR(__xludf.DUMMYFUNCTION("let(row, match($B35&if($C35<>"""","" [""&$C35&""]"",""""),index(nebulae,,2),0),join("","",iferror(round(index(nebulae,row,5)/2,3),1),iferror(round(index(nebulae,row,6)/2,3),1),0))"),"1,1,0") -> 1,1,0 | G35: https://www.sarna.net/wiki/Adhafera | H35: {=let(systemId,match(A35,index(systems,0,1),),refSystemId,match($H$1,index(systems,0,1),),x,index(systems,systemId,3),y,index(systems,systemId,4),refX,index(systems,refSystemId,3),refY,index(systems,refSystemId,4),round(sqrt((x-refX)^2+(y-refY)^2),3))} -> 117.08 | I35: U | J35: U | K35: U | L35: U | M35: U | N35: U | P35: FWL,Stewart Confederation | Q35: FWL,Stewart Confederation | R35: FWL,Stewart Confederation | S35: FWL,Stewart Confederation | T35: FWL,Stewart Confederation | U35: FWL,Stewart Confederation | V35: FWL,Stewart Confederation | W35: FWL,Stewart Confederation | X35: FWL,Stewart Confederation | Y35: FWL,Stewart Commonality | Z35: FWL,Stewart Commonality | AA35: FWL,Stewart Commonality | AB35: FWL,Stewart Commonality | AC35: FWL,Stewart Commonality | AD35: FWL,Stewart Commonality | AE35: FWL,Stewart Commonality | AF35: FWL,Stewart Commonality | AG35: FWL,Stewart Commonality | AH35: FWL,Stewart Commonality | AI35: FWL,Stewart Commonality | AJ35: FWL,Stewart Commonality | AK35: FWL,Stewart Commonality | AL35: FWL,Stewart Commonality | AM35: FWL,Stewart Commonality | AN35: FWL,Stewart Commonality | AO35: FWL,Stewart Commonality | AP35: FWL,Stewart Commonality | AQ35: FWL,Stewart Commonality | AR35: FWL,Stewart Commonality | AS35: SC | AT35: RS,Prefecture VII | AU35: RS,Prefecture VII | AV35: RS,Prefecture VII | AW35: I | AX35: WE | AY35: WE | AZ35: FWL,Clan Protectorate
A36: 30 | B36: Adhara | C36: Trip (3040+) | D36: {=index(systems,match($A36,INDEX(systems,0,1),),3)} -> -123.314 | E36: {=index(systems,match($A36,INDEX(systems,0,1),),4)} -> -468.96 | F36: =IFERROR(__xludf.DUMMYFUNCTION("let(row, match($B36&if($C36<>"""","" [""&$C36&""]"",""""),index(nebulae,,2),0),join("","",iferror(round(index(nebulae,row,5)/2,3),1),iferror(round(index(nebulae,row,6)/2,3),1),0))"),"1,1,0") -> 1,1,0 | G36: https://www.sarna.net/wiki/Trip | H36: {=let(systemId,match(A36,index(systems,0,1),),refSystemId,match($H$1,index(systems,0,1),),x,index(systems,systemId,3),y,index(systems,systemId,4),refX,index(systems,refSystemId,3),refY,index(systems,refSystemId,4),round(sqrt((x-refX)^2+(y-refY)^2),3))} -> 484.902 | I36: U | J36: U | K36: U | L36: U | M36: U | N36: U | P36: MOC,Canopus District | Q36: MOC,Canopus District | R36: MOC,Canopus District | S36: MOC,Canopus District | T36: MOC,Canopus District | U36: MOC,Canopus District | V36: MOC,Canopus District | W36: MOC,Canopus District | X36: MOC | Y36: MOC | Z36: MOC | AA36: MOC | AB36: MOC | AC36: MOC | AD36: MOC | AE36: MOC | AF36: MOC | AG36: MOC | AH36: MOC | AI36: MOC | AJ36: MOC | AK36: MOC | AL36: MOC | AM36: MOC | AN36: MOC | AO36: MOC | AP36: MOC | AQ36: MOC | AR36: MOC | AS36: MOC | AT36: MOC | AU36: MOC | AV36: MOC | AW36: MOC | AX36: MOC | AY36: MOC | AZ36: MOC
A37: 31 | B37: Adherlwin | D37: {=index(systems,match($A37,INDEX(systems,0,1),),3)} -> -134.304 | E37: {=index(systems,match($A37,INDEX(systems,0,1),),4)} -> -418.682 | F37: =IFERROR(__xludf.DUMMYFUNCTION("let(row, match($B37&if($C37<>"""","" [""&$C37&""]"",""""),index(nebulae,,2),0),join("","",iferror(round(index(nebulae,row,5)/2,3),1),iferror(round(index(nebulae,row,6)/2,3),1),0))"),"1,1,0") -> 1,1,0 | G37: https://www.sarna.net/wiki/Adherlwin | H37: {=let(systemId,match(A37,index(systems,0,1),),refSystemId,match($H$1,index(systems,0,1),),x,index(systems,systemId,3),y,index(systems,systemId,4),refX,index(systems,refSystemId,3),refY,index(systems,refSystemId,4),round(sqrt((x-refX)^2+(y-refY)^2),3))} -> 439.696 | I37: U | J37: U | K37: U | L37: U | M37: U | N37: MOC | O37: MOC | P37: MOC,Canopus District | Q37: MOC,Canopus District | R37: MOC,Canopus District | S37: MOC,Canopus District | T37: MOC,Canopus District | U37: MOC,Canopus District | V37: MOC,Canopus District | W37: MOC,Canopus District | X37: MOC | Y37: MOC | Z37: MOC | AA37: MOC | AB37: MOC | AC37: MOC | AD37: MOC | AE37: MOC | AF37: MOC | AG37: MOC | AH37: MOC | AI37: MOC | AJ37: MOC | AK37: MOC | AL37: MOC | AM37: MOC | AN37: MOC | AO37: MOC | AP37: MOC | AQ37: MOC | AR37: MOC | AS37: MOC | AT37: MOC | AU37: MOC | AV37: MOC | AW37: MOC | AX37: MOC | AY37: MOC | AZ37: MOC
A38: 32 | B38: Adler | D38: {=index(systems,match($A38,INDEX(systems,0,1),),3)} -> 155.257 | E38: {=index(systems,match($A38,INDEX(systems,0,1),),4)} -> -210.669 | F38: =IFERROR(__xludf.DUMMYFUNCTION("let(row, match($B38&if($C38<>"""","" [""&$C38&""]"",""""),index(nebulae,,2),0),join("","",iferror(round(index(nebulae,row,5)/2,3),1),iferror(round(index(nebulae,row,6)/2,3),1),0))"),"1,1,0") -> 1,1,0 | G38: https://www.sarna.net/wiki/Adler | H38: {=let(systemId,match(A38,index(systems,0,1),),refSystemId,match($H$1,index(systems,0,1),),x,index(systems,systemId,3),y,index(systems,systemId,4),refX,index(systems,refSystemId,3),refY,index(systems,refSystemId,4),round(sqrt((x-refX)^2+(y-refY)^2),3))} -> 261.699 | I38: U | J38: U | K38: U | L38: U | M38: U | N38: U | P38: CC,St. Ives Commonality,Region 3 | Q38: CC,St. Ives Commonality,Region 3 | R38: CC,St. Ives Commonality,Region 3 | S38: CC,St. Ives Commonality,Region 3 | T38: CC,St. Ives Commonality,Region 3 | U38: CC,St. Ives Commonality,Region 3 | V38: CC,St. Ives Commonality,Region 3 | W38: A | X38: A | Y38: A | Z38: A | AA38: A | AB38: A | AC38: A | AD38: A | AE38: A | AF38: A | AG38: A | AH38: A | AI38: A | AJ38: A | AK38: A | AL38: A | AM38: A | AN38: A | AO38: A | AP38: A | AQ38: A | AR38: A | AS38: A | AT38: A | AU38: A | AV38: A | AW38: A | AX38: A | AY38: A | AZ38: A
A39: 33 | B39: Adrar | D39: {=index(systems,match($A39,INDEX(systems,0,1),),3)} -> -4.382 | E39: {=index(systems,match($A39,INDEX(systems,0,1),),4)} -> -409.233 | F39: =IFERROR(__xludf.DUMMYFUNCTION("let(row, match($B39&if($C39<>"""","" [""&$C39&""]"",""""),index(nebulae,,2),0),join("","",iferror(round(index(nebulae,row,5)/2,3),1),iferror(round(index(nebulae,row,6)/2,3),1),0))"),"1,1,0") -> 1,1,0 | G39: https://www.sarna.net/wiki/Adrar | H39: {=let(systemId,match(A39,index(systems,0,1),),refSystemId,match($H$1,index(systems,0,1),),x,index(systems,systemId,3),y,index(systems,systemId,4),refX,index(systems,refSystemId,3),refY,index(systems,refSystemId,4),round(sqrt((x-refX)^2+(y-refY)^2),3))} -> 409.256 | I39: U | J39: U | K39: U | L39: U | M39: U | N39: U | P39: CC,Sian Commonality,Region 13 | Q39: CC,Sian Commonality,Region 13 | R39: CC,Sian Commonality,Region 13 | S39: CC,Sian Commonality,Region 13 | T39: CC,Sian Commonality,Region 13 | U39: CC,Sian Commonality,Region 13 | V39: CC,Sian Commonality,Region 13 | W39: CC,Sian Commonality,Region 13 | X39: A | Y39: A | Z39: A | AA39: A | AB39: A | AC39: A | AD39: A | AE39: A | AF39: A | AG39: A | AH39: A | AI39: A | AJ39: A | AK39: A | AL39: A | AM39: A | AN39: A | AO39: A | AP39: A | AQ39: A | AR39: A | AS39: A | AT39: A | AU39: A | AV39: A | AW39: A | AX39: A | AY39: A | AZ39: A
A40: 34 | B40: Adrian | D40: {=index(systems,match($A40,INDEX(systems,0,1),),3)} -> 449.254 | E40: {=index(systems,match($A40,INDEX(systems,0,1),),4)} -> 28.13 | F40: =IFERROR(__xludf.DUMMYFUNCTION("let(row, match($B40&if($C40<>"""","" [""&$C40&""]"",""""),index(nebulae,,2),0),join("","",iferror(round(index(nebulae,row,5)/2,3),1),iferror(round(index(nebulae,row,6)/2,3),1),0))"),"1,1,0") -> 1,1,0 | G40: https://www.sarna.net/wiki/Adrian | H40: {=let(systemId,match(A40,index(systems,0,1),),refSystemId,match($H$1,index(systems,0,1),),x,index(systems,systemId,3),y,index(systems,systemId,4),refX,index(systems,refSystemId,3),refY,index(systems,refSystemId,4),round(sqrt((x-refX)^2+(y-refY)^2),3))} -> 450.134 | N40: FS,Draconis March,Woodbine Operational Area,Region 1 | O40: FS,Draconis March,Woodbine Operational Area,Region 1 | P40: FS,Draconis March,Woodbine Operational Area,Region 1 | Q40: FS,Draconis March,Woodbine Operational Area,Region 1 | R40: FS,Draconis March,Woodbine Operational Area,Region 1 | S40: FS,Draconis March,Woodbine Operational Area,Region 1 | T40: FS,Draconis March,Woodbine Operational Area,Region 1 | U40: FS,Draconis March,Woodbine Operational Area,Region 3 | V40: FS,Draconis March,Woodbine Operational Area,Region 3 | W40: FS,Draconis March,Woodbine Operational Area,Region 3 | X40: FS,Draconis March,Woodbine Operational Area,Region 3 | Y40: FS,Draconis March,Woodbine Operational Area,Milligan PDZ | Z40: FS,Draconis March,Woodbine Operational Area,Milligan PDZ | AA40: FCF,Draconis March,Woodbine Operational Area,Milligan PDZ | AB40: FCF,Draconis March,Woodbine Operational Area,Milligan PDZ | AC40: FCF,Draconis March,Woodbine Operational Area,Milligan PDZ | AD40: FCF,Draconis March,Woodbine Operational Area,Milligan PDZ | AE40: FCF,Draconis March,Woodbine Operational Area,Milligan PDZ | AF40: FCF,Draconis March,Woodbine Operational Area,Milligan PDZ | AG40: FCF,Draconis March,Woodbine Operational Area,Milligan PDZ | AH40: FCF,Draconis March,Woodbine Operational Area,Milligan PDZ | AI40: FCF,Draconis March,Woodbine Operational Area,Milligan PDZ | AJ40: FCF,Draconis March,Woodbine Operational Area,Milligan PDZ | AK40: FCF,Draconis March,Woodbine Operational Area,Milligan PDZ | AL40: FCF,Draconis March,Woodbine Operational Area,Milligan PDZ | AM40: FCF,Draconis March,Woodbine Operational Area,Milligan PDZ | AN40: FCF,Draconis March,Woodbine Operational Area,Milligan PDZ | AO40: FS,Draconis March,Woodbine Operational Area,Milligan PDZ | AP40: FS,Draconis March,Woodbine Operational Area,Milligan PDZ | AQ40: FS,Draconis March,Woodbine Operational Area,Milligan PDZ | AR40: FS,Draconis March,Woodbine Operational Area,Milligan PDZ | AS40: FS,Draconis March,Woodbine Operational Area,Milligan PDZ | AT40: FS,Draconis March,Woodbine Operational Area,Milligan PDZ | AU40: FS,Draconis March,Woodbine Operational Area,Milligan PDZ | AV40: FS,Draconis March,Woodbine Operational Area,Milligan PDZ | AW40: FS,Draconis March,Milligan Operational Area,Milligan PDZ | AX40: DC,New Samarkand Military District,Tancredi Prefecture | AY40: DC,New Samarkand Military District,Tancredi Prefecture | AZ40: FS,Draconis March,Tancredi Operational Area,Milligan PDZ
A41: 2881 | B41: Aea | D41: {=index(systems,match($A41,INDEX(systems,0,1),),3)} -> 156.045 | E41: {=index(systems,match($A41,INDEX(systems,0,1),),4)} -> -426.071 | F41: =IFERROR(__xludf.DUMMYFUNCTION("let(row, match($B41&if($C41<>"""","" [""&$C41&""]"",""""),index(nebulae,,2),0),join("","",iferror(round(index(nebulae,row,5)/2,3),1),iferror(round(index(nebulae,row,6)/2,3),1),0))"),"1,1,0") -> 1,1,0 | G41: https://www.sarna.net/wiki/Aea | H41: {=let(systemId,match(A41,index(systems,0,1),),refSystemId,match($H$1,index(systems,0,1),),x,index(systems,systemId,3),y,index(systems,systemId,4),refX,index(systems,refSystemId,3),refY,index(systems,refSystemId,4),round(sqrt((x-refX)^2+(y-refY)^2),3))} -> 453.747 | I41: U | J41: U | K41: U | L41: U | M41: U | N41: U | P41: U | Q41: U | R41: U | S41: U | T41: U | U41: U | V41: U | W41: U | X41: U | Y41: AuC | Z41: I | AA41: TC,Hyades Union | AB41: TC,Hyades Union | AC41: TC,Hyades Union | AD41: TC,Hyades Union | AE41: TC,Hyades Union | AF41: TC,Hyades Union | AG41: TC,Hyades Union | AH41: TC,Hyades Union | AI41: TC,Hyades Union | AJ41: TC,Hyades Union | AK41: TC,Hyades Union | AL41: TC,Hyades Union | AM41: TC,Hyades Union | AN41: TC,Hyades Union | AO41: TC,Hyades Union | AP41: TC,Hyades Union | AQ41: A | AR41: A | AS41: A | AT41: A | AU41: A | AV41: A | AW41: A | AX41: A | AY41: A | AZ41: A
A42: 35 | B42: Aer | C42: Finnalon (2822+) | D42: {=index(systems,match($A42,INDEX(systems,0,1),),3)} -> 55.145 | E42: {=index(systems,match($A42,INDEX(systems,0,1),),4)} -> -187.635 | F42: =IFERROR(__xludf.DUMMYFUNCTION("let(row, match($B42&if($C42<>"""","" [""&$C42&""]"",""""),index(nebulae,,2),0),join("","",iferror(round(index(nebulae,row,5)/2,3),1),iferror(round(index(nebulae,row,6)/2,3),1),0))"),"1,1,0") -> 1,1,0 | G42: https://www.sarna.net/wiki/Finnalon | H42: {=let(systemId,match(A42,index(systems,0,1),),refSystemId,match($H$1,index(systems,0,1),),x,index(systems,systemId,3),y,index(systems,systemId,4),refX,index(systems,refSystemId,3),refY,index(systems,refSystemId,4),round(sqrt((x-refX)^2+(y-refY)^2),3))} -> 195.571 | I42: U | J42: U | K42: U | L42: U | M42: U | N42: U | P42: CC,Capella Commonality,Region 3 | Q42: CC,Capella Commonality,Region 3 | R42: CC,Capella Commonality,Region 3 | S42: CC,Capella Commonality,Region 3 | T42: CC,Capella Commonality,Region 3 | U42: CC,Capella Commonality,Region 3 | V42: CC,Capella Commonality,Region 3 | W42: A | X42: A | Y42: A | Z42: A | AA42: A | AB42: A | AC42: A | AD42: A | AE42: A | AF42: A | AG42: A | AH42: A | AI42: A | AJ42: A | AK42: A | AL42: A | AM42: A | AN42: A | AO42: A | AP42: A | AQ42: A | AR42: A | AS42: A | AT42: A | AU42: A | AV42: A | AW42: A | AX42: A | AY42: A | AZ42: A
A43: 36 | B43: Afarsin | D43: {=index(systems,match($A43,INDEX(systems,0,1),),3)} -> -216.314 | E43: {=index(systems,match($A43,INDEX(systems,0,1),),4)} -> -369.872 | F43: =IFERROR(__xludf.DUMMYFUNCTION("let(row, match($B43&if($C43<>"""","" [""&$C43&""]"",""""),index(nebulae,,2),0),join("","",iferror(round(index(nebulae,row,5)/2,3),1),iferror(round(index(nebulae,row,6)/2,3),1),0))"),"1,1,0") -> 1,1,0 | G43: https://www.sarna.net/wiki/Afarsin | H43: {=let(systemId,match(A43,index(systems,0,1),),refSystemId,match($H$1,index(systems,0,1),),x,index(systems,systemId,3),y,index(systems,systemId,4),refX,index(systems,refSystemId,3),refY,index(systems,refSystemId,4),round(sqrt((x-refX)^2+(y-refY)^2),3))} -> 428.482 | I43: U | J43: U | K43: U | L43: U | M43: U | N43: MOC | O43: MOC | P43: MOC,Canopus District | Q43: MOC,Canopus District | R43: MOC,Canopus District | S43: MOC,Canopus District | T43: MOC,Canopus District | U43: MOC,Canopus District | V43: MOC,Canopus District | W43: MOC,Canopus District | X43: MOC | Y43: MOC | Z43: MOC | AA43: MOC | AB43: MOC | AC43: MOC | AD43: MOC | AE43: MOC | AF43: MOC | AG43: MOC | AH43: MOC | AI43: MOC | AJ43: MOC | AK43: MOC | AL43: MOC | AM43: MOC | AN43: MOC | AO43: MOC | AP43: MOC | AQ43: MOC | AR43: MOC | AS43: MOC | AT43: MOC | AU43: MOC | AV43: MOC | AW43: MOC | AX43: MOC | AY43: MOC | AZ43: MOC
A44: 37 | B44: Afleir | D44: {=index(systems,match($A44,INDEX(systems,0,1),),3)} -> -51.281 | E44: {=index(systems,match($A44,INDEX(systems,0,1),),4)} -> -2.977 | F44: =IFERROR(__xludf.DUMMYFUNCTION("let(row, match($B44&if($C44<>"""","" [""&$C44&""]"",""""),index(nebulae,,2),0),join("","",iferror(round(index(nebulae,row,5)/2,3),1),iferror(round(index(nebulae,row,6)/2,3),1),0))"),"1,1,0") -> 1,1,0 | G44: https://www.sarna.net/wiki/Afleir | H44: {=let(systemId,match(A44,index(systems,0,1),),refSystemId,match($H$1,index(systems,0,1),),x,index(systems,systemId,3),y,index(systems,systemId,4),refX,index(systems,refSystemId,3),refY,index(systems,refSystemId,4),round(sqrt((x-refX)^2+(y-refY)^2),3))} -> 51.367 | I44: U | J44: U | K44: U | L44: U | M44: TH | N44: TH,Tyrfing Province | O44: TH,Tyrfing Province | P44: TH,Tyrfing Province | Q44: TH,Tyrfing Province | R44: AE,Tyrfing Province | S44: TH,Tyrfing Province | T44: LC,Federation of Skye,Isle of Skye | U44: LC,Federation of Skye,Isle of Skye | V44: LC,Federation of Skye,Isle of Skye | W44: LC,Federation of Skye,Isle of Skye | X44: A | Y44: A | Z44: A | AA44: A | AB44: A | AC44: A | AD44: A | AE44: A | AF44: A | AG44: A | AH44: A | AI44: A | AJ44: A | AK44: A | AL44: A | AM44: A | AN44: A | AO44: A | AP44: A | AQ44: A | AR44: A | AS44: A | AT44: A | AU44: A | AV44: A | AW44: A | AX44: A | AY44: A | AZ44: A
A45: 38 | B45: Agador | C45: Yance I | D45: {=index(systems,match($A45,INDEX(systems,0,1),),3)} -> 69.791 | E45: {=index(systems,match($A45,INDEX(systems,0,1),),4)} -> 51.65 | F45: =IFERROR(__xludf.DUMMYFUNCTION("let(row, match($B45&if($C45<>"""","" [""&$C45&""]"",""""),index(nebulae,,2),0),join("","",iferror(round(index(nebulae,row,5)/2,3),1),iferror(round(index(nebulae,row,6)/2,3),1),0))"),"1,1,0") -> 1,1,0 | G45: https://www.sarna.net/wiki/Yance | H45: {=let(systemId,match(A45,index(systems,0,1),),refSystemId,match($H$1,index(systems,0,1),),x,index(systems,systemId,3),y,index(systems,systemId,4),refX,index(systems,refSystemId,3),refY,index(systems,refSystemId,4),round(sqrt((x-refX)^2+(y-refY)^2),3))} -> 86.825 | J45: I | K45: AG | L45: DC | M45: DC | N45: DC,Benjamin Military District,Ashio Prefecture | O45: DC,Benjamin Military District,Ashio Prefecture | P45: DC,Benjamin Military District,Ashio Prefecture | Q45: DC,Benjamin Military District,Ashio Prefecture | R45: DC,Benjamin Military District,Ashio Prefecture | S45: DC,Benjamin Military District,Ashio Prefecture | T45: DC,Benjamin Military District,Ashio Prefecture | U45: DC,Dieron Military District,Ashio Prefecture | V45: DC,Dieron Military District,Ashio Prefecture | W45: DC,Dieron Military District,Ashio Prefecture | X45: DC,Dieron Military District,Ashio Prefecture | Y45: DC,Dieron Military District,Ashio Prefecture | Z45: DC,Dieron Military District,Ashio Prefecture | AA45: DC,Dieron Military District,Ashio Prefecture | AB45: DC,Dieron Military District,Ashio Prefecture | AC45: DC,Dieron Military District,Ashio Prefecture | AD45: DC,Dieron Military District,Ashio Prefecture | AE45: DC,Dieron Military District,Ashio Prefecture | AF45: DC,Dieron Military District,Ashio Prefecture | AG45: DC,Dieron Military District,Ashio Prefecture | AH45: DC,Dieron Military District,Ashio Prefecture | AI45: DC,Dieron Military District,Ashio Prefecture | AJ45: DC,Dieron Military District,Ashio Prefecture | AK45: DC,Dieron Military District,Ashio Prefecture | AL45: DC,Dieron Military District,Ashio Prefecture | AM45: DC,Dieron Military District,Ashio Prefecture | AN45: DC,Dieron Military District,Ashio Prefecture | AO45: DC,Dieron Military District,Ashio Prefecture | AP45: DC,Dieron Military District,Ashio Prefecture | AQ45: DC,Dieron Military District,Ashio Prefecture | AR45: DC,Dieron Military District,Ashio Prefecture | AS45: RS,Prefecture II | AT45: RS,Prefecture II | AU45: RS,Prefecture II | AV45: RS,Prefecture II | AW45: DC,Benjamin Military District,Algedi Prefecture | AX45: DC,Dieron Military District,Ashio Prefecture | AY45: DC,Dieron Military District,Ashio Prefecture | AZ45: DC,Dieron Military District,Ashio Prefecture
A46: 39 | B46: Agematsu | D46: {=index(systems,match($A46,INDEX(systems,0,1),),3)} -> 253.838 | E46: {=index(systems,match($A46,INDEX(systems,0,1),),4)} -> 185.545 | F46: =IFERROR(__xludf.DUMMYFUNCTION("let(row, match($B46&if($C46<>"""","" [""&$C46&""]"",""""),index(nebulae,,2),0),join("","",iferror(round(index(nebulae,row,5)/2,3),1),iferror(round(index(nebulae,row,6)/2,3),1),0))"),"1,1,0") -> 1,1,0 | G46: https://www.sarna.net/wiki/Agematsu | H46: {=let(systemId,match(A46,index(systems,0,1),),refSystemId,match($H$1,index(systems,0,1),),x,index(systems,systemId,3),y,index(systems,systemId,4),refX,index(systems,refSystemId,3),refY,index(systems,refSystemId,4),round(sqrt((x-refX)^2+(y-refY)^2),3))} -> 314.421 | K46: I | N46: DC,Galedon Military District,Oshika Prefecture | O46: DC,Galedon Military District,Oshika Prefecture | P46: DC,Galedon Military District,Oshika Prefecture | Q46: DC,Galedon Military District,Oshika Prefecture | R46: DC,Galedon Military District,Oshika Prefecture | S46: DC,Galedon Military District,Oshika Prefecture | T46: DC,Galedon Military District,Oshika Prefecture | U46: DC,Galedon Military District,Oshika Prefecture | V46: DC,Galedon Military District,Oshika Prefecture | W46: DC,Galedon Military District,Oshika Prefecture | X46: DC,Galedon Military District,Oshika Prefecture | Y46: DC,Galedon Military District,Oshika Prefecture | Z46: DC,Galedon Military District,Oshika Prefecture | AA46: DC,Galedon Military District,Oshika Prefecture | AB46: DC,Galedon Military District,Oshika Prefecture | AC46: DC,Galedon Military District,Oshika Prefecture | AD46: DC,Galedon Military District,Oshika Prefecture | AE46: DC,Galedon Military District,Oshika Prefecture | AF46: DC,Galedon Military District,Oshika Prefecture | AG46: DC,Galedon Military District,Oshika Prefecture | AH46: DC,Galedon Military District,Oshika Prefecture | AI46: DC,Galedon Military District,Oshika Prefecture | AJ46: DC,Galedon Military District,Oshika Prefecture | AK46: DC,Galedon Military District,Oshika Prefecture | AL46: DC,Galedon Military District,Oshika Prefecture | AM46: DC,Galedon Military District,Oshika Prefecture | AN46: DC,Galedon Military District,Oshika Prefecture | AO46: DC,Galedon Military District,Oshika Prefecture | AP46: DC,Galedon Military District,Oshika Prefecture | AQ46: DC,New Samarkand Military District,Oshika Prefecture | AR46: DC,New Samarkand Military District,Oshika Prefecture | AS46: DC,New Samarkand Military District,Oshika Prefecture | AT46: DC,New Samarkand Military District,Oshika Prefecture | AU46: DC,New Samarkand Military District,Oshika Prefecture | AV46: DC,New Samarkand Military District,Oshika Prefecture | AW46: DC,New Samarkand Military District,Oshika Prefecture | AX46: DC,New Samarkand Military District,Oshika Prefecture | AY46: DC,New Samarkand Military District,Oshika Prefecture | AZ46: DC,New Samarkand Military District,Oshika Prefecture
A47: 40 | B47: Aggstein | D47: {=index(systems,match($A47,INDEX(systems,0,1),),3)} -> 219.606 | E47: {=index(systems,match($A47,INDEX(systems,0,1),),4)} -> -203.11 | F47: =IFERROR(__xludf.DUMMYFUNCTION("let(row, match($B47&if($C47<>"""","" [""&$C47&""]"",""""),index(nebulae,,2),0),join("","",iferror(round(index(nebulae,row,5)/2,3),1),iferror(round(index(nebulae,row,6)/2,3),1),0))"),"1,1,0") -> 1,1,0 | G47: https://www.sarna.net/wiki/Aggstein | H47: {=let(systemId,match(A47,index(systems,0,1),),refSystemId,match($H$1,index(systems,0,1),),x,index(systems,systemId,3),y,index(systems,systemId,4),refX,index(systems,refSystemId,3),refY,index(systems,refSystemId,4),round(sqrt((x-refX)^2+(y-refY)^2),3))} -> 299.133 | I47: U | J47: U | K47: U | L47: U | M47: U | N47: U | P47: FS,Capellan March,Kathil Operational Area,Region 2 | Q47: FS,Capellan March,Kathil Operational Area,Region 2 | R47: FS,Capellan March,Kathil Operational Area,Region 2 | S47: FS,Capellan March,Kathil Operational Area,Region 2 | T47: FS,Capellan March,Kathil Operational Area,Region 2 | U47: FS,Capellan March,Kathil Operational Area,Region 2 | V47: FS,Capellan March,Kathil Operational Area,Region 2 | W47: FS,Capellan March,Kathil Operational Area,Region 2 | X47: A | Y47: A | Z47: A | AA47: A | AB47: A | AC47: A | AD47: A | AE47: A | AF47: A | AG47: A | AH47: A | AI47: A | AJ47: A | AK47: A | AL47: A | AM47: A | AN47: A | AO47: A | AP47: A | AQ47: A | AR47: A | AS47: A | AT47: A | AU47: A | AV47: A | AW47: A | AX47: A | AY47: A | AZ47: A
A48: 41 | B48: Agliana | D48: {=index(systems,match($A48,INDEX(systems,0,1),),3)} -> 389.805 | E48: {=index(systems,match($A48,INDEX(systems,0,1),),4)} -> -289.562 | F48: =IFERROR(__xludf.DUMMYFUNCTION("let(row, match($B48&if($C48<>"""","" [""&$C48&""]"",""""),index(nebulae,,2),0),join("","",iferror(round(index(nebulae,row,5)/2,3),1),iferror(round(index(nebulae,row,6)/2,3),1),0))"),"1,1,0") -> 1,1,0 | G48: https://www.sarna.net/wiki/Agliana | H48: {=let(systemId,match(A48,index(systems,0,1),),refSystemId,match($H$1,index(systems,0,1),),x,index(systems,systemId,3),y,index(systems,systemId,4),refX,index(systems,refSystemId,3),refY,index(systems,refSystemId,4),round(sqrt((x-refX)^2+(y-refY)^2),3))} -> 485.586 | I48: U | J48: U | N48: FS,Crucis March,Chirikof Operational Area,Region 3 | O48: FS,Crucis March,Chirikof Operational Area,Region 3 | P48: FS,Crucis March,Chirikof Operational Area,Region 3 | Q48: FS,Crucis March,Chirikof Operational Area,Region 3 | R48: FS,Crucis March,Chirikof Operational Area,Region 3 | S48: FS,Crucis March,Chirikof Operational Area,Region 3 | T48: FS,Crucis March,Chirikof Operational Area,Region 3 | U48: FS,Crucis March,Chirikof Operational Area,Region 3 | V48: FS,Crucis March,Chirikof Operational Area,Region 3 | W48: FS,Crucis March,Chirikof Operational Area,Region 3 | X48: FS,Crucis March,Chirikof Operational Area,Region 3 | Y48: FS,Crucis March,Chirikof Operational Area,Kearny Combat Region | Z48: FS,Crucis March,Chirikof Operational Area,Kearny Combat Region | AA48: FCF,Crucis March,Chirikof Operational Area,Kearny Combat Region | AB48: FCF,Crucis March,Chirikof Operational Area,Kearny Combat Region | AC48: FCF,Crucis March,Chirikof Operational Area,Kearny Combat Region | AD48: FCF,Crucis March,Chirikof Operational Area,Kearny Combat Region | AE48: FCF,Crucis March,Chirikof Operational Area,Kearny Combat Region | AF48: FCF,Crucis March,Chirikof Operational Area,Kearny Combat Region | AG48: FCF,Crucis March,Chirikof Operational Area,Kearny Combat Region | AH48: FCF,Crucis March,Chirikof Operational Area,Kearny Combat Region | AI48: FCF,Crucis March,Chirikof Operational Area,Kearny Combat Region | AJ48: FCF,Crucis March,Chirikof Operational Area,Kearny Combat Region | AK48: FCF,Crucis March,Chirikof Operational Area,Kearny Combat Region | AL48: FCF,Crucis March,Chirikof Operational Area,Kearny Combat Region | AM48: FCF,Crucis March,Chirikof Operational Area,Kearny Combat Region | AN48: FCF,Crucis March,Chirikof Operational Area,Kearny Combat Region | AO48: FS,Crucis March,Chirikof Operational Area,Kearny Combat Region | AP48: FS,Crucis March,Chirikof Operational Area,Kearny Combat Region | AQ48: FS,Crucis March,Chirikof Operational Area,Kearny Combat Region | AR48: FS,Periphery March,June Operational Area,Islamabad Combat Region | AS48: FS,Periphery March,June Operational Area,Islamabad Combat Region | AT48: FS,Periphery March,June Operational Area,Islamabad Combat Region | AU48: FS,Periphery March,June Operational Area,Islamabad Combat Region | AV48: FS,Periphery March,June Operational Area,Islamabad Combat Region | AW48: FS,Periphery March,June Operational Area,Islamabad Combat Region | AX48: FS,Periphery March,June Operational Area,Islamabad Combat Region | AY48: FS,Periphery March,June Operational Area,Islamabad Combat Region | AZ48: FS,Periphery March,June Operational Area,Islamabad Combat Region
A49: 42 | B49: Agmond | C49: Bornal (3130+) | D49: {=index(systems,match($A49,INDEX(systems,0,1),),3)} -> 395.843 | E49: {=index(systems,match($A49,INDEX(systems,0,1),),4)} -> -140.358 | F49: =IFERROR(__xludf.DUMMYFUNCTION("let(row, match($B49&if($C49<>"""","" [""&$C49&""]"",""""),index(nebulae,,2),0),join("","",iferror(round(index(nebulae,row,5)/2,3),1),iferror(round(index(nebulae,row,6)/2,3),1),0))"),"1,1,0") -> 1,1,0 | G49: https://www.sarna.net/wiki/Bornal | H49: {=let(systemId,match(A49,index(systems,0,1),),refSystemId,match($H$1,index(systems,0,1),),x,index(systems,systemId,3),y,index(systems,systemId,4),refX,index(systems,refSystemId,3),refY,index(systems,refSystemId,4),round(sqrt((x-refX)^2+(y-refY)^2),3))} -> 419.991 | I49: U | J49: U | K49: U | L49: U | M49: U | N49: U | P49: FS,Crucis March,Minette Operational Area,Point Barrow Combat Region | Q49: FS,Crucis March,Minette Operational Area,Point Barrow Combat Region | R49: FS,Crucis March,Minette Operational Area,Point Barrow Combat Region | S49: FS,Crucis March,Minette Operational Area,Point Barrow Combat Region | T49: FS,Crucis March,Minette Operational Area,Point Barrow Combat Region | U49: FS,Crucis March,Minette Operational Area,Point Barrow Combat Region | V49: FS,Crucis March,Minette Operational Area,Point Barrow Combat Region | W49: FS,Crucis March,Minette Operational Area,Point Barrow Combat Region | X49: FS,Crucis March,Minette Operational Area,Point Barrow Combat Region | Y49: A | Z49: A | AA49: A | AB49: A | AC49: A | AD49: A | AE49: A | AF49: A | AG49: A | AH49: A | AI49: A | AJ49: A | AK49: A | AL49: A | AM49: A | AN49: A | AO49: A | AP49: A | AQ49: A | AR49: A | AS49: A | AT49: A | AU49: A | AV49: FS,Crucis March,Minette Operational Area,Point Barrow Combat Region | AW49: FS,Crucis March,Minette Operational Area,Point Barrow Combat Region | AX49: FS,Crucis March,Minette Operational Area,Point Barrow Combat Region | AY49: FS,Crucis March,Minette Operational Area,Point Barrow Combat Region | AZ49: FS,Crucis March,Minette Operational Area,Point Barrow Combat Region
A50: 3158 | B50: Ahlat | D50: {=index(systems,match($A50,INDEX(systems,0,1),),3)} -> 207.051 | E50: {=index(systems,match($A50,INDEX(systems,0,1),),4)} -> -508.185 | F50: =IFERROR(__xludf.DUMMYFUNCTION("let(row, match($B50&if($C50<>"""","" [""&$C50&""]"",""""),index(nebulae,,2),0),join("","",iferror(round(index(nebulae,row,5)/2,3),1),iferror(round(index(nebulae,row,6)/2,3),1),0))"),"1,1,0") -> 1,1,0 | G50: https://www.sarna.net/wiki/Ahlat | H50: {=let(systemId,match(A50,index(systems,0,1),),refSystemId,match($H$1,index(systems,0,1),),x,index(systems,systemId,3),y,index(systems,systemId,4),refX,index(systems,refSystemId,3),refY,index(systems,refSystemId,4),round(sqrt((x-refX)^2+(y-refY)^2),3))} -> 548.746 | I50: U | J50: U | K50: U | L50: U | M50: U | N50: U | P50: U | Q50: U | R50: U | S50: U | T50: U | U50: U | V50: U | W50: U | X50: U | Y50: I | Z50: A | AA50: A | AB50: A | AC50: A | AD50: A | AE50: A | AF50: A | AG50: A | AH50: A | AI50: A | AJ50: A | AK50: A | AL50: A | AM50: A | AN50: A | AO50: A | AP50: A | AQ50: A | AR50: A | AS50: A | AT50: A | AU50: A | AV50: A | AW50: A | AX50: A | AY50: A | AZ50: A
A51: 43 | B51: Aigle | D51: {=index(systems,match($A51,INDEX(systems,0,1),),3)} -> -234.767 | E51: {=index(systems,match($A51,INDEX(systems,0,1),),4)} -> -19.069 | F51: =IFERROR(__xludf.DUMMYFUNCTION("let(row, match($B51&if($C51<>"""","" [""&$C51&""]"",""""),index(nebulae,,2),0),join("","",iferror(round(index(nebulae,row,5)/2,3),1),iferror(round(index(nebulae,row,6)/2,3),1),0))"),"1,1,0") -> 1,1,0 | G51: https://www.sarna.net/wiki/Aigle | H51: {=let(systemId,match(A51,index(systems,0,1),),refSystemId,match($H$1,index(systems,0,1),),x,index(systems,systemId,3),y,index(systems,systemId,4),refX,index(systems,refSystemId,3),refY,index(systems,refSystemId,4),round(sqrt((x-refX)^2+(y-refY)^2),3))} -> 235.54 | I51: U | J51: U | K51: U | L51: U | M51: U | N51: U | P51: LC,Protectorate of Donegal,Furillo Province | Q51: LC,Protectorate of Donegal,Furillo Province | R51: LC,Protectorate of Donegal,Furillo Province | S51: LC,Protectorate of Donegal,Furillo Province | T51: LC,Protectorate of Donegal,Furillo Province | U51: LC,Protectorate of Donegal,Furillo Province | V51: LC,Protectorate of Donegal,Furillo Province | W51: LC,Protectorate of Donegal,Furillo Province | X51: A | Y51: A | Z51: A | AA51: A | AB51: A | AC51: A | AD51: A | AE51: A | AF51: A | AG51: A | AH51: A | AI51: A | AJ51: A | AK51: A | AL51: A | AM51: A | AN51: A | AO51: A | AP51: A | AQ51: A | AR51: A | AS51: A | AT51: A | AU51: A | AV51: A | AW51: A | AX51: A | AY51: A | AZ51: A
A52: 44 | B52: Aiguebelle | D52: {=index(systems,match($A52,INDEX(systems,0,1),),3)} -> -384.879 | E52: {=index(systems,match($A52,INDEX(systems,0,1),),4)} -> 101.539 | F52: =IFERROR(__xludf.DUMMYFUNCTION("let(row, match($B52&if($C52<>"""","" [""&$C52&""]"",""""),index(nebulae,,2),0),join("","",iferror(round(index(nebulae,row,5)/2,3),1),iferror(round(index(nebulae,row,6)/2,3),1),0))"),"1,1,0") -> 1,1,0 | G52: https://www.sarna.net/wiki/Aiguebelle | H52: {=let(systemId,match(A52,index(systems,0,1),),refSystemId,match($H$1,index(systems,0,1),),x,index(systems,systemId,3),y,index(systems,systemId,4),refX,index(systems,refSystemId,3),refY,index(systems,refSystemId,4),round(sqrt((x-refX)^2+(y-refY)^2),3))} -> 398.048 | I52: U | J52: U | K52: U | L52: U | M52: U | N52: U | P52: LC,Protectorate of Donegal,Alarion Province | Q52: LC,Protectorate of Donegal,Alarion Province | R52: LC,Protectorate of Donegal,Alarion Province | S52: LC,Protectorate of Donegal,Alarion Province | T52: LC,Protectorate of Donegal,Alarion Province | U52: LC,Protectorate of Donegal,Alarion Province | V52: LC,Protectorate of Donegal,Alarion Province | W52: LC,Protectorate of Donegal,Alarion Province | X52: LC,Protectorate of Donegal,Alarion Province | Y52: LC,Protectorate of Donegal,Alarion Province | Z52: LC,Protectorate of Donegal,Alarion Province | AA52: FCL,Periphery March,Venaria Operational Area,Region 2 | AB52: FCL,Periphery March,Venaria Operational Area,Region 2 | AC52: FCL,Periphery March,Venaria Operational Area,Region 2 | AD52: FCL,Periphery March,Venaria Operational Area,Region 2 | AE52: FCL,Periphery March,Venaria Operational Area,Region 2 | AF52: FCL,Periphery March,Venaria Operational Area,Region 2 | AG52: FCL,Periphery March,Venaria Operational Area,Region 2 | AH52: LA,Periphery March,Venaria Operational Area,Region 2 | AI52: LA,Alarion Province | AJ52: LA,Alarion Province | AK52: LA,Alarion Province | AL52: LA,Alarion Province | AM52: LA,Alarion Province | AN52: LA,Alarion Province | AO52: LA,Alarion Province | AP52: LA,Alarion Province | AQ52: LA,Alarion Province | AR52: LA,Alarion Province | AS52: LA,Buena Province | AT52: LC,Buena Province | AU52: LC,Buena Province | AV52: LC,Buena Province | AW52: LC,Buena Province | AX52: LC,Buena Province | AY52: LC,Buena Province | AZ52: LC,Bolan Province
A53: 45 | B53: Aitutaki | D53: {=index(systems,match($A53,INDEX(systems,0,1),),3)} -> -164.636 | E53: {=index(systems,match($A53,INDEX(systems,0,1),),4)} -> -166.561 | F53: =IFERROR(__xludf.DUMMYFUNCTION("let(row, match($B53&if($C53<>"""","" [""&$C53&""]"",""""),index(nebulae,,2),0),join("","",iferror(round(index(nebulae,row,5)/2,3),1),iferror(round(index(nebulae,row,6)/2,3),1),0))"),"1,1,0") -> 1,1,0 | G53: https://www.sarna.net/wiki/Aitutaki | H53: {=let(systemId,match(A53,index(systems,0,1),),refSystemId,match($H$1,index(systems,0,1),),x,index(systems,systemId,3),y,index(systems,systemId,4),refX,index(systems,refSystemId,3),refY,index(systems,refSystemId,4),round(sqrt((x-refX)^2+(y-refY)^2),3))} -> 234.196 | I53: PR | J53: FWL,Principality of Regulus | K53: FWL,Principality of Regulus | L53: FWL,Principality of Regulus | M53: FWL,Principality of Regulus | N53: FWL,Principality of Regulus | O53: FWL,Principality of Regulus | P53: FWL,Principality of Regulus | Q53: FWL,Principality of Regulus | R53: FWL,Principality of Regulus | S53: FWL,Principality of Regulus | T53: FWL,Principality of Regulus | U53: FWL,Principality of Regulus | V53: FWL,Principality of Regulus | W53: FWL,Principality of Regulus | X53: FWL,Principality of Regulus | Y53: FWL,Principality of Regulus | Z53: FWL,Principality of Regulus | AA53: FWL,Principality of Regulus | AB53: FWL,Principality of Regulus | AC53: FWL,Principality of Regulus | AD53: FWL,Principality of Regulus | AE53: FWL,Principality of Regulus | AF53: FWL,Principality of Regulus | AG53: FWL,Principality of Regulus | AH53: FWL,Principality of Regulus | AI53: FWL,Principality of Regulus | AJ53: FWL,Principality of Regulus | AK53: FWL,Principality of Regulus | AL53: FWL,Principality of Regulus | AM53: FWL,Principality of Regulus | AN53: FWL,Principality of Regulus | AO53: FWL,Principality of Regulus | AP53: FWL,Principality of Regulus | AQ53: FWL,Principality of Regulus | AR53: PR | AS53: PR | AT53: PR | AU53: RF | AV53: I | AW53: I | AX53: FWL | AY53: FWL | AZ53: FWL
A54: 46 | B54: Aix-la-Chapelle | D54: {=index(systems,match($A54,INDEX(systems,0,1),),3)} -> 76.599 | E54: {=index(systems,match($A54,INDEX(systems,0,1),),4)} -> 162.627 | F54: =IFERROR(__xludf.DUMMYFUNCTION("let(row, match($B54&if($C54<>"""","" [""&$C54&""]"",""""),index(nebulae,,2),0),join("","",iferror(round(index(nebulae,row,5)/2,3),1),iferror(round(index(nebulae,row,6)/2,3),1),0))"),"1,1,0") -> 1,1,0 | G54: https://www.sarna.net/wiki/Aix-la-Chapelle | H54: {=let(systemId,match(A54,index(systems,0,1),),refSystemId,match($H$1,index(systems,0,1),),x,index(systems,systemId,3),y,index(systems,systemId,4),refX,index(systems,refSystemId,3),refY,index(systems,refSystemId,4),round(sqrt((x-refX)^2+(y-refY)^2),3))} -> 179.764 | I54: I | J54: I | K54: I | N54: DC,Benjamin Military District,Kajikazawa Prefecture | O54: DC,Benjamin Military District,Kajikazawa Prefecture | P54: DC,Benjamin Military District,Kajikazawa Prefecture | Q54: DC,Benjamin Military District,Kajikazawa Prefecture | R54: DC,Benjamin Military District,Kajikazawa Prefecture | S54: DC,Benjamin Military District,Kajikazawa Prefecture | T54: DC,Benjamin Military District,Kajikazawa Prefecture | U54: DC,Benjamin Military District,Kajikazawa Prefecture | V54: DC,Benjamin Military District,Kajikazawa Prefecture | W54: DC,Benjamin Military District,Kajikazawa Prefecture | X54: DC,Benjamin Military District,Kajikazawa Prefecture | Y54: DC,Benjamin Military District,Benjamin Prefecture | Z54: DC,Benjamin Military District,Benjamin Prefecture | AA54: DC,Benjamin Military District,Benjamin Prefecture | AB54: DC,Benjamin Military District,Benjamin Prefecture | AC54: DC,Benjamin Military District,Benjamin Prefecture | AD54: DC,Benjamin Military District,Benjamin Prefecture | AE54: DC,Benjamin Military District,Benjamin Prefecture | AF54: DC,Benjamin Military District,Benjamin Prefecture | AG54: DC,Benjamin Military District,Benjamin Prefecture | AH54: DC,Benjamin Military District,Benjamin Prefecture | AI54: DC,Benjamin Military District,Benjamin Prefecture | AJ54: DC,Benjamin Military District,Benjamin Prefecture | AK54: DC,Benjamin Military District,Benjamin Prefecture | AL54: DC,Benjamin Military District,Benjamin Prefecture | AM54: DC,Benjamin Military District,Benjamin Prefecture | AN54: DC,Benjamin Military District,Benjamin Prefecture | AO54: DC,Benjamin Military District,Benjamin Prefecture | AP54: DC,Benjamin Military District,Benjamin Prefecture | AQ54: DC,Benjamin Military District,Benjamin Prefecture | AR54: DC,Benjamin Military District,Benjamin Prefecture | AS54: DC,Benjamin Military District,Benjamin Prefecture | AT54: DC,Benjamin Military District,Benjamin Prefecture | AU54: DC,Benjamin Military District,Benjamin Prefecture | AV54: DC,Benjamin Military District,Benjamin Prefecture | AW54: DC,Benjamin Military District,Benjamin Prefecture | AX54: DC,Benjamin Military District,Benjamin Prefecture | AY54: DC,Benjamin Military District,Benjamin Prefecture | AZ54: DC,Benjamin Military District,Benjamin Prefecture
A55: 47 | B55: Akfata | D55: {=index(systems,match($A55,INDEX(systems,0,1),),3)} -> -381.799 | E55: {=index(systems,match($A55,INDEX(systems,0,1),),4)} -> 176.248 | F55: =IFERROR(__xludf.DUMMYFUNCTION("let(row, match($B55&if($C55<>"""","" [""&$C55&""]"",""""),index(nebulae,,2),0),join("","",iferror(round(index(nebulae,row,5)/2,3),1),iferror(round(index(nebulae,row,6)/2,3),1),0))"),"1,1,0") -> 1,1,0 | G55: https://www.sarna.net/wiki/Akfata | H55: {=let(systemId,match(A55,index(systems,0,1),),refSystemId,match($H$1,index(systems,0,1),),x,index(systems,systemId,3),y,index(systems,systemId,4),refX,index(systems,refSystemId,3),refY,index(systems,refSystemId,4),round(sqrt((x-refX)^2+(y-refY)^2),3))} -> 420.516 | N55: LC,Protectorate of Donegal,Alarion Province | O55: LC,Protectorate of Donegal,Alarion Province | P55: LC,Protectorate of Donegal,Alarion Province | Q55: LC,Protectorate of Donegal,Alarion Province | R55: LC,Protectorate of Donegal,Alarion Province | S55: LC,Protectorate of Donegal,Alarion Province | T55: LC,Protectorate of Donegal,Alarion Province | U55: LC,Protectorate of Donegal,Alarion Province | V55: LC,Protectorate of Donegal,Alarion Province | W55: LC,Protectorate of Donegal,Alarion Province | X55: LC,Protectorate of Donegal,Alarion Province | Y55: LC,Protectorate of Donegal,Alarion Province | Z55: LC,Protectorate of Donegal,Alarion Province | AA55: FCL,Periphery March,Venaria Operational Area,Region 1 | AB55: FCL,Periphery March,Venaria Operational Area,Region 1 | AC55: FCL,Periphery March,Venaria Operational Area,Region 1 | AD55: FCL,Periphery March,Venaria Operational Area,Region 1 | AE55: FCL,Periphery March,Venaria Operational Area,Region 1 | AF55: FCL,Periphery March,Venaria Operational Area,Region 1 | AG55: FCL,Periphery March,Venaria Operational Area,Region 1 | AH55: LA,Periphery March,Venaria Operational Area,Region 1 | AI55: LA,Alarion Province | AJ55: LA,Alarion Province | AK55: LA,Alarion Province | AL55: LA,Alarion Province | AM55: LA,Alarion Province | AN55: LA,Alarion Province | AO55: LA,Alarion Province | AP55: LA,Alarion Province | AQ55: LA,Alarion Province,Kaumberg Archonette | AR55: LA,Alarion Province,Kaumberg Archonette | AS55: LA,Buena Province,Kaumberg Archonette | AT55: LC,Buena Province | AU55: LC,Buena Province | AV55: LC,Buena Province | AW55: LC,Buena Province | AX55: LC,Buena Province | AY55: LC,Buena Province | AZ55: LC,Bolan Province
A56: 48 | B56: Al Hillah | D56: {=index(systems,match($A56,INDEX(systems,0,1),),3)} -> -25.374 | E56: {=index(systems,match($A56,INDEX(systems,0,1),),4)} -> 178.71 | F56: =IFERROR(__xludf.DUMMYFUNCTION("let(row, match($B56&if($C56<>"""","" [""&$C56&""]"",""""),index(nebulae,,2),0),join("","",iferror(round(index(nebulae,row,5)/2,3),1),iferror(round(index(nebulae,row,6)/2,3),1),0))"),"1,1,0") -> 1,1,0 | G56: https://www.sarna.net/wiki/Al_Hillah | H56: {=let(systemId,match(A56,index(systems,0,1),),refSystemId,match($H$1,index(systems,0,1),),x,index(systems,systemId,3),y,index(systems,systemId,4),refX,index(systems,refSystemId,3),refY,index(systems,refSystemId,4),round(sqrt((x-refX)^2+(y-refY)^2),3))} -> 180.502 | K56: TamP | L56: TamP | M56: LC,Tamar Pact | N56: LC,Tamar Pact,Camlann Shire | O56: LC,Tamar Pact,Camlann Shire | P56: LC,Tamar Pact,Camlann Shire | Q56: LC,Tamar Pact,Camlann Shire | R56: LC,Tamar Pact,Camlann Shire | S56: LC,Tamar Pact,Camlann Shire | T56: LC,Tamar Pact,Camlann Shire | U56: LC,Tamar Pact,Camlann Shire | V56: LC,Tamar Pact,Camlann Shire | W56: LC,Tamar Pact,Camlann Shire | X56: DC,Benjamin Military District,Dehgolan Prefecture | Y56: DC,Rasalhague Military District,Rubigen Prefecture | Z56: LC,Tamar Pact,Tamar Domains | AA56: FR,Skandia Province | AB56: FR,Skandia Province | AC56: FR,Skandia Province | AD56: FR,Skandia Province | AE56: FR,Skandia Province | AF56: FR,Skandia Province | AG56: FR | AH56: FR | AI56: FR | AJ56: FR | AK56: FR | AL56: FR | AM56: FR | AN56: FR | AO56: FR | AP56: FR | AQ56: GBD | AR56: GBD | AS56: GBD | AT56: GBD | AU56: GBD | AV56: RD,Region 3 | AW56: RD,Region 3 | AX56: RD,Region 3 | AY56: RD,Region 3 | AZ56: RD,Region 3
A57: 49 | B57: Al Jafr | D57: {=index(systems,match($A57,INDEX(systems,0,1),),3)} -> -412.829 | E57: {=index(systems,match($A57,INDEX(systems,0,1),),4)} -> 12.108 | F57: =IFERROR(__xludf.DUMMYFUNCTION("let(row, match($B57&if($C57<>"""","" [""&$C57&""]"",""""),index(nebulae,,2),0),join("","",iferror(round(index(nebulae,row,5)/2,3),1),iferror(round(index(nebulae,row,6)/2,3),1),0))"),"1,1,0") -> 1,1,0 | G57: https://www.sarna.net/wiki/Al_Jafr | H57: {=let(systemId,match(A57,index(systems,0,1),),refSystemId,match($H$1,index(systems,0,1),),x,index(systems,systemId,3),y,index(systems,systemId,4),refX,index(systems,refSystemId,3),refY,index(systems,refSystemId,4),round(sqrt((x-refX)^2+(y-refY)^2),3))} -> 413.007 | I57: U | J57: U | K57: U | L57: U | M57: U | N57: U | P57: LC,Protectorate of Donegal,Alarion Province | Q57: LC,Protectorate of Donegal,Alarion Province | R57: LC,Protectorate of Donegal,Alarion Province | S57: LC,Protectorate of Donegal,Alarion Province | T57: LC,Protectorate of Donegal,Alarion Province | U57: LC,Protectorate of Donegal,Alarion Province | V57: LC,Protectorate of Donegal,Alarion Province | W57: LC,Protectorate of Donegal,Alarion Province | X57: LC,Protectorate of Donegal,Alarion Province | Y57: LC,Protectorate of Donegal,Alarion Province | Z57: LC,Protectorate of Donegal,Alarion Province | AA57: FCL,Periphery March,Venaria Operational Area,Region 3 | AB57: FCL,Periphery March,Venaria Operational Area,Region 3 | AC57: FCL,Periphery March,Venaria Operational Area,Region 3 | AD57: FCL,Periphery March,Venaria Operational Area,Region 3 | AE57: FCL,Periphery March,Venaria Operational Area,Region 3 | AF57: FCL,Periphery March,Venaria Operational Area,Region 3 | AG57: FCL,Periphery March,Venaria Operational Area,Region 3 | AH57: LA,Periphery March,Venaria Operational Area,Region 3 | AI57: LA,Alarion Province,Timbuktu Theater | AJ57: LA,Alarion Province,Timbuktu Theater | AK57: LA,Alarion Province,Timbuktu Theater | AL57: LA,Alarion Province,Timbuktu Theater | AM57: LA,Alarion Province,Timbuktu Theater | AN57: LA,Alarion Province,Timbuktu Theater | AO57: LA,Alarion Province,Timbuktu Theater | AP57: LA,Alarion Province,Timbuktu Theater | AQ57: LA,Alarion Province,Timbuktu Theater,Buena Archonette | AR57: LA,Alarion Province,Timbuktu Theater,Buena Archonette | AS57: LA,Timbuktu Theater | AT57: LC,Timbuktu Theater | AU57: LC,Timbuktu Theater | AV57: LC,Timbuktu Theater | AW57: LC,Timbuktu Theater | AX57: LC,Florida Theater | AY57: LC,Florida Theater | AZ57: LC,Florida Theater
A58: 50 | B58: Al Jubaylah | D58: {=index(systems,match($A58,INDEX(systems,0,1),),3)} -> -183.766 | E58: {=index(systems,match($A58,INDEX(systems,0,1),),4)} -> -281.832 | F58: =IFERROR(__xludf.DUMMYFUNCTION("let(row, match($B58&if($C58<>"""","" [""&$C58&""]"",""""),index(nebulae,,2),0),join("","",iferror(round(index(nebulae,row,5)/2,3),1),iferror(round(index(nebulae,row,6)/2,3),1),0))"),"1,1,0") -> 1,1,0 | G58: https://www.sarna.net/wiki/Al_Jubaylah | H58: {=let(systemId,match(A58,index(systems,0,1),),refSystemId,match($H$1,index(systems,0,1),),x,index(systems,systemId,3),y,index(systems,systemId,4),refX,index(systems,refSystemId,3),refY,index(systems,refSystemId,4),round(sqrt((x-refX)^2+(y-refY)^2),3))} -> 336.451 | I58: U | N58: FWL,Principality of Regulus | O58: FWL,Principality of Regulus | P58: FWL | Q58: FWL | R58: FWL | S58: FWL | T58: FWL | U58: FWL | V58: FWL | W58: FWL | X58: FWL | Y58: FWL | Z58: FWL | AA58: FWL | AB58: FWL | AC58: FWL | AD58: FWL | AE58: FWL | AF58: FWL | AG58: FWL | AH58: FWL | AI58: FWL | AJ58: FWL | AK58: FWL | AL58: FWL | AM58: FWL | AN58: FWL | AO58: FWL | AP58: FWL | AQ58: FWL | AR58: FWL | AS58: I | AT58: I | AU58: I | AV58: I | AW58: I | AX58: I | AY58: I | AZ58: FWL
A59: 51 | B59: Al Na'ir | D59: {=index(systems,match($A59,INDEX(systems,0,1),),3)} -> 60.097 | E59: {=index(systems,match($A59,INDEX(systems,0,1),),4)} -> 31.239 | F59: =IFERROR(__xludf.DUMMYFUNCTION("let(row, match($B59&if($C59<>"""","" [""&$C59&""]"",""""),index(nebulae,,2),0),join("","",iferror(round(index(nebulae,row,5)/2,3),1),iferror(round(index(nebulae,row,6)/2,3),1),0))"),"1,1,0") -> 1,1,0 | G59: https://www.sarna.net/wiki/Al_Na'ir | H59: {=let(systemId,match(A59,index(systems,0,1),),refSystemId,match($H$1,index(systems,0,1),),x,index(systems,systemId,3),y,index(systems,systemId,4),refX,index(systems,refSystemId,3),refY,index(systems,refSystemId,4),round(sqrt((x-refX)^2+(y-refY)^2),3))} -> 67.731 | I59: U | J59: I | K59: I | N59: TH,Lockdale Province | O59: TH,Lockdale Province | P59: TH,Lockdale Province | Q59: TH,Lockdale Province | R59: AE,Lockdale Province | S59: TH,Lockdale Province | T59: DC,Benjamin Military District,Ashio Prefecture | U59: DC,Dieron Military District,Ashio Prefecture | V59: DC,Dieron Military District,Ashio Prefecture | W59: DC,Dieron Military District,Ashio Prefecture | X59: DC,Dieron Military District,Ashio Prefecture | Y59: DC,Dieron Military District,Al Na'ir Prefecture,Minor Capital | Z59: DC,Dieron Military District,Al Na'ir Prefecture,Minor Capital | AA59: DC,Dieron Military District,Al Na'ir Prefecture,Minor Capital | AB59: DC,Dieron Military District,Al Na'ir Prefecture,Minor Capital | AC59: DC,Dieron Military District,Al Na'ir Prefecture,Minor Capital | AD59: DC,Dieron Military District,Al Na'ir Prefecture,Minor Capital | AE59: DC,Dieron Military District,Al Na'ir Prefecture,Minor Capital | AF59: DC,Dieron Military District,Al Na'ir Prefecture,Minor Capital | AG59: DC,Dieron Military District,Al Na'ir Prefecture,Minor Capital | AH59: DC,Dieron Military District,Al Na'ir Prefecture,Minor Capital | AI59: DC,Dieron Military District,Al Na'ir Prefecture,Minor Capital | AJ59: DC,Dieron Military District,Al Na'ir Prefecture,Minor Capital | AK59: DC,Dieron Military District,Al Na'ir Prefecture,Minor Capital | AL59: DC,Dieron Military District,Al Na'ir Prefecture,Minor Capital | AM59: DC,Dieron Military District,Al Na'ir Prefecture,Minor Capital | AN59: DC,Dieron Military District,Al Na'ir Prefecture,Minor Capital | AO59: DC,Dieron Military District,Al Na'ir Prefecture,Minor Capital | AP59: DC,Dieron Military District,Al Na'ir Prefecture,Minor Capital | AQ59: WB | AR59: CoF | AS59: RS,Prefecture II,Minor Capital | AT59: RS,Prefecture II,Minor Capital | AU59: RS,Prefecture II,Minor Capital | AV59: RS,Prefecture II,Minor Capital | AW59: DC,Benjamin Military District,Algedi Prefecture | AX59: DC,Dieron Military District,Al Na'ir Prefecture,Minor Capital | AY59: DC,Dieron Military District,Al Na'ir Prefecture,Minor Capital | AZ59: DC,Dieron Military District,Al Na'ir Prefecture,Minor Capital
A60: 3147 | B60: Alamagordo | D60: {=index(systems,match($A60,INDEX(systems,0,1),),3)} -> -69.377 | E60: {=index(systems,match($A60,INDEX(systems,0,1),),4)} -> -370.671 | F60: =IFERROR(__xludf.DUMMYFUNCTION("let(row, match($B60&if($C60<>"""","" [""&$C60&""]"",""""),index(nebulae,,2),0),join("","",iferror(round(index(nebulae,row,5)/2,3),1),iferror(round(index(nebulae,row,6)/2,3),1),0))"),"1,1,0") -> 1,1,0 | G60: https://www.sarna.net/wiki/Alamagordo | H60: {=let(systemId,match(A60,index(systems,0,1),),refSystemId,match($H$1,index(systems,0,1),),x,index(systems,systemId,3),y,index(systems,systemId,4),refX,index(systems,refSystemId,3),refY,index(systems,refSystemId,4),round(sqrt((x-refX)^2+(y-refY)^2),3))} -> 377.108 | I60: U | J60: U | K60: U | L60: U | M60: U | N60: U | P60: U | Q60: U | R60: U | S60: U | T60: U | U60: U | V60: U | W60: U | X60: U | Y60: A | Z60: A | AA60: A | AB60: A | AC60: A | AD60: A | AE60: A | AF60: A | AG60: A | AH60: A | AI60: A | AJ60: A | AK60: A | AL60: A | AM60: A | AN60: A | AO60: A | AP60: A | AQ60: A | AR60: A | AS60: A | AT60: A | AU60: A | AV60: A | AW60: A | AX60: A | AY60: A | AZ60: A
A61: 52 | B61: Alarion | D61: {=index(systems,match($A61,INDEX(systems,0,1),),3)} -> -319.706 | E61: {=index(systems,match($A61,INDEX(systems,0,1),),4)} -> 138.602 | F61: =IFERROR(__xludf.DUMMYFUNCTION("let(row, match($B61&if($C61<>"""","" [""&$C61&""]"",""""),index(nebulae,,2),0),join("","",iferror(round(index(nebulae,row,5)/2,3),1),iferror(round(index(nebulae,row,6)/2,3),1),0))"),"1,1,0") -> 1,1,0 | G61: https://www.sarna.net/wiki/Alarion | H61: {=let(systemId,match(A61,index(systems,0,1),),refSystemId,match($H$1,index(systems,0,1),),x,index(systems,systemId,3),y,index(systems,systemId,4),refX,index(systems,refSystemId,3),refY,index(systems,refSystemId,4),round(sqrt((x-refX)^2+(y-refY)^2),3))} -> 348.457 | I61: U | J61: U | K61: U | L61: U | M61: LC,Protectorate of Donegal | N61: LC,Protectorate of Donegal,Alarion Province,Minor Capital | O61: LC,Protectorate of Donegal,Alarion Province,Minor Capital | P61: LC,Protectorate of Donegal,Alarion Province,Minor Capital | Q61: LC,Protectorate of Donegal,Alarion Province,Minor Capital | R61: LC,Protectorate of Donegal,Alarion Province,Minor Capital | S61: LC,Protectorate of Donegal,Alarion Province,Minor Capital | T61: LC,Protectorate of Donegal,Alarion Province,Minor Capital | U61: LC,Protectorate of Donegal,Alarion Province,Minor Capital | V61: LC,Protectorate of Donegal,Alarion Province,Minor Capital | W61: LC,Protectorate of Donegal,Alarion Province,Minor Capital | X61: LC,Protectorate of Donegal,Alarion Province,Minor Capital | Y61: LC,Protectorate of Donegal,Alarion Province,Minor Capital | Z61: LC,Protectorate of Donegal,Alarion Province,Minor Capital | AA61: FCL,Donegal March,Alarion Operational Area,Region 1,Major Capital | AB61: FCL,Donegal March,Alarion Operational Area,Region 1,Major Capital | AC61: FCL,Donegal March,Alarion Operational Area,Region 1,Major Capital | AD61: FCL,Donegal March,Alarion Operational Area,Region 1,Major Capital | AE61: FCL,Donegal March,Alarion Operational Area,Region 1,Major Capital | AF61: FCL,Donegal March,Alarion Operational Area,Region 1,Major Capital | AG61: FCL,Donegal March,Alarion Operational Area,Region 1,Major Capital | AH61: LA,Donegal March,Alarion Operational Area,Region 1,Major Capital | AI61: LA,Alarion Province,Major Capital | AJ61: LA,Alarion Province,Major Capital | AK61: LA,Alarion Province,Major Capital | AL61: LA,Alarion Province,Major Capital | AM61: LA,Alarion Province,Major Capital | AN61: LA,Alarion Province,Major Capital | AO61: LA,Alarion Province,Major Capital | AP61: LA,Alarion Province,Major Capital | AQ61: A | AR61: A | AS61: A | AT61: A | AU61: A | AV61: A | AW61: A | AX61: A | AY61: A | AZ61: A
A62: 53 | B62: Albalii | D62: {=index(systems,match($A62,INDEX(systems,0,1),),3)} -> 71.079 | E62: {=index(systems,match($A62,INDEX(systems,0,1),),4)} -> 78.532 | F62: =IFERROR(__xludf.DUMMYFUNCTION("let(row, match($B62&if($C62<>"""","" [""&$C62&""]"",""""),index(nebulae,,2),0),join("","",iferror(round(index(nebulae,row,5)/2,3),1),iferror(round(index(nebulae,row,6)/2,3),1),0))"),"1,1,0") -> 1,1,0 | G62: https://www.sarna.net/wiki/Albalii | H62: {=let(systemId,match(A62,index(systems,0,1),),refSystemId,match($H$1,index(systems,0,1),),x,index(systems,systemId,3),y,index(systems,systemId,4),refX,index(systems,refSystemId,3),refY,index(systems,refSystemId,4),round(sqrt((x-refX)^2+(y-refY)^2),3))} -> 105.922 | I62: U | J62: U | K62: U | N62: DC,Benjamin Military District,Ashio Prefecture | O62: DC,Benjamin Military District,Ashio Prefecture | P62: DC,Benjamin Military District,Ashio Prefecture | Q62: DC,Benjamin Military District,Ashio Prefecture | R62: DC,Benjamin Military District,Ashio Prefecture | S62: DC,Benjamin Military District,Ashio Prefecture | T62: DC,Benjamin Military District,Ashio Prefecture | U62: DC,Dieron Military District,Ashio Prefecture | V62: DC,Dieron Military District,Ashio Prefecture | W62: DC,Dieron Military District,Ashio Prefecture | X62: DC,Dieron Military District,Ashio Prefecture | Y62: DC,Dieron Military District,Ashio Prefecture | Z62: DC,Dieron Military District,Ashio Prefecture | AA62: DC,Dieron Military District,Ashio Prefecture | AB62: DC,Dieron Military District,Ashio Prefecture | AC62: DC,Dieron Military District,Ashio Prefecture | AD62: DC,Dieron Military District,Ashio Prefecture | AE62: DC,Dieron Military District,Ashio Prefecture | AF62: DC,Dieron Military District,Ashio Prefecture | AG62: DC,Dieron Military District,Ashio Prefecture | AH62: DC,Dieron Military District,Ashio Prefecture | AI62: DC,Dieron Military District,Ashio Prefecture | AJ62: DC,Dieron Military District,Ashio Prefecture | AK62: DC,Dieron Military District,Ashio Prefecture | AL62: DC,Dieron Military District,Ashio Prefecture | AM62: DC,Dieron Military District,Ashio Prefecture | AN62: DC,Dieron Military District,Ashio Prefecture | AO62: DC,Dieron Military District,Ashio Prefecture | AP62: DC,Dieron Military District,Ashio Prefecture | AQ62: AB | AR62: AB | AS62: RS,Prefecture II | AT62: RS,Prefecture II | AU62: RS,Prefecture II | AV62: RS,Prefecture II | AW62: DC,Benjamin Military District,Algedi Prefecture | AX62: DC,Dieron Military District,Ashio Prefecture | AY62: DC,Dieron Military District,Ashio Prefecture | AZ62: DC,Dieron Military District,Ashio Prefecture
A63: 3128 | B63: Albaracht | D63: {=index(systems,match($A63,INDEX(systems,0,1),),3)} -> 492.587 | E63: {=index(systems,match($A63,INDEX(systems,0,1),),4)} -> -458.157 | F63: =IFERROR(__xludf.DUMMYFUNCTION("let(row, match($B63&if($C63<>"""","" [""&$C63&""]"",""""),index(nebulae,,2),0),join("","",iferror(round(index(nebulae,row,5)/2,3),1),iferror(round(index(nebulae,row,6)/2,3),1),0))"),"1,1,0") -> 1,1,0 | G63: https://www.sarna.net/wiki/Albaracht | H63: {=let(systemId,match(A63,index(systems,0,1),),refSystemId,match($H$1,index(systems,0,1),),x,index(systems,systemId,3),y,index(systems,systemId,4),refX,index(systems,refSystemId,3),refY,index(systems,refSystemId,4),round(sqrt((x-refX)^2+(y-refY)^2),3))} -> 672.718 | I63: U | J63: U | K63: U | L63: U | M63: U | N63: U | P63: U | Q63: U | R63: U | S63: U | T63: U | U63: U | V63: U | W63: U | X63: U | Y63: U | Z63: U | AA63: U | AB63: U | AC63: U | AD63: U | AE63: U | AF63: U | AG63: U | AH63: U | AI63: U | AJ63: U | AK63: U | AL63: U | AM63: U | AN63: U | AO63: U | AP63: U | AQ63: U | AR63: U | AS63: U | AT63: U | AU63: U | AV63: CDP | AW63: CDP | AX63: CDP | AY63: CDP | AZ63: CDP
A64: 54 | B64: Albert Falls | D64: {=index(systems,match($A64,INDEX(systems,0,1),),3)} -> -259.83 | E64: {=index(systems,match($A64,INDEX(systems,0,1),),4)} -> -132.288 | F64: =IFERROR(__xludf.DUMMYFUNCTION("let(row, match($B64&if($C64<>"""","" [""&$C64&""]"",""""),index(nebulae,,2),0),join("","",iferror(round(index(nebulae,row,5)/2,3),1),iferror(round(index(nebulae,row,6)/2,3),1),0))"),"1,1,0") -> 1,1,0 | G64: https://www.sarna.net/wiki/Albert_Falls | H64: {=let(systemId,match(A64,index(systems,0,1),),refSystemId,match($H$1,index(systems,0,1),),x,index(systems,systemId,3),y,index(systems,systemId,4),refX,index(systems,refSystemId,3),refY,index(systems,refSystemId,4),round(sqrt((x-refX)^2+(y-refY)^2),3))} -> 291.568 | I64: U | N64: FWL,Duchy of Graham-Marik | O64: FWL,Duchy of Graham-Marik | P64: FWL,Duchy of Graham-Marik | Q64: FWL,Duchy of Graham-Marik | R64: FWL,Duchy of Graham-Marik | S64: FWL,Duchy of Graham-Marik | T64: FWL,Duchy of Graham-Marik | U64: FWL,Duchy of Graham-Marik | V64: FWL,Duchy of Graham-Marik | W64: FWL,Duchy of Graham-Marik | X64: FWL,Duchy of Graham-Marik | Y64: FWL | Z64: FWL | AA64: FWL | AB64: FWL | AC64: FWL | AD64: FWL | AE64: FWL | AF64: FWL | AG64: FWL | AH64: FWL | AI64: FWL | AJ64: FWL | AK64: FWL | AL64: FWL | AM64: FWL | AN64: FWL | AO64: FWL | AP64: FWL | AQ64: FWL | AR64: FWL | AS64: I | AT64: I | AU64: I | AV64: I | AW64: I | AX64: FWL | AY64: FWL | AZ64: FWL
A65: 2882 | B65: Albiero | D65: {=index(systems,match($A65,INDEX(systems,0,1),),3)} -> 150.439 | E65: {=index(systems,match($A65,INDEX(systems,0,1),),4)} -> 356.731 | F65: =IFERROR(__xludf.DUMMYFUNCTION("let(row, match($B65&if($C65<>"""","" [""&$C65&""]"",""""),index(nebulae,,2),0),join("","",iferror(round(index(nebulae,row,5)/2,3),1),iferror(round(index(nebulae,row,6)/2,3),1),0))"),"1,1,0") -> 1,1,0 | G65: https://www.sarna.net/wiki/Albiero | H65: {=let(systemId,match(A65,index(systems,0,1),),refSystemId,match($H$1,index(systems,0,1),),x,index(systems,systemId,3),y,index(systems,systemId,4),refX,index(systems,refSystemId,3),refY,index(systems,refSystemId,4),round(sqrt((x-refX)^2+(y-refY)^2),3))} -> 387.155 | I65: U | J65: U | K65: U | L65: U | M65: U | N65: U | P65: DC,Pesht Military District,Coudoux Prefecture | Q65: DC,Pesht Military District,Coudoux Prefecture | R65: DC,Pesht Military District,Coudoux Prefecture | S65: DC,Pesht Military District,Coudoux Prefecture | T65: DC,Pesht Military District,Coudoux Prefecture | U65: DC,Pesht Military District,Coudoux Prefecture | V65: DC,Pesht Military District,Coudoux Prefecture | W65: DC,Pesht Military District,Coudoux Prefecture | X65: DC,Pesht Military District,Coudoux Prefecture | Y65: DC,Pesht Military District,Albiero Prefecture,Minor Capital | Z65: DC,Pesht Military District,Albiero Prefecture,Minor Capital | AA65: DC,Pesht Military District,Albiero Prefecture,Minor Capital | AB65: DC,Pesht Military District,Albiero Prefecture,Minor Capital | AC65: DC,Pesht Military District,Albiero Prefecture,Minor Capital | AD65: DC,Pesht Military District,Albiero Prefecture,Minor Capital | AE65: CSJ | AF65: CSJ | AG65: CSJ | AH65: CSJ | AI65: CSJ | AJ65: CSJ | AK65: CSJ | AL65: CSJ | AM65: DC,Pesht Military District,Lonaconing Prefecture | AN65: DC,Pesht Military District,Albiero Prefecture,Minor Capital | AO65: DC,Pesht Military District,Albiero Prefecture,Minor Capital | AP65: DC,Pesht Military District,Albiero Prefecture,Minor Capital | AQ65: DC,Pesht Military District,Albiero Prefecture,Minor Capital | AR65: DC,Pesht Military District,Albiero Prefecture,Minor Capital | AS65: DC,Pesht Military District,Albiero Prefecture,Minor Capital | AT65: DC,Pesht Military District,Albiero Prefecture,Minor Capital | AU65: DC,Pesht Military District,Albiero Prefecture,Minor Capital | AV65: DC,Pesht Military District,Albiero Prefecture,Minor Capital | AW65: DC,Pesht Military District,Albiero Prefecture,Minor Capital | AX65: DC,Pesht Military District,Albiero Prefecture,Minor Capital | AY65: DC,Pesht Military District,Albiero Prefecture,Minor Capital | AZ65: DC,Pesht Military District,Albiero Prefecture,Minor Capital
A66: 55 | B66: Albion | C66: LC | D66: {=index(systems,match($A66,INDEX(systems,0,1),),3)} -> -284.426 | E66: {=index(systems,match($A66,INDEX(systems,0,1),),4)} -> 143.518 | F66: =IFERROR(__xludf.DUMMYFUNCTION("let(row, match($B66&if($C66<>"""","" [""&$C66&""]"",""""),index(nebulae,,2),0),join("","",iferror(round(index(nebulae,row,5)/2,3),1),iferror(round(index(nebulae,row,6)/2,3),1),0))"),"1,1,0") -> 1,1,0 | G66: https://www.sarna.net/wiki/Albion_(LC) | H66: {=let(systemId,match(A66,index(systems,0,1),),refSystemId,match($H$1,index(systems,0,1),),x,index(systems,systemId,3),y,index(systems,systemId,4),refX,index(systems,refSystemId,3),refY,index(systems,refSystemId,4),round(sqrt((x-refX)^2+(y-refY)^2),3))} -> 318.584 | I66: U | J66: U | K66: U | L66: U | M66: U | N66: U | P66: LC,Protectorate of Donegal,Alarion Province | Q66: LC,Protectorate of Donegal,Alarion Province | R66: LC,Protectorate of Donegal,Alarion Province | S66: LC,Protectorate of Donegal,Alarion Province | T66: LC,Protectorate of Donegal,Alarion Province | U66: LC,Protectorate of Donegal,Alarion Province | V66: LC,Protectorate of Donegal,Alarion Province | W66: LC,Protectorate of Donegal,Alarion Province | X66: LC,Protectorate of Donegal,Alarion Province | Y66: A | Z66: A | AA66: A | AB66: A | AC66: A | AD66: A | AE66: A | AF66: A | AG66: A | AH66: A | AI66: A | AJ66: A | AK66: A | AL66: A | AM66: A | AN66: A | AO66: A | AP66: A | AQ66: A | AR66: A | AS66: A | AT66: A | AU66: A | AV66: A | AW66: A | AX66: A | AY66: A | AZ66: A
A67: 2929 | B67: Albion | C67: C | D67: {=index(systems,match($A67,INDEX(systems,0,1),),3)} -> -50.167 | E67: {=index(systems,match($A67,INDEX(systems,0,1),),4)} -> 1792.145 | F67: =IFERROR(__xludf.DUMMYFUNCTION("let(row, match($B67&if($C67<>"""","" [""&$C67&""]"",""""),index(nebulae,,2),0),join("","",iferror(round(index(nebulae,row,5)/2,3),1),iferror(round(index(nebulae,row,6)/2,3),1),0))"),"1,1,0") -> 1,1,0 | G67: https://www.sarna.net/wiki/Albion_(Clan_System) | H67: {=let(systemId,match(A67,index(systems,0,1),),refSystemId,match($H$1,index(systems,0,1),),x,index(systems,systemId,3),y,index(systems,systemId,4),refX,index(systems,refSystemId,3),refY,index(systems,refSystemId,4),round(sqrt((x-refX)^2+(y-refY)^2),3))} -> 1792.847 | P67: U | Q67: U | R67: U | S67: U | T67: U | U67: CBR,Faction Capital | V67: CBR,Faction Capital | W67: CBR,Faction Capital | X67: CBR,Faction Capital | Y67: CBR,Faction Capital | Z67: CBR,Faction Capital | AA67: CBR,Faction Capital | AB67: CBR,Faction Capital | AC67: CBR,Faction Capital | AD67: CBR,Faction Capital | AE67: CBR,Faction Capital | AF67: CBR,Faction Capital | AG67: CBR,Faction Capital | AH67: CBR,Faction Capital | AI67: CBR,Faction Capital | AJ67: CSA | AK67: CSA | AL67: CSA | AM67: CSA | AN67: CSA | AO67: CSA | AP67: CSA | AQ67: C | AR67: C | AT67: A
A68: 3129 | B68: Ålborg | D68: {=index(systems,match($A68,INDEX(systems,0,1),),3)} -> 552.541 | E68: {=index(systems,match($A68,INDEX(systems,0,1),),4)} -> 499.056 | F68: =IFERROR(__xludf.DUMMYFUNCTION("let(row, match($B68&if($C68<>"""","" [""&$C68&""]"",""""),index(nebulae,,2),0),join("","",iferror(round(index(nebulae,row,5)/2,3),1),iferror(round(index(nebulae,row,6)/2,3),1),0))"),"1,1,0") -> 1,1,0 | G68: http://www.sarna.net/wiki/%C3%85lborg | H68: {=let(systemId,match(A68,index(systems,0,1),),refSystemId,match($H$1,index(systems,0,1),),x,index(systems,systemId,3),y,index(systems,systemId,4),refX,index(systems,refSystemId,3),refY,index(systems,refSystemId,4),round(sqrt((x-refX)^2+(y-refY)^2),3))} -> 744.553 | I68: U | J68: U | K68: U | L68: U | M68: U | N68: JF | O68: JF | P68: JF | Q68: JF | R68: JF | S68: JF | T68: JF | U68: JF | V68: JF | W68: JF | X68: JF | Y68: JF | Z68: JF | AA68: JF | AB68: JF | AC68: JF | AD68: JF | AE68: JF | AF68: JF | AG68: JF | AH68: JF | AI68: JF | AJ68: JF | AK68: JF | AL68: JF | AM68: JF | AN68: JF | AO68: JF | AP68: JF | AQ68: JF | AR68: JF | AS68: JF | AT68: JF | AU68: JF | AV68: JF | AW68: JF | AX68: JF | AY68: JF | AZ68: JF
A69: 56 | B69: Alchiba | D69: {=index(systems,match($A69,INDEX(systems,0,1),),3)} -> -67.732 | E69: {=index(systems,match($A69,INDEX(systems,0,1),),4)} -> 1.767 | F69: =IFERROR(__xludf.DUMMYFUNCTION("let(row, match($B69&if($C69<>"""","" [""&$C69&""]"",""""),index(nebulae,,2),0),join("","",iferror(round(index(nebulae,row,5)/2,3),1),iferror(round(index(nebulae,row,6)/2,3),1),0))"),"1,1,0") -> 1,1,0 | G69: https://www.sarna.net/wiki/Alchiba | H69: {=let(systemId,match(A69,index(systems,0,1),),refSystemId,match($H$1,index(systems,0,1),),x,index(systems,systemId,3),y,index(systems,systemId,4),refX,index(systems,refSystemId,3),refY,index(systems,refSystemId,4),round(sqrt((x-refX)^2+(y-refY)^2),3))} -> 67.755 | I69: I | J69: I | K69: I | L69: I | N69: LC,Federation of Skye,Isle of Skye | O69: LC,Federation of Skye,Isle of Skye | P69: LC,Federation of Skye,Isle of Skye | Q69: LC,Federation of Skye,Isle of Skye | R69: AE,Tyrfing Province | S69: TH,Tyrfing Province | T69: LC,Federation of Skye,Isle of Skye | U69: LC,Federation of Skye,Isle of Skye | V69: LC,Federation of Skye,Isle of Skye | W69: LC,Federation of Skye,Isle of Skye | X69: LC,Federation of Skye,Isle of Skye | Y69: LC,Federation of Skye,Isle of Skye | Z69: LC,Federation of Skye,Isle of Skye | AA69: FCL,Skye March,Alcor Operational Area,Region 3 | AB69: FCL,Skye March,Alcor Operational Area,Region 3 | AC69: FCL,Skye March,Alcor Operational Area,Region 3 | AD69: FCL,Skye March,Alcor Operational Area,Region 3 | AE69: FCL,Skye March,Alcor Operational Area,Region 3 | AF69: FCL,Skye March,Alcor Operational Area,Region 3 | AG69: FCL,Skye March,Alcor Operational Area,Region 3 | AH69: LA,Skye March,Alcor Operational Area,Region 3 | AI69: LA,Skye Province,Freedom Theater | AJ69: LA,Skye Province,Freedom Theater | AK69: LA,Skye Province,Freedom Theater | AL69: LA,Skye Province,Freedom Theater | AM69: LA,Skye Province,Freedom Theater | AN69: LA,Skye Province,Freedom Theater | AO69: LA,Skye Province,Freedom Theater | AP69: FWL | AQ69: LA,Skye Province,Freedom Theater | AR69: LA,Skye Province,Freedom Theater | AS69: RS,Prefecture VIII | AT69: RS,Prefecture VIII | AU69: RS,Prefecture VIII | AV69: RS,Prefecture VIII | AW69: I | AX69: WE | AY69: WE | AZ69: WE
A70: 57 | B70: Alcor | D70: {=index(systems,match($A70,INDEX(systems,0,1),),3)} -> -74.708 | E70: {=index(systems,match($A70,INDEX(systems,0,1),),4)} -> 28.904 | F70: =IFERROR(__xludf.DUMMYFUNCTION("let(row, match($B70&if($C70<>"""","" [""&$C70&""]"",""""),index(nebulae,,2),0),join("","",iferror(round(index(nebulae,row,5)/2,3),1),iferror(round(index(nebulae,row,6)/2,3),1),0))"),"1,1,0") -> 1,1,0 | G70: https://www.sarna.net/wiki/Alcor | H70: {=let(systemId,match(A70,index(systems,0,1),),refSystemId,match($H$1,index(systems,0,1),),x,index(systems,systemId,3),y,index(systems,systemId,4),refX,index(systems,refSystemId,3),refY,index(systems,refSystemId,4),round(sqrt((x-refX)^2+(y-refY)^2),3))} -> 80.104 | I70: I | J70: I | L70: FoS | M70: LC,Federation of Skye | N70: LC,Federation of Skye,Isle of Skye | O70: LC,Federation of Skye,Isle of Skye | P70: LC,Federation of Skye,Isle of Skye | Q70: LC,Federation of Skye,Isle of Skye | R70: LC,Federation of Skye,Isle of Skye | S70: LC,Federation of Skye,Isle of Skye | T70: LC,Federation of Skye,Isle of Skye | U70: LC,Federation of Skye,Isle of Skye | V70: LC,Federation of Skye,Isle of Skye | W70: LC,Federation of Skye,Isle of Skye | X70: LC,Federation of Skye,Isle of Skye | Y70: LC,Federation of Skye,Isle of Skye | Z70: LC,Federation of Skye,Isle of Skye | AA70: FCL,Skye March,Alcor Operational Area,Region 2,Minor Capital | AB70: FCL,Skye March,Alcor Operational Area,Region 2,Minor Capital | AC70: FCL,Skye March,Alcor Operational Area,Region 2,Minor Capital | AD70: FCL,Skye March,Alcor Operational Area,Region 2,Minor Capital | AE70: FCL,Skye March,Alcor Operational Area,Region 2,Minor Capital | AF70: FCL,Skye March,Alcor Operational Area,Region 2,Minor Capital | AG70: FCL,Skye March,Alcor Operational Area,Region 2,Minor Capital | AH70: LA,Skye March,Alcor Operational Area,Region 2,Minor Capital | AI70: LA,Skye Province,Freedom Theater | AJ70: LA,Skye Province,Freedom Theater | AK70: LA,Skye Province,Freedom Theater | AL70: LA,Skye Province,Freedom Theater | AM70: LA,Skye Province,Freedom Theater | AN70: LA,Skye Province,Freedom Theater | AO70: LA,Skye Province,Freedom Theater | AP70: FWL | AQ70: LA,Skye Province,Freedom Theater | AR70: LA,Skye Province,Freedom Theater | AS70: RS,Prefecture VIII | AT70: RS,Prefecture VIII | AU70: RS,Prefecture VIII | AV70: RS,Prefecture VIII | AW70: I | AX70: GL | AY70: GL | AZ70: IoS
A71: 58 | B71: Alcyone | D71: {=index(systems,match($A71,INDEX(systems,0,1),),3)} -> 129.758 | E71: {=index(systems,match($A71,INDEX(systems,0,1),),4)} -> -197.583 | F71: =IFERROR(__xludf.DUMMYFUNCTION("let(row, match($B71&if($C71<>"""","" [""&$C71&""]"",""""),index(nebulae,,2),0),join("","",iferror(round(index(nebulae,row,5)/2,3),1),iferror(round(index(nebulae,row,6)/2,3),1),0))"),"1,1,0") -> 1,1,0 | G71: https://www.sarna.net/wiki/Alcyone | H71: {=let(systemId,match(A71,index(systems,0,1),),refSystemId,match($H$1,index(systems,0,1),),x,index(systems,systemId,3),y,index(systems,systemId,4),refX,index(systems,refSystemId,3),refY,index(systems,refSystemId,4),round(sqrt((x-refX)^2+(y-refY)^2),3))} -> 236.381 | J71: CCom | M71: SIML | N71: CC,St. Ives Commonality,Region 3 | O71: CC,St. Ives Commonality,Region 3 | P71: CC,St. Ives Commonality,Region 3 | Q71: CC,St. Ives Commonality,Region 3 | R71: CC,St. Ives Commonality,Region 3 | S71: CC,St. Ives Commonality,Region 3 | T71: CC,St. Ives Commonality,Region 3 | U71: CC,St. Ives Commonality,Region 3 | V71: CC,St. Ives Commonality,Region 3 | W71: CC,St. Ives Commonality,Region 3 | X71: FS,Capellan March,Kathil Operational Area,Region 3 | Y71: FS,Capellan March,Kathil Operational Area,Alcyone PDZ | Z71: FS,Capellan March,Kathil Operational Area,Alcyone PDZ | AA71: FCF,Capellan March,Kathil Operational Area,Alcyone PDZ | AB71: FCF,Capellan March,Kathil Operational Area,Alcyone PDZ | AC71: FCF,Capellan March,Kathil Operational Area,Alcyone PDZ | AD71: FCF,Capellan March,Kathil Operational Area,Alcyone PDZ | AE71: FCF,Capellan March,Kathil Operational Area,Alcyone PDZ | AF71: FCF,Capellan March,Kathil Operational Area,Alcyone PDZ | AG71: FCF,Capellan March,Kathil Operational Area,Alcyone PDZ | AH71: FCF,Capellan March,Kathil Operational Area,Alcyone PDZ | AI71: FCF,Capellan March,Kathil Operational Area,Alcyone PDZ | AJ71: FCF,Capellan March,Kathil Operational Area,Alcyone PDZ | AK71: FCF,Capellan March,Kathil Operational Area,Alcyone PDZ | AL71: FCF,Capellan March,Kathil Operational Area,Alcyone PDZ | AM71: FCF,Capellan March,Kathil Operational Area,Alcyone PDZ | AN71: FCF,Capellan March,Kathil Operational Area,Alcyone PDZ | AO71: FS,Capellan March,Kathil Operational Area,Alcyone PDZ | AP71: FS,Capellan March,Kathil Operational Area,Alcyone PDZ | AQ71: FS,Capellan March,Kathil Operational Area,Alcyone PDZ | AR71: FS,Capellan March,Kathil Operational Area,Alcyone PDZ | AS71: FS,Capellan March,Kathil Operational Area,Alcyone PDZ | AT71: FS,Capellan March,Kathil Operational Area,Alcyone PDZ | AU71: FS,Capellan March,Kathil Operational Area,Alcyone PDZ | AV71: FS,Capellan March,Kathil Operational Area,Alcyone PDZ | AW71: FS,Capellan March,Kathil Operational Area,Alcyone PDZ | AX71: FS,Capellan March,Kathil Operational Area,Alcyone PDZ | AY71: FS,Capellan March,Kathil Operational Area,Alcyone PDZ | AZ71: FS,Capellan March,Kathil Operational Area,Alcyone PDZ
A72: 59 | B72: Aldebaran | D72: {=index(systems,match($A72,INDEX(systems,0,1),),3)} -> 24.813 | E72: {=index(systems,match($A72,INDEX(systems,0,1),),4)} -> -64.414 | F72: =IFERROR(__xludf.DUMMYFUNCTION("let(row, match($B72&if($C72<>"""","" [""&$C72&""]"",""""),index(nebulae,,2),0),join("","",iferror(round(index(nebulae,row,5)/2,3),1),iferror(round(index(nebulae,row,6)/2,3),1),0))"),"1,1,0") -> 1,1,0 | G72: https://www.sarna.net/wiki/Aldebaran | H72: {=let(systemId,match(A72,index(systems,0,1),),refSystemId,match($H$1,index(systems,0,1),),x,index(systems,systemId,3),y,index(systems,systemId,4),refX,index(systems,refSystemId,3),refY,index(systems,refSystemId,4),round(sqrt((x-refX)^2+(y-refY)^2),3))} -> 69.028 | I72: I | J72: DL | K72: DL | L72: DL | M72: DL | N72: TH,Terra Firma Province | O72: TH,Terra Firma Province | P72: TH,Terra Firma Province | Q72: TH,Terra Firma Province | R72: AE,Terra Firma Province | S72: TH,Terra Firma Province | T72: CC,Tikonov Commonality,Region 2 | U72: CC,Tikonov Commonality,Region 6 | V72: CC,Tikonov Commonality,Region 6 | W72: CC,Tikonov Commonality,Region 6 | X72: CC,Tikonov Commonality,Region 6 | Y72: CC,Tikonov Commonality,Region 9 | Z72: LC,Sarna March,Tikonov Operational Area,Region 1 | AA72: FCL,Sarna March,Terra Firma Operational Area,Region 4 | AB72: FCL,Sarna March,Terra Firma Operational Area,Region 4 | AC72: FCL,Sarna March,Terra Firma Operational Area,Region 4 | AD72: FCL,Sarna March,Terra Firma Operational Area,Region 4 | AE72: FCL,Sarna March,Terra Firma Operational Area,Region 4 | AF72: FCL,Sarna March,Terra Firma Operational Area,Region 4 | AG72: FCL,Sarna March,Terra Firma Operational Area,Region 4 | AH72: I | AI72: I | AJ72: I | AK72: I | AL72: I | AM72: I | AN72: CC,Liao Commonality,Region 1 | AO72: CC,Liao Commonality,Region 1 | AP72: CC,Liao Commonality,Region 1 | AQ72: CC,Liao Commonality,Region 1 | AR72: CC,Liao Commonality,Region 1 | AS72: CC,Liao Commonality,Region 1 | AT72: RS,Prefecture VI | AU72: RS,Prefecture VI | AV72: RS,Prefecture VI | AW72: I | AX72: CC,Tikonov Commonality,Region 4 | AY72: CC,Tikonov Commonality,Region 7 | AZ72: CC,Tikonov Commonality,Region 7
A73: 60 | B73: Aldertaine | D73: {=index(systems,match($A73,INDEX(systems,0,1),),3)} -> 44.714 | E73: {=index(systems,match($A73,INDEX(systems,0,1),),4)} -> -191.043 | F73: =IFERROR(__xludf.DUMMYFUNCTION("let(row, match($B73&if($C73<>"""","" [""&$C73&""]"",""""),index(nebulae,,2),0),join("","",iferror(round(index(nebulae,row,5)/2,3),1),iferror(round(index(nebulae,row,6)/2,3),1),0))"),"1,1,0") -> 1,1,0 | G73: https://www.sarna.net/wiki/Aldertaine | H73: {=let(systemId,match(A73,index(systems,0,1),),refSystemId,match($H$1,index(systems,0,1),),x,index(systems,systemId,3),y,index(systems,systemId,4),refX,index(systems,refSystemId,3),refY,index(systems,refSystemId,4),round(sqrt((x-refX)^2+(y-refY)^2),3))} -> 196.206 | I73: I | M73: CCom | N73: CC,Capella Commonality,Region 2 | O73: CC,Capella Commonality,Region 2 | P73: CC,Capella Commonality,Region 2 | Q73: CC,Capella Commonality,Region 2 | R73: CC,Capella Commonality,Region 2 | S73: CC,Capella Commonality,Region 2 | T73: CC,Capella Commonality,Region 2 | U73: CC,Capella Commonality,Region 2 | V73: CC,Capella Commonality,Region 2 | W73: CC,Capella Commonality,Region 2 | X73: CC,Capella Commonality,Region 2 | Y73: CC,Capella Commonality,Region 2 | Z73: CC,Capella Commonality,Region 2 | AA73: CC,Capella Commonality,Region 2 | AB73: CC,Capella Commonality,Region 2 | AC73: CC,Capella Commonality,Region 2 | AD73: CC,Capella Commonality,Region 2 | AE73: CC,Capella Commonality,Region 2 | AF73: CC,Capella Commonality,Region 2 | AG73: CC,Capella Commonality,Region 2 | AH73: CC,Capella Commonality,Region 2 | AI73: CC,Capella Commonality,Region 2 | AJ73: CC,Capella Commonality,Region 2 | AK73: CC,Capella Commonality,Region 2 | AL73: CC,Capella Commonality,Region 2 | AM73: CC,Capella Commonality,Region 2 | AN73: CC,Capella Commonality,Region 2 | AO73: CC,Capella Commonality,Region 2 | AP73: FS,Capellan March,Kathil Operational Area,Alcyone PDZ | AQ73: CC,Capella Commonality,Region 2 | AR73: CC,Capella Commonality,Region 2 | AS73: CC,Capella Commonality,Region 2 | AT73: CC,Capella Commonality,Region 2 | AU73: CC,Capella Commonality,Region 2 | AV73: CC,Capella Commonality,Region 2 | AW73: CC,Capella Commonality,Region 2 | AX73: CC,Capella Commonality,Region 2 | AY73: CC,Capella Commonality,Region 2 | AZ73: CC,Capella Commonality,Region 2
A74: 61 | B74: Aldrecht | D74: {=index(systems,match($A74,INDEX(systems,0,1),),3)} -> 150.833 | E74: {=index(systems,match($A74,INDEX(systems,0,1),),4)} -> 88.192 | F74: =IFERROR(__xludf.DUMMYFUNCTION("let(row, match($B74&if($C74<>"""","" [""&$C74&""]"",""""),index(nebulae,,2),0),join("","",iferror(round(index(nebulae,row,5)/2,3),1),iferror(round(index(nebulae,row,6)/2,3),1),0))"),"1,1,0") -> 1,1,0 | G74: https://www.sarna.net/wiki/Aldrecht | H74: {=let(systemId,match(A74,index(systems,0,1),),refSystemId,match($H$1,index(systems,0,1),),x,index(systems,systemId,3),y,index(systems,systemId,4),refX,index(systems,refSystemId,3),refY,index(systems,refSystemId,4),round(sqrt((x-refX)^2+(y-refY)^2),3))} -> 174.724 | I74: U | J74: U | K74: U | N74: DC,Benjamin Military District,Irurzun Prefecture | O74: DC,Benjamin Military District,Irurzun Prefecture | P74: DC,Benjamin Military District,Irurzun Prefecture | Q74: DC,Benjamin Military District,Irurzun Prefecture | R74: DC,Benjamin Military District,Irurzun Prefecture | S74: DC,Benjamin Military District,Irurzun Prefecture | T74: DC,Benjamin Military District,Irurzun Prefecture | U74: A | V74: A | W74: A | X74: A | Y74: A | Z74: A | AA74: A | AB74: A | AC74: A | AD74: A | AE74: A | AF74: A | AG74: A | AH74: A | AI74: A | AJ74: A | AK74: A | AL74: A | AM74: A | AN74: A | AO74: A | AP74: A | AQ74: A | AR74: A | AS74: A | AT74: A | AU74: A | AV74: A | AW74: A | AX74: A | AY74: A | AZ74: A
A75: 62 | B75: Alegro | D75: {=index(systems,match($A75,INDEX(systems,0,1),),3)} -> 429.841 | E75: {=index(systems,match($A75,INDEX(systems,0,1),),4)} -> 144.618 | F75: =IFERROR(__xludf.DUMMYFUNCTION("let(row, match($B75&if($C75<>"""","" [""&$C75&""]"",""""),index(nebulae,,2),0),join("","",iferror(round(index(nebulae,row,5)/2,3),1),iferror(round(index(nebulae,row,6)/2,3),1),0))"),"1,1,0") -> 1,1,0 | G75: https://www.sarna.net/wiki/Alegro | H75: {=let(systemId,match(A75,index(systems,0,1),),refSystemId,match($H$1,index(systems,0,1),),x,index(systems,systemId,3),y,index(systems,systemId,4),refX,index(systems,refSystemId,3),refY,index(systems,refSystemId,4),round(sqrt((x-refX)^2+(y-refY)^2),3))} -> 453.517 | I75: U | J75: U | K75: U | L75: U | M75: U | N75: U | P75: OA,Ramora Province | Q75: OA,Ramora Province | R75: OA,Ramora Province | S75: OA,Ramora Province | T75: OA,Ramora Province | U75: OA,Ramora Province | V75: OA,Ramora Province | W75: OA,Ramora Province | X75: OA,Ramora Province | Y75: OA,Ramora Province | Z75: OA,Ramora Province | AA75: OA,Ramora Province | AB75: OA,Ramora Province | AC75: OA,Ramora Province | AD75: OA,Ramora Province | AE75: OA,Ramora Province | AF75: OA,Ramora Province | AG75: OA,Ramora Province | AH75: OA,Ramora Province | AI75: OA,Ramora Province | AJ75: OA,Ramora Province | AK75: OA,Ramora Province | AL75: OA,Ramora Province | AM75: OA,Ramora Province | AN75: OA,Ramora Province | AO75: OA,Ramora Province | AP75: OA,Ramora Province | AQ75: OA,Ramora Province | AR75: OA,Ramora Province | AS75: OA,Ramora Province | AT75: RA | AU75: RA | AV75: RA | AW75: RA | AX75: RA | AY75: RA | AZ75: RA
A76: 63 | B76: Alekseyevka | D76: {=index(systems,match($A76,INDEX(systems,0,1),),3)} -> -403.504 | E76: {=index(systems,match($A76,INDEX(systems,0,1),),4)} -> 183.741 | F76: =IFERROR(__xludf.DUMMYFUNCTION("let(row, match($B76&if($C76<>"""","" [""&$C76&""]"",""""),index(nebulae,,2),0),join("","",iferror(round(index(nebulae,row,5)/2,3),1),iferror(round(index(nebulae,row,6)/2,3),1),0))"),"1,1,0") -> 1,1,0 | G76: https://www.sarna.net/wiki/Alekseyevka | H76: {=let(systemId,match(A76,index(systems,0,1),),refSystemId,match($H$1,index(systems,0,1),),x,index(systems,systemId,3),y,index(systems,systemId,4),refX,index(systems,refSystemId,3),refY,index(systems,refSystemId,4),round(sqrt((x-refX)^2+(y-refY)^2),3))} -> 443.369 | N76: LC,Protectorate of Donegal,Alarion Province | O76: LC,Protectorate of Donegal,Alarion Province | P76: LC,Protectorate of Donegal,Alarion Province | Q76: LC,Protectorate of Donegal,Alarion Province | R76: LC,Protectorate of Donegal,Alarion Province | S76: LC,Protectorate of Donegal,Alarion Province | T76: LC,Protectorate of Donegal,Alarion Province | U76: LC,Protectorate of Donegal,Alarion Province | V76: LC,Protectorate of Donegal,Alarion Province | W76: LC,Protectorate of Donegal,Alarion Province | X76: LC,Protectorate of Donegal,Alarion Province | Y76: LC,Protectorate of Donegal,Alarion Province | Z76: LC,Protectorate of Donegal,Alarion Province | AA76: FCL,Periphery March,Venaria Operational Area,Region 1 | AB76: FCL,Periphery March,Venaria Operational Area,Region 1 | AC76: FCL,Periphery March,Venaria Operational Area,Region 1 | AD76: FCL,Periphery March,Venaria Operational Area,Region 1 | AE76: FCL,Periphery March,Venaria Operational Area,Region 1 | AF76: FCL,Periphery March,Venaria Operational Area,Region 1 | AG76: FCL,Periphery March,Venaria Operational Area,Region 1 | AH76: LA,Periphery March,Venaria Operational Area,Region 1 | AI76: LA,Alarion Province,Timbuktu Theater | AJ76: LA,Alarion Province,Timbuktu Theater | AK76: LA,Alarion Province,Timbuktu Theater | AL76: LA,Alarion Province,Timbuktu Theater | AM76: LA,Alarion Province,Timbuktu Theater | AN76: LA,Alarion Province,Timbuktu Theater | AO76: LA,Alarion Province,Timbuktu Theater | AP76: LA,Alarion Province,Timbuktu Theater | AQ76: LA,Alarion Province,Timbuktu Theater | AR76: LA,Alarion Province,Timbuktu Theater | AS76: LA,Timbuktu Theater | AT76: LC,Timbuktu Theater | AU76: LC,Timbuktu Theater | AV76: LC,Timbuktu Theater | AW76: LC,Timbuktu Theater | AX76: LC,Florida Theater | AY76: LC,Florida Theater | AZ76: LC,Florida Theater
A77: 64 | B77: Alexandria | C77: CC | D77: {=index(systems,match($A77,INDEX(systems,0,1),),3)} -> 110.827 | E77: {=index(systems,match($A77,INDEX(systems,0,1),),4)} -> -356.104 | F77: =IFERROR(__xludf.DUMMYFUNCTION("let(row, match($B77&if($C77<>"""","" [""&$C77&""]"",""""),index(nebulae,,2),0),join("","",iferror(round(index(nebulae,row,5)/2,3),1),iferror(round(index(nebulae,row,6)/2,3),1),0))"),"1,1,0") -> 1,1,0 | G77: https://www.sarna.net/wiki/Alexandria_(CC) | H77: {=let(systemId,match(A77,index(systems,0,1),),refSystemId,match($H$1,index(systems,0,1),),x,index(systems,systemId,3),y,index(systems,systemId,4),refX,index(systems,refSystemId,3),refY,index(systems,refSystemId,4),round(sqrt((x-refX)^2+(y-refY)^2),3))} -> 372.951 | M77: I | N77: CC,Sian Commonality,Region 11 | O77: CC,Sian Commonality,Region 11 | P77: CC,Sian Commonality,Region 11 | Q77: CC,Sian Commonality,Region 11 | R77: CC,Sian Commonality,Region 11 | S77: CC,Sian Commonality,Region 11 | T77: CC,Sian Commonality,Region 11 | U77: CC,Sian Commonality,Region 11 | V77: CC,Sian Commonality,Region 11 | W77: CC,Sian Commonality,Region 11 | X77: CC,Sian Commonality,Region 11 | Y77: A | Z77: A | AA77: A | AB77: A | AC77: A | AD77: A | AE77: A | AF77: A | AG77: A | AH77: A | AI77: A | AJ77: A | AK77: A | AL77: A | AM77: A | AN77: A | AO77: A | AP77: A | AQ77: A | AR77: A | AS77: A | AT77: A | AU77: A | AV77: A | AW77: A | AX77: A | AY77: A | AZ77: A
A78: 65 | B78: Alexandria | C78: LC | D78: {=index(systems,match($A78,INDEX(systems,0,1),),3)} -> -57.639 | E78: {=index(systems,match($A78,INDEX(systems,0,1),),4)} -> 115.993 | F78: =IFERROR(__xludf.DUMMYFUNCTION("let(row, match($B78&if($C78<>"""","" [""&$C78&""]"",""""),index(nebulae,,2),0),join("","",iferror(round(index(nebulae,row,5)/2,3),1),iferror(round(index(nebulae,row,6)/2,3),1),0))"),"1,1,0") -> 1,1,0 | G78: https://www.sarna.net/wiki/Alexandria_(LC) | H78: {=let(systemId,match(A78,index(systems,0,1),),refSystemId,match($H$1,index(systems,0,1),),x,index(systems,systemId,3),y,index(systems,systemId,4),refX,index(systems,refSystemId,3),refY,index(systems,refSystemId,4),round(sqrt((x-refX)^2+(y-refY)^2),3))} -> 129.525 | I78: I | K78: FoS | L78: FoS | M78: LC,Federation of Skye | N78: LC,Federation of Skye,Virginia Shire,Minor Capital | O78: LC,Federation of Skye,Virginia Shire,Minor Capital | P78: LC,Federation of Skye,Virginia Shire,Minor Capital | Q78: LC,Federation of Skye,Virginia Shire,Minor Capital | R78: LC,Federation of Skye,Virginia Shire,Minor Capital | S78: LC,Federation of Skye,Virginia Shire,Minor Capital | T78: LC,Federation of Skye,Virginia Shire,Minor Capital | U78: LC,Federation of Skye,Virginia Shire,Minor Capital | V78: LC,Federation of Skye,Virginia Shire,Minor Capital | W78: LC,Federation of Skye,Virginia Shire,Minor Capital | X78: LC,Federation of Skye,Virginia Shire,Minor Capital | Y78: LC,Federation of Skye,Virginia Shire,Minor Capital | Z78: LC,Federation of Skye,Virginia Shire | AA78: FCL,Skye March,Ryde Operational Area,Region 2 | AB78: FCL,Skye March,Ryde Operational Area,Region 2 | AC78: FCL,Skye March,Ryde Operational Area,Region 2 | AD78: FCL,Skye March,Ryde Operational Area,Region 2 | AE78: FCL,Skye March,Ryde Operational Area,Region 2 | AF78: FCL,Skye March,Ryde Operational Area,Region 2 | AG78: FCL,Skye March,Ryde Operational Area,Region 2 | AH78: LA,Skye March,Ryde Operational Area,Region 2 | AI78: LA,Skye Province,Freedom Theater | AJ78: LA,Skye Province,Freedom Theater | AK78: LA,Skye Province,Freedom Theater | AL78: LA,Skye Province,Freedom Theater | AM78: LA,Skye Province,Freedom Theater | AN78: LA,Skye Province,Freedom Theater,Minor Capital | AO78: LA,Skye Province,Freedom Theater | AP78: LA,Skye Province,Freedom Theater | AQ78: LA,Skye Province,Freedom Theater | AR78: LA,Skye Province,Freedom Theater | AS78: LA,Donegal Province | AT78: LC,Donegal Province | AU78: LC,Donegal Province | AV78: LC,Donegal Province | AW78: LC,Donegal Province | AX78: CJF | AY78: CJF | AZ78: I
A79: 66 | B79: Alfirk | D79: {=index(systems,match($A79,INDEX(systems,0,1),),3)} -> 588.602 | E79: {=index(systems,match($A79,INDEX(systems,0,1),),4)} -> 454.172 | F79: =IFERROR(__xludf.DUMMYFUNCTION("let(row, match($B79&if($C79<>"""","" [""&$C79&""]"",""""),index(nebulae,,2),0),join("","",iferror(round(index(nebulae,row,5)/2,3),1),iferror(round(index(nebulae,row,6)/2,3),1),0))"),"1,1,0") -> 1,1,0 | G79: https://www.sarna.net/wiki/Alfirk | H79: {=let(systemId,match(A79,index(systems,0,1),),refSystemId,match($H$1,index(systems,0,1),),x,index(systems,systemId,3),y,index(systems,systemId,4),refX,index(systems,refSystemId,3),refY,index(systems,refSystemId,4),round(sqrt((x-refX)^2+(y-refY)^2),3))} -> 743.454 | I79: I | J79: I | K79: I | L79: I | M79: I | N79: I | O79: I | P79: I | Q79: I | R79: I | S79: I | T79: I | U79: I | V79: I | W79: I | X79: I | Y79: I | Z79: I(H) | AA79: I | AB79: I | AC79: I | AD79: I | AE79: I | AF79: I | AG79: I | AH79: I | AI79: I | AJ79: I | AK79: I | AL79: I | AM79: I | AN79: I | AO79: I | AP79: I | AQ79: I | AR79: I | AS79: I | AT79: I | AU79: I | AV79: I | AW79: I | AX79: I | AY79: I | AZ79: I
A80: 67 | B80: Algate | D80: {=index(systems,match($A80,INDEX(systems,0,1),),3)} -> 323.626 | E80: {=index(systems,match($A80,INDEX(systems,0,1),),4)} -> 378.128 | F80: =IFERROR(__xludf.DUMMYFUNCTION("let(row, match($B80&if($C80<>"""","" [""&$C80&""]"",""""),index(nebulae,,2),0),join("","",iferror(round(index(nebulae,row,5)/2,3),1),iferror(round(index(nebulae,row,6)/2,3),1),0))"),"1,1,0") -> 1,1,0 | G80: https://www.sarna.net/wiki/Algate | H80: {=let(systemId,match(A80,index(systems,0,1),),refSystemId,match($H$1,index(systems,0,1),),x,index(systems,systemId,3),y,index(systems,systemId,4),refX,index(systems,refSystemId,3),refY,index(systems,refSystemId,4),round(sqrt((x-refX)^2+(y-refY)^2),3))} -> 497.709 | I80: U | J80: U | K80: U | N80: DC,Pesht Military District,Pusht-i-rud Prefecture | O80: DC,Pesht Military District,Pusht-i-rud Prefecture | P80: DC,Pesht Military District,Pusht-i-rud Prefecture | Q80: DC,Pesht Military District,Pusht-i-rud Prefecture | R80: DC,Pesht Military District,Pusht-i-rud Prefecture | S80: DC,Pesht Military District,Pusht-i-rud Prefecture | T80: DC,Pesht Military District,Pusht-i-rud Prefecture | U80: DC,Pesht Military District,Pusht-i-rud Prefecture | V80: DC,Pesht Military District,Pusht-i-rud Prefecture | W80: DC,Pesht Military District,Pusht-i-rud Prefecture | X80: DC,Pesht Military District,Pusht-i-rud Prefecture | Y80: DC,Pesht Military District,Qandahar Prefecture | Z80: DC,Pesht Military District,Qandahar Prefecture | AA80: DC,Pesht Military District,Qandahar Prefecture | AB80: DC,Pesht Military District,Qandahar Prefecture | AC80: DC,Pesht Military District,Qandahar Prefecture | AD80: DC,Pesht Military District,Qandahar Prefecture | AE80: DC,Pesht Military District,Qandahar Prefecture | AF80: DC,Pesht Military District,Qandahar Prefecture | AG80: DC,Pesht Military District,Qandahar Prefecture | AH80: DC,Pesht Military District,Qandahar Prefecture | AI80: DC,Pesht Military District,Qandahar Prefecture | AJ80: DC,Pesht Military District,Qandahar Prefecture | AK80: DC,Pesht Military District,Qandahar Prefecture | AL80: DC,Pesht Military District,Qandahar Prefecture | AM80: DC,Pesht Military District,Qandahar Prefecture | AN80: DC,Pesht Military District,Qandahar Prefecture | AO80: DC,Pesht Military District,Qandahar Prefecture | AP80: DC,Pesht Military District,Qandahar Prefecture | AQ80: DC,Pesht Military District,Qandahar Prefecture | AR80: DC,Pesht Military District,Qandahar Prefecture | AS80: DC,Pesht Military District,Qandahar Prefecture | AT80: DC,Pesht Military District,Qandahar Prefecture | AU80: DC,Pesht Military District,Qandahar Prefecture | AV80: DC,Pesht Military District,Qandahar Prefecture | AW80: DC,Pesht Military District,Qandahar Prefecture | AX80: DC,Pesht Military District,Qandahar Prefecture | AY80: DC,Pesht Military District,Qandahar Prefecture | AZ80: DC,Pesht Military District,Qandahar Prefecture
A81: 68 | B81: Algedi | D81: {=index(systems,match($A81,INDEX(systems,0,1),),3)} -> 66.07 | E81: {=index(systems,match($A81,INDEX(systems,0,1),),4)} -> 94.935 | F81: =IFERROR(__xludf.DUMMYFUNCTION("let(row, match($B81&if($C81<>"""","" [""&$C81&""]"",""""),index(nebulae,,2),0),join("","",iferror(round(index(nebulae,row,5)/2,3),1),iferror(round(index(nebulae,row,6)/2,3),1),0))"),"1,1,0") -> 1,1,0 | G81: https://www.sarna.net/wiki/Algedi | H81: {=let(systemId,match(A81,index(systems,0,1),),refSystemId,match($H$1,index(systems,0,1),),x,index(systems,systemId,3),y,index(systems,systemId,4),refX,index(systems,refSystemId,3),refY,index(systems,refSystemId,4),round(sqrt((x-refX)^2+(y-refY)^2),3))} -> 115.663 | K81: I | N81: DC,Benjamin Military District,Kuzuu Prefecture | O81: DC,Benjamin Military District,Kuzuu Prefecture | P81: DC,Benjamin Military District,Kuzuu Prefecture | Q81: DC,Benjamin Military District,Kuzuu Prefecture | R81: DC,Benjamin Military District,Kuzuu Prefecture | S81: DC,Benjamin Military District,Kuzuu Prefecture | T81: DC,Benjamin Military District,Kuzuu Prefecture | U81: DC,Dieron Military District,Kuzuu Prefecture | V81: DC,Dieron Military District,Kuzuu Prefecture | W81: DC,Dieron Military District,Kuzuu Prefecture | X81: DC,Dieron Military District,Kuzuu Prefecture | Y81: DC,Dieron Military District,Algedi Prefecture,Minor Capital | Z81: DC,Dieron Military District,Algedi Prefecture,Minor Capital | AA81: DC,Dieron Military District,Algedi Prefecture,Minor Capital | AB81: DC,Dieron Military District,Algedi Prefecture,Minor Capital | AC81: DC,Dieron Military District,Algedi Prefecture,Minor Capital | AD81: DC,Dieron Military District,Algedi Prefecture,Minor Capital | AE81: DC,Dieron Military District,Algedi Prefecture,Minor Capital | AF81: DC,Dieron Military District,Algedi Prefecture,Minor Capital | AG81: DC,Dieron Military District,Algedi Prefecture,Minor Capital | AH81: DC,Dieron Military District,Algedi Prefecture,Minor Capital | AI81: DC,Dieron Military District,Algedi Prefecture,Minor Capital | AJ81: DC,Dieron Military District,Algedi Prefecture,Minor Capital | AK81: DC,Dieron Military District,Algedi Prefecture,Minor Capital | AL81: DC,Dieron Military District,Algedi Prefecture,Minor Capital | AM81: DC,Dieron Military District,Algedi Prefecture,Minor Capital | AN81: DC,Dieron Military District,Algedi Prefecture,Minor Capital | AO81: DC,Dieron Military District,Algedi Prefecture,Minor Capital | AP81: DC,Dieron Military District,Algedi Prefecture,Minor Capital | AQ81: AB,Faction Capital | AR81: AB,Faction Capital | AS81: DC,Benjamin Military District,Benjamin Prefecture | AT81: DC,Benjamin Military District,Benjamin Prefecture | AU81: DC,Benjamin Military District,Benjamin Prefecture | AV81: DC,Benjamin Military District,Benjamin Prefecture,Minor Capital | AW81: DC,Benjamin Military District,Algedi Prefecture,Minor Capital | AX81: DC,Dieron Military District,Algedi Prefecture,Minor Capital | AY81: DC,Dieron Military District,Algedi Prefecture,Minor Capital | AZ81: DC,Dieron Military District,Algedi Prefecture,Minor Capital
